Workbook

Sheet Dashboard
A1: Technical Debt, Risk & Application Portfolio Simulator
A2: Manage technical debt, application risk, and portfolio disposition using the Gartner TIME model.
A3: Edit dropdown options and scoring weights on the Lists sheet. Weights ship at even defaults; calibrated weights are part of the full simulator. See the Instructions tab for how everything works.
A5: ACTIVE DEBT ITEMS | B5: OVERDUE ITEMS | E5: CRITICAL ACTIVE | F5: ACTIVE DIRECT COST
A6: =B37 -> 7 | B6: =B38 -> 6 | E6: =F36 -> 1 | F6: =B53 -> 0
A8: APPLICATIONS | B8: HIGH-RISK APPS | E8: ELIMINATE CANDIDATES | F8: TOTAL ANNUAL RUN COST
A9: =B57 -> 7 | B9: =F58 -> 2 | E9: =B61 -> 1 | F9: =B76 -> 0
A11: Application TIME Matrix (Business Value vs Technical Health)
A12: ="MIGRATE "&COUNTIFS('Application Portfolio'!$B$2:$B$1000,"<>",'Application Portfolio'!$AB$2:$AB$1000,"Migrate")&IF(COUNTIFS('Application Portfolio'!$B$2:$B$1000,"<>",'Application Portfolio'!$AB$2:$AB$1000,"Migrate")=1," app"," apps") -> MIGRATE 3 apps | E12: ="INVEST "&COUNTIFS('Application Portfolio'!$B$2:$B$1000,"<>",'Application Portfolio'!$AB$2:$AB$1000,"Invest")&IF(COUNTIFS('Application Portfolio'!$B$2:$B$1000,"<>",'Application Portfolio'!$AB$2:$AB$1000,"Invest")=1," app"," apps") -> INVEST 2 apps
A13: High business value, low technical health. Modernize or replatform. | E13: High business value, high technical health. Keep investing.
A14: {=IF(COUNTIFS('Application Portfolio'!$B$2:$B$1000,"<>",'Application Portfolio'!$AB$2:$AB$1000,"Migrate")=0,"None",_xlfn.TEXTJOIN(", ",TRUE(),IF(('Application Portfolio'!$AB$2:$AB$1000="Migrate")*('Application Portfolio'!$B$2:$B$1000<>""),'Application Portfolio'!$B$2:$B$1000,"")))} -> Customer Portal, Payment Processor, Financial Reconciliation | E14: {=IF(COUNTIFS('Application Portfolio'!$B$2:$B$1000,"<>",'Application Portfolio'!$AB$2:$AB$1000,"Invest")=0,"None",_xlfn.TEXTJOIN(", ",TRUE(),IF(('Application Portfolio'!$AB$2:$AB$1000="Invest")*('Application Portfolio'!$B$2:$B$1000<>""),'Application Portfolio'!$B$2:$B$1000,"")))} -> Order Management System, Partner API Gateway
A16: ="ELIMINATE "&COUNTIFS('Application Portfolio'!$B$2:$B$1000,"<>",'Application Portfolio'!$AB$2:$AB$1000,"Eliminate")&IF(COUNTIFS('Application Portfolio'!$B$2:$B$1000,"<>",'Application Portfolio'!$AB$2:$AB$1000,"Eliminate")=1," app"," apps") -> ELIMINATE 1 app | E16: ="TOLERATE "&COUNTIFS('Application Portfolio'!$B$2:$B$1000,"<>",'Application Portfolio'!$AB$2:$AB$1000,"Tolerate")&IF(COUNTIFS('Application Portfolio'!$B$2:$B$1000,"<>",'Application Portfolio'!$AB$2:$AB$1000,"Tolerate")=1," app"," apps") -> TOLERATE 1 app
A17: Low business value, low technical health. Retire or consolidate. | E17: Low business value, high technical health. Keep running, minimal spend.
A18: {=IF(COUNTIFS('Application Portfolio'!$B$2:$B$1000,"<>",'Application Portfolio'!$AB$2:$AB$1000,"Eliminate")=0,"None",_xlfn.TEXTJOIN(", ",TRUE(),IF(('Application Portfolio'!$AB$2:$AB$1000="Eliminate")*('Application Portfolio'!$B$2:$B$1000<>""),'Application Portfolio'!$B$2:$B$1000,"")))} -> Legacy CRM | E18: {=IF(COUNTIFS('Application Portfolio'!$B$2:$B$1000,"<>",'Application Portfolio'!$AB$2:$AB$1000,"Tolerate")=0,"None",_xlfn.TEXTJOIN(", ",TRUE(),IF(('Application Portfolio'!$AB$2:$AB$1000="Tolerate")*('Application Portfolio'!$B$2:$B$1000<>""),'Application Portfolio'!$B$2:$B$1000,"")))} -> Marketing Analytics
A35: Debt Backlog - At a Glance | E35: Debt - Active by Severity
A36: Total Items | B36: =COUNTA('Debt Backlog'!B2:B1000) -> 7 | E36: Critical Active | F36: =COUNTIFS('Debt Backlog'!B2:B1000,"<>",'Debt Backlog'!H2:H1000,"Critical",'Debt Backlog'!N2:N1000,"<>Done",'Debt Backlog'!N2:N1000,"<>Won't Fix",'Debt Backlog'!N2:N1000,"<>Duplicate") -> 1
A37: Active Items | B37: =COUNTIFS('Debt Backlog'!B2:B1000,"<>",'Debt Backlog'!N2:N1000,"<>Done",'Debt Backlog'!N2:N1000,"<>Won't Fix",'Debt Backlog'!N2:N1000,"<>Duplicate") -> 7 | E37: High Active | F37: =COUNTIFS('Debt Backlog'!B2:B1000,"<>",'Debt Backlog'!H2:H1000,"High",'Debt Backlog'!N2:N1000,"<>Done",'Debt Backlog'!N2:N1000,"<>Won't Fix",'Debt Backlog'!N2:N1000,"<>Duplicate") -> 3
A38: Overdue Items | B38: =COUNTIF('Debt Backlog'!AE2:AE1000,"Yes") -> 6 | E38: Medium Active | F38: =COUNTIFS('Debt Backlog'!B2:B1000,"<>",'Debt Backlog'!H2:H1000,"Medium",'Debt Backlog'!N2:N1000,"<>Done",'Debt Backlog'!N2:N1000,"<>Won't Fix",'Debt Backlog'!N2:N1000,"<>Duplicate") -> 2
A39: Done Items | B39: =COUNTIFS('Debt Backlog'!B2:B1000,"<>",'Debt Backlog'!N2:N1000,"Done") -> 0 | E39: Low Active | F39: =COUNTIFS('Debt Backlog'!B2:B1000,"<>",'Debt Backlog'!H2:H1000,"Low",'Debt Backlog'!N2:N1000,"<>Done",'Debt Backlog'!N2:N1000,"<>Won't Fix",'Debt Backlog'!N2:N1000,"<>Duplicate") -> 1
A41: Debt Status Breakdown | E41: Severity Breakdown (legend)
A42: Status | B42: Count | E42: Severity | F42: Count
A43: New | B43: =COUNTIFS('Debt Backlog'!B$2:B$1000,"<>",'Debt Backlog'!N$2:N$1000,A43) -> 2 | E43: Critical | F43: =COUNTIFS('Debt Backlog'!B$2:B$1000,"<>",'Debt Backlog'!H$2:H$1000,E43,'Debt Backlog'!N$2:N$1000,"<>Done",'Debt Backlog'!N$2:N$1000,"<>Won't Fix",'Debt Backlog'!N$2:N$1000,"<>Duplicate") -> 1
A44: Triaged | B44: =COUNTIFS('Debt Backlog'!B$2:B$1000,"<>",'Debt Backlog'!N$2:N$1000,A44) -> 1 | E44: High | F44: =COUNTIFS('Debt Backlog'!B$2:B$1000,"<>",'Debt Backlog'!H$2:H$1000,E44,'Debt Backlog'!N$2:N$1000,"<>Done",'Debt Backlog'!N$2:N$1000,"<>Won't Fix",'Debt Backlog'!N$2:N$1000,"<>Duplicate") -> 3
A45: Planned | B45: =COUNTIFS('Debt Backlog'!B$2:B$1000,"<>",'Debt Backlog'!N$2:N$1000,A45) -> 2 | E45: Medium | F45: =COUNTIFS('Debt Backlog'!B$2:B$1000,"<>",'Debt Backlog'!H$2:H$1000,E45,'Debt Backlog'!N$2:N$1000,"<>Done",'Debt Backlog'!N$2:N$1000,"<>Won't Fix",'Debt Backlog'!N$2:N$1000,"<>Duplicate") -> 2
A46: In Progress | B46: =COUNTIFS('Debt Backlog'!B$2:B$1000,"<>",'Debt Backlog'!N$2:N$1000,A46) -> 2 | E46: Low | F46: =COUNTIFS('Debt Backlog'!B$2:B$1000,"<>",'Debt Backlog'!H$2:H$1000,E46,'Debt Backlog'!N$2:N$1000,"<>Done",'Debt Backlog'!N$2:N$1000,"<>Won't Fix",'Debt Backlog'!N$2:N$1000,"<>Duplicate") -> 1
A47: Blocked | B47: =COUNTIFS('Debt Backlog'!B$2:B$1000,"<>",'Debt Backlog'!N$2:N$1000,A47) -> 0
A48: Done | B48: =COUNTIFS('Debt Backlog'!B$2:B$1000,"<>",'Debt Backlog'!N$2:N$1000,A48) -> 0
A49: Won't Fix | B49: =COUNTIFS('Debt Backlog'!B$2:B$1000,"<>",'Debt Backlog'!N$2:N$1000,A49) -> 0
A50: Duplicate | B50: =COUNTIFS('Debt Backlog'!B$2:B$1000,"<>",'Debt Backlog'!N$2:N$1000,A50) -> 0
A52: Debt Cost Summary | E52: Cost by Confidence
A53: Total Direct ($) | B53: =SUMIFS('Debt Backlog'!Y2:Y1000,'Debt Backlog'!B2:B1000,"<>",'Debt Backlog'!N2:N1000,"<>Done",'Debt Backlog'!N2:N1000,"<>Won't Fix",'Debt Backlog'!N2:N1000,"<>Duplicate") -> 0 | E53: High Confidence ($) | F53: =SUMIFS('Debt Backlog'!Y2:Y1000,'Debt Backlog'!B2:B1000,"<>",'Debt Backlog'!AB2:AB1000,"High",'Debt Backlog'!N2:N1000,"<>Done",'Debt Backlog'!N2:N1000,"<>Won't Fix",'Debt Backlog'!N2:N1000,"<>Duplicate") -> 0
A54: Total Annual Carry ($) | B54: =SUMIFS('Debt Backlog'!Z2:Z1000,'Debt Backlog'!B2:B1000,"<>",'Debt Backlog'!N2:N1000,"<>Done",'Debt Backlog'!N2:N1000,"<>Won't Fix",'Debt Backlog'!N2:N1000,"<>Duplicate") -> 0 | E54: Medium Confidence ($) | F54: =SUMIFS('Debt Backlog'!Y2:Y1000,'Debt Backlog'!B2:B1000,"<>",'Debt Backlog'!AB2:AB1000,"Medium",'Debt Backlog'!N2:N1000,"<>Done",'Debt Backlog'!N2:N1000,"<>Won't Fix",'Debt Backlog'!N2:N1000,"<>Duplicate") -> 0
A55: Total Contingent ($) | B55: =SUMIFS('Debt Backlog'!AA2:AA1000,'Debt Backlog'!B2:B1000,"<>",'Debt Backlog'!N2:N1000,"<>Done",'Debt Backlog'!N2:N1000,"<>Won't Fix",'Debt Backlog'!N2:N1000,"<>Duplicate") -> 0 | E55: Low Confidence ($) | F55: =SUMIFS('Debt Backlog'!Y2:Y1000,'Debt Backlog'!B2:B1000,"<>",'Debt Backlog'!AB2:AB1000,"Low",'Debt Backlog'!N2:N1000,"<>Done",'Debt Backlog'!N2:N1000,"<>Won't Fix",'Debt Backlog'!N2:N1000,"<>Duplicate") -> 0
A56: Application Portfolio (APM) - TIME Classification | E56: Portfolio Health Indicators
A57: Total Applications | B57: =COUNTA('Application Portfolio'!B2:B1000) -> 7 | E57: Average CPS | F57: =IFERROR(AVERAGE('Application Portfolio'!AA2:AA1000),"") -> -0.028571429
A58: INVEST | B58: =COUNTIFS('Application Portfolio'!B2:B1000,"<>",'Application Portfolio'!AB2:AB1000,"Invest") -> 2 | E58: High Risk Apps | F58: =COUNTIFS('Application Portfolio'!B2:B1000,"<>",'Application Portfolio'!O2:O1000,">="&Lists!$AG$4) -> 2
A59: TOLERATE | B59: =COUNTIFS('Application Portfolio'!B2:B1000,"<>",'Application Portfolio'!AB2:AB1000,"Tolerate") -> 1 | E59: High Business Value | F59: =COUNTIFS('Application Portfolio'!B2:B1000,"<>",'Application Portfolio'!N2:N1000,">="&Lists!$AG$2) -> 5
A60: MIGRATE | B60: =COUNTIFS('Application Portfolio'!B2:B1000,"<>",'Application Portfolio'!AB2:AB1000,"Migrate") -> 3 | E60: Low Technical Health | F60: =COUNTIFS('Application Portfolio'!B2:B1000,"<>",'Application Portfolio'!Z2:Z1000,"<"&Lists!$AG$3) -> 4
A61: ELIMINATE | B61: =COUNTIFS('Application Portfolio'!B2:B1000,"<>",'Application Portfolio'!AB2:AB1000,"Eliminate") -> 1 | E61: High Cost Apps | F61: =COUNTIFS('Application Portfolio'!B2:B1000,"<>",'Application Portfolio'!T2:T1000,">="&Lists!$AG$6) -> 3
A63: TIME Breakdown | E63: Risk Distribution
A64: TIME Quadrant | B64: Count | E64: Risk Score Range | F64: Count
A65: Invest | B65: =COUNTIFS('Application Portfolio'!B$2:B$1000,"<>",'Application Portfolio'!AB$2:AB$1000,A65) -> 2 | E65: ="High (>= "&TEXT(Lists!$AG$4,"0.0")&")" -> High (>= 3.5) | F65: =COUNTIFS('Application Portfolio'!B$2:B$1000,"<>",'Application Portfolio'!O$2:O$1000,">="&Lists!$AG$4) -> 2
A66: Tolerate | B66: =COUNTIFS('Application Portfolio'!B$2:B$1000,"<>",'Application Portfolio'!AB$2:AB$1000,A66) -> 1 | E66: ="Moderate ("&TEXT(Lists!$AG$5,"0.0")&" to <"&TEXT(Lists!$AG$4,"0.0")&")" -> Moderate (2.5 to <3.5) | F66: =COUNTIFS('Application Portfolio'!B$2:B$1000,"<>",'Application Portfolio'!O$2:O$1000,">="&Lists!$AG$5,'Application Portfolio'!O$2:O$1000,"<"&Lists!$AG$4) -> 3
A67: Migrate | B67: =COUNTIFS('Application Portfolio'!B$2:B$1000,"<>",'Application Portfolio'!AB$2:AB$1000,A67) -> 3 | E67: ="Low (< "&TEXT(Lists!$AG$5,"0.0")&")" -> Low (< 2.5) | F67: =COUNTIFS('Application Portfolio'!B$2:B$1000,"<>",'Application Portfolio'!O$2:O$1000,"<"&Lists!$AG$5) -> 2
A68: Eliminate | B68: =COUNTIFS('Application Portfolio'!B$2:B$1000,"<>",'Application Portfolio'!AB$2:AB$1000,A68) -> 1 | E68: Not scored | F68: =COUNTIFS('Application Portfolio'!B$2:B$1000,"<>",'Application Portfolio'!O$2:O$1000,"") -> 0
A70: Gartner TIME Model
A71: TIME classifies apps on two axes: Business Value (BV) and Technical Health (TH).
A72: Invest: High BV + High TH | Migrate: High BV + Low TH | Tolerate: Low BV + High TH | Eliminate: Low BV + Low TH
A73: ="Thresholds (edit on Lists AF:AG): High BV >= "&TEXT(Lists!$AG$2,"0.0")&", High TH >= "&TEXT(Lists!$AG$3,"0.0")&", High Risk >= "&TEXT(Lists!$AG$4,"0.0")&", Moderate Risk >= "&TEXT(Lists!$AG$5,"0.0")&", High Cost >= "&TEXT(Lists!$AG$6,"0.0")&". TIME uses BV and TH only; Risk and Cost are informational." -> Thresholds (edit on Lists AF:AG): High BV >= 3.0, High TH >= 3.0, High Risk >= 3.5, Moderate Risk >= 2.5, High Cost >= 3.5. TIME uses BV and TH only; Risk and Cost are informational.
A75: Run Cost (Total Annual Cost $) | E75: Thresholds in Use
A76: Total annual run cost ($) | B76: =SUM('Application Portfolio'!AG2:AG1000) -> 0 | E76: High Business Value >= | F76: =Lists!$AG$2 -> 3
A77: Run cost in Migrate + Eliminate ($) | B77: =SUMIFS('Application Portfolio'!AG2:AG1000,'Application Portfolio'!AB2:AB1000,"Migrate")+SUMIFS('Application Portfolio'!AG2:AG1000,'Application Portfolio'!AB2:AB1000,"Eliminate") -> 0 | E77: High Technical Health >= | F77: =Lists!$AG$3 -> 3
A78: Share of run cost in Migrate + Eliminate | B78: =IF(B76>0,B77/B76,"") | E78: High Risk >= | F78: =Lists!$AG$4 -> 3.5
A79: Apps missing cost | B79: =SUMPRODUCT(('Application Portfolio'!B2:B1000<>"")*NOT(ISNUMBER('Application Portfolio'!AG2:AG1000))) -> 7 | E79: Moderate Risk >= | F79: =Lists!$AG$5 -> 2.5
E80: High Cost >= | F80: =Lists!$AG$6 -> 3.5
A81: Enter annual cost per application in Application Portfolio column AG. Apps without a number there are counted as missing cost.
A83: IDs | E83: Cross-checks
A84: Next App ID to assign | B84: {=IFERROR("APM-"&TEXT(MAX(--("0"&SUBSTITUTE('Application Portfolio'!$A$2:$A$1000,"APM-","")))+1,"0000"),"Fix malformed IDs first")} -> APM-0008 | E84: Active debt on apps marked Eliminate | F84: =COUNTIFS('Debt Backlog'!$AH$2:$AH$1000,"Eliminate",'Debt Backlog'!$B$2:$B$1000,"<>",'Debt Backlog'!$N$2:$N$1000,"<>Done",'Debt Backlog'!$N$2:$N$1000,"<>Won't Fix",'Debt Backlog'!$N$2:$N$1000,"<>Duplicate") -> 0
A85: Next Debt ID to assign | B85: {=IFERROR("TD-"&TEXT(MAX(--("0"&SUBSTITUTE('Debt Backlog'!$A$2:$A$1000,"TD-","")))+1,"0000"),"Fix malformed IDs first")} -> TD-0008 | E85: Active debt on apps marked Migrate | F85: =COUNTIFS('Debt Backlog'!$AH$2:$AH$1000,"Migrate",'Debt Backlog'!$B$2:$B$1000,"<>",'Debt Backlog'!$N$2:$N$1000,"<>Done",'Debt Backlog'!$N$2:$N$1000,"<>Won't Fix",'Debt Backlog'!$N$2:$N$1000,"<>Duplicate") -> 4
A86: Next Risk ID to assign | B86: {=IFERROR("R-"&TEXT(MAX(--("0"&SUBSTITUTE('Risk Register'!$A$2:$A$1000,"R-","")))+1,"0000"),"Fix malformed IDs first")} -> R-0008 | E86: Active debt not linked to an app | F86: =COUNTIFS('Debt Backlog'!$AF$2:$AF$1000,"",'Debt Backlog'!$B$2:$B$1000,"<>",'Debt Backlog'!$N$2:$N$1000,"<>Done",'Debt Backlog'!$N$2:$N$1000,"<>Won't Fix",'Debt Backlog'!$N$2:$N$1000,"<>Duplicate") -> 1
A87: Apps with ID problems | B87: {=SUMPRODUCT(('Application Portfolio'!$B$2:$B$1000<>"")*((('Application Portfolio'!$A$2:$A$1000="")+(COUNTIF('Application Portfolio'!$A$2:$A$1000,'Application Portfolio'!$A$2:$A$1000)>1)+(LEFT('Application Portfolio'!$A$2:$A$1000,4)<>"APM-")+(LEN('Application Portfolio'!$A$2:$A$1000)<>8)+NOT(ISNUMBER(--RIGHT('Application Portfolio'!$A$2:$A$1000,4))))>0))} -> 0 | E87: Apps with more than one risk row | F87: =SUMPRODUCT(('Application Portfolio'!$A$2:$A$1000<>"")*(COUNTIF('Risk Register'!$B$2:$B$1000,'Application Portfolio'!$A$2:$A$1000)>1)) -> 0
A88: Debt items with ID problems | B88: {=SUMPRODUCT(('Debt Backlog'!$B$2:$B$1000<>"")*((('Debt Backlog'!$A$2:$A$1000="")+(COUNTIF('Debt Backlog'!$A$2:$A$1000,'Debt Backlog'!$A$2:$A$1000)>1)+(LEFT('Debt Backlog'!$A$2:$A$1000,3)<>"TD-")+(LEN('Debt Backlog'!$A$2:$A$1000)<>7)+NOT(ISNUMBER(--RIGHT('Debt Backlog'!$A$2:$A$1000,4))))>0))} -> 0
A89: Risks with ID problems | B89: {=SUMPRODUCT(('Risk Register'!$B$2:$B$1000<>"")*((('Risk Register'!$A$2:$A$1000="")+(COUNTIF('Risk Register'!$A$2:$A$1000,'Risk Register'!$A$2:$A$1000)>1)+(LEFT('Risk Register'!$A$2:$A$1000,2)<>"R-")+(LEN('Risk Register'!$A$2:$A$1000)<>6)+NOT(ISNUMBER(--RIGHT('Risk Register'!$A$2:$A$1000,4))))>0))} -> 0
A90: All IDs are fixed values, the same for typed and imported rows. For a new row enter the Next ID in column A; for a batch, enter it in the first new row and drag the fill handle down. Never renumber or reuse an ID.

Sheet Instructions
B1: How to Use This Workbook
B2: What each tab does, how the scores are calculated, and how to change lists, weights and thresholds.
B4: What this workbook does
B5: It keeps three registers in one place: a technical debt backlog, an application risk register, and an application portfolio. It scores every item, classifies each application with the Gartner TIME model (Invest, Tolerate, Migrate, Eliminate), links debt to the applications it sits on, and rolls everything up to the Dashboard. Everything recalculates as you type; there are no macros and nothing to refresh.
B7: The tabs
B8: Dashboard | C8: Read-only. Top: headline tiles (numbers that need attention turn red when above zero), the TIME matrix listing every application in its quadrant, and two charts (portfolio mix and active debt by severity). Below: the detail tables, with in-cell bars, for debt status, severity, cost, TIME, risk, run cost, thresholds, the next ID to assign on each sheet, and data-quality cross-checks. Everything updates on its own.
B9: Instructions | C9: This page.
B10: Debt Backlog | C10: One row per technical debt item. You enter the item; the sheet scores it, sets its priority and due date, flags it overdue, and links it to an application.
B11: Risk Register | C11: One row per application, scored on five risk factors. The Risk Score feeds the Application Portfolio.
B12: Application Portfolio | C12: One row per application, scored on value, cost and technical health. The sheet works out the TIME classification, a composite score, a value vs risk quadrant, and the open debt on each app.
B13: Lists | C13: Every dropdown list, scoring weight, threshold, due-date window and priority cutoff. Change the model here, not in the formulas.
B15: Cell colors
B16: Light blue | C16: Calculated. Do not type in these cells; doing so overwrites the formula for that row.
B17: Pale yellow | C17: Score input, 1 to 5 (Application Portfolio scoring columns).
B18: Light gray / white | C18: Regular input: text, dates, dropdowns and dollar amounts.
B19: Red ID cell | C19: The ID in column A is blank, duplicated or malformed. Fix it before relying on the numbers.
B21: Quick start
B22: 1. Add applications | C22: On Application Portfolio, put the Next App ID from the Dashboard in column A, the name in B, and score the pale-yellow columns 1 to 5. Add Total Annual Cost ($) in column AG if you have it.
B23: 2. Score their risk | C23: On Risk Register, add one row per application: Next Risk ID, pick the App ID, and score the five risk factors 1 to 5. The Risk Score flows back to the portfolio.
B24: 3. Log debt | C24: On Debt Backlog, use the Next Debt ID, enter a Title, then pick Severity, Impact, Confidence and Effort. Those four drive the score. Pick the App ID so the debt rolls up to that application.
B25: 4. Keep it current | C25: Update Status as work moves. Set Date Identified and a Target Window (or a Due Date) so overdue items are flagged. Check the Dashboard cross-checks now and then.
B27: Debt Backlog: how it calculates
B28: Debt Score (L) | C28: Severity points x Impact points x Confidence weight / Effort points, using the tables on Lists. Defaults: Severity Critical 4, High 3, Medium 2, Low 1. Impact High 3, Medium 2, Low 1. Confidence High 1.0, Medium 0.8, Low 0.6. Effort XS 1, S 2, M 3, L 5, XL 8. Bigger, surer, cheaper fixes score higher. Blank until Title, Severity, Impact, Confidence and Effort are all filled.
B29: Priority (M) | C29: Priority Override (AC) wins if you enter one. Otherwise Critical severity is always P0. Otherwise the Debt Score is compared with the cutoffs on Lists AL:AM (defaults P0 at 3.5 or more, P1 at 2.5, P2 at 1.5, anything lower is P3).
B30: Age (R) | C30: Days since Date Identified.
B31: Effective Due Date (AD) | C31: Due Date (T) if you enter one. Otherwise Date Identified plus the days for the Target Window on Lists AI:AJ (Next Sprint 14, Next 2 Sprints 28, This Quarter 90, Next Quarter 180). Backlog and TBD have no implied date.
B32: Overdue (AE) | C32: Yes when the Effective Due Date has passed and the item is still active.
B33: Active | C33: Any status except Done, Won't Fix and Duplicate. Active items drive the Dashboard counts, cost totals and the open debt rollups on the portfolio.
B34: App link (AF:AH) | C34: Pick an App ID and the application name and its TIME classification are pulled in. "Unknown App ID" means the ID is not on Application Portfolio.
B35: Costs (Y:AB) | C35: Direct remediation, annual carry and contingent risk cost, plus how sure you are of the numbers. Active items feed the Debt Cost Summary and Cost by Confidence on the Dashboard.
B37: Risk Register: how it calculates
B38: Risk Score (I) | C38: Weighted average of the five factors (Cybersecurity, Compliance, Operational Resilience, Vendor, Knowledge Concentration) using the Risk weights on Lists. 5 is the riskiest. Blank until all five are scored.
B39: One row per app | C39: The portfolio reads the first row it finds for each App ID. A second row for the same app is ignored and counted under "Apps with more than one risk row" on the Dashboard.
B41: Application Portfolio: how it calculates
B42: Scoring direction | C42: Business Value and Technical Health factors: 5 is best. That includes Integration Complexity and Technical Debt, so score them 5 when complexity or debt is low. Cost factors: 5 is the most expensive. Risk comes from the Risk Register, where 5 is the riskiest.
B43: BV, C, TH (N, T, Z) | C43: Business Value, Cost Score and Technical Health are weighted averages of their 1-5 inputs, using the weights on Lists. Each is blank until every factor in its group is scored.
B44: Risk Score (O) | C44: Pulled from the Risk Register by App ID.
B45: CPS (AA) | C45: Composite Portfolio Score = BV x weight - Risk x weight - Cost x weight + TH x weight. It rewards value and technical health and penalizes risk and cost, in one number. Blank until BV, Risk, Cost and TH all have a score.
B46: CPS range | C46: With the default even weights (0.25 each) CPS runs from -2.00 to +2.00. +2.00 means BV and TH scored 5 with Risk and Cost scored 1. -2.00 is the reverse. 0.00 means value and health exactly offset risk and cost, for example every factor scored 3.
B47: What is a good CPS | C47: Rule of thumb, not a built-in threshold (nothing in the workbook classifies by CPS; the Dashboard only shows the average): +1.0 or higher is strong. 0 to +1.0 is sound, with value and health ahead of risk and cost. -1.0 to 0 is a watch item, where risk and cost outweigh what the app delivers. Below -1.0 is weak and a candidate for remediation or retirement.
B48: How to use CPS | C48: Use it to rank, not to decide strategy. TIME says what to do with an app and uses only BV and TH; CPS says how strong the app is overall once risk and cost count. Sort Application Portfolio by CPS, or compare apps in the same TIME class: of two Migrate apps, the lower CPS usually goes first. In the sample data Customer Portal is Migrate with high value, but its risk and cost pull its CPS to -0.14; Legacy CRM is the weakest at -1.53 and Order Management System the strongest at +0.65.
B49: If you change CPS weights | C49: The range moves with them. Top = 5 x (BV weight + TH weight) - (Risk weight + Cost weight). Bottom = (BV weight + TH weight) - 5 x (Risk weight + Cost weight). Keep the four weights adding to 1.00 so scores stay comparable over time, and adjust the rule-of-thumb bands above if the range changes.
B50: TIME (AB) | C50: High BV and high TH = Invest. High BV, low TH = Migrate. Low BV, high TH = Tolerate. Low BV, low TH = Eliminate. "High" means at or above the thresholds on Lists AF:AG (default 3.0 for both). Risk and Cost do not change the TIME call.
B51: Quadrant (AE) | C51: Business Value against Risk, using the High BV and High Risk thresholds.
B52: Flags (AC, AD) | C52: Clinical Criticality = Yes when Clinical / Business Criticality is 4 or 5. Compliance Exposure = Yes when the Compliance risk factor is 4 or 5.
B53: Total Annual Cost (AG) | C53: Dollar run cost per app, entered by you. Drives the Run Cost section of the Dashboard. Apps without a number are counted as missing cost.
B54: Open debt (AH, AI) | C54: Count and summed Debt Score of the active debt items linked to the app.
B56: Changing dropdown lists
B57: Each dropdown reads a named range on the Lists tab (Formulas > Name Manager shows them all, for example lstDebtType = Lists!A2:A13). The dropdowns show whatever is in that range.
B58: Add an item | C58: Click a cell inside the list (below the header, above the last item), choose Insert > Insert Cells > Shift cells down, and type the new value. Inserting inside the list makes the named range grow by itself. If you type below the last item instead, extend the range in Name Manager or the new value will not appear in the dropdown.
B59: Lists with a points column | C59: Severity, Impact, Confidence and Effort each have a points column beside them (E:F, H:I, K:L, N:O). Select both cells of a row before inserting so the value and its points stay paired, and give the new value a points number.
B60: Rename an item | C60: Change the text on Lists, then fix the rows that already used the old value. Dropdowns do not rewrite existing data: those rows keep the old text, stop matching the list, and drop out of any count that looks for the new name. Data > Data Validation > Circle Invalid Data shows them.
B61: Remove an item | C61: Select the cell, Delete > Shift cells up, then fix any rows that used it.
B62: Target Window | C62: This one lives in two places: the dropdown list (Lists W) and the days table (Lists AI:AJ). Add or rename a window in both, with matching spelling, or its due dates will not calculate.
B63: Do not rename | C63: These exact words are written into formulas: Status Done, Won't Fix and Duplicate; Severity Critical, High, Medium and Low; Confidence High, Medium and Low; Priority P0 to P3; and the TIME names Invest, Tolerate, Migrate and Eliminate. Renaming them breaks the counts. Adding new values is fine.
B64: New Status values | C64: They work everywhere, but the Debt Status Breakdown table and chart on the Dashboard list fixed statuses. To show a new one, add a row to that table (copy the row above, change the label).
B66: Changing weights, thresholds and cutoffs
B67: Scoring weights (Lists AC:AD) | C67: Five groups: Business Value (rows 2-6), Cost (7-10), Technical Health (11-15), CPS (16-19) and Risk (20-24). Raise a factor's weight to make it count more. Each group must add up to 1.00.
B68: Weight Check (Lists AO:AQ) | C68: Shows Yes or No for the Business Value, Cost, Technical Health and Risk groups and turns red on No. It does not check the CPS group, so keep those four adding to 1.00 yourself. Enter CPS weights as positive numbers; the formula already subtracts Risk and Cost.
B69: Thresholds (Lists AF:AG) | C69: High Business Value and High Technical Health set the TIME lines. High Risk and Moderate Risk set the risk bands and the quadrant. High Cost sets the Dashboard high-cost count.
B70: Due-date windows (Lists AI:AJ) | C70: Days added to Date Identified for each Target Window.
B71: Priority cutoffs (Lists AL:AM) | C71: Minimum Debt Score for P0, P1 and P2. Anything below the P2 cutoff is P3.
B72: Debt scoring points (Lists E:O) | C72: The Severity, Impact, Confidence and Effort numbers used in the Debt Score.
B73: Every change takes effect immediately across all sheets and the Dashboard. Weights ship at even defaults; note what you changed and why, since a changed weight can move applications between TIME classes.
B75: IDs and data quality
B76: Assigning IDs | C76: Use the Next ID on the Dashboard (APM-0000, TD-0000, R-0000 style). For a batch, enter the next ID in the first new row and drag the fill handle down. Never renumber or reuse an ID; other sheets link by it.
B77: Validation | C77: Typing a badly formed or duplicate ID is blocked. A pasted or imported bad ID turns red and is counted under the ID problem checks on the Dashboard, and the Next ID cell shows "Fix malformed IDs first".
B78: Cross-checks | C78: The Dashboard also counts active debt on apps marked Eliminate or Migrate, active debt not linked to any app, and apps with more than one risk row. Any non-zero count is worth a look.
B80: Good habits
B81: Capacity | C81: Rows 2 to 1000 on each data sheet are pre-built, so each holds up to 999 records.
B82: Sorting and filtering | C82: Safe on every data sheet. Formulas follow their rows.
B83: Removing a record | C83: Delete its row (right-click > Delete > Table Rows) rather than clearing a few cells.
B84: Columns | C84: Do not insert, delete or move columns on the data sheets. The Dashboard and the links between sheets use fixed column positions.
B85: Calculated cells | C85: If you overwrite a light-blue cell by accident, copy the same cell from the row above or below to restore the formula.

Sheet Debt Backlog
A1: Debt ID | B1: Title | C1: Description | D1: Product/Service | E1: Component/Module | F1: Debt Type | G1: Impact Area | H1: Severity | I1: Impact | J1: Confidence | K1: Effort | L1: Debt Score | M1: Priority | N1: Status | O1: Owner | P1: Team | Q1: Date Identified | R1: Age (days) | S1: Target Window | T1: Due Date | U1: Last Updated | V1: Dependencies/Related Work | W1: Link (Jira/Confluence/LeanIX) | X1: Notes | Y1: Direct Remediation Cost ($) | Z1: Annual Carry Cost ($) | AA1: Contingent Risk Cost ($) | AB1: Cost Confidence | AC1: Priority Override | AD1: Effective Due Date | AE1: Overdue | AF1: App ID | AG1: Application Name | AH1: App TIME Classification
A2: TD-0001 | B2: Legacy auth library past EOL | C2: Spring Security 4.x, end of life 2022, multiple CVEs unpatched. | D2: Customer Portal | E2: auth-service | F2: Security | G2: Security | H2: Critical | I2: High | J2: High | K2: L | L2: =IF(OR($B2="", $H2="", $I2="", $J2="", $K2=""),"",ROUND((VLOOKUP($H2,Lists!$E$2:$F$5,2,FALSE())*VLOOKUP($I2,Lists!$H$2:$I$4,2,FALSE())*VLOOKUP($J2,Lists!$K$2:$L$4,2,FALSE()))/VLOOKUP($K2,Lists!$N$2:$O$6,2,FALSE()),2)) -> 2.4 | M2: =IF($B2="","",IF($AC2<>"",$AC2,IF($H2="Critical","P0",IF(NOT(ISNUMBER($L2)),"",IF($L2>=Lists!$AM$2,"P0",IF($L2>=Lists!$AM$3,"P1",IF($L2>=Lists!$AM$4,"P2","P3"))))))) -> P0 | N2: In Progress | O2: J. Park | P2: Platform | Q2: 45976 | R2: =IF($Q2="","", TODAY()-$Q2) -> 344 | S2: This Quarter | V2: Coordination with Identity team | W2: JIRA-TD-1041 | X2: Blocks HITRUST certification | AD2: =IF($B2="","",IF(ISNUMBER($T2),$T2,IF(OR(NOT(ISNUMBER($Q2)),$S2=""),"",IFERROR(IF(ISNUMBER(INDEX(Lists!$AJ$2:$AJ$7,MATCH($S2,Lists!$AI$2:$AI$7,0))),$Q2+INDEX(Lists!$AJ$2:$AJ$7,MATCH($S2,Lists!$AI$2:$AI$7,0)),""),"")))) -> 46066 | AE2: =IF($B2="","",IF(AND(ISNUMBER($AD2),N($AD2)<TODAY(),$N2<>"Done",$N2<>"Won't Fix",$N2<>"Duplicate"),"Yes","No")) -> Yes | AF2: APM-0001 | AG2: =IF($AF2="","",IFERROR(VLOOKUP($AF2,'Application Portfolio'!$A$2:$B$1000,2,FALSE()),"Unknown App ID")) -> Customer Portal | AH2: =IF(OR($B2="",$AF2=""),"",IFERROR(VLOOKUP($AF2,'Application Portfolio'!$A$2:$AB$1000,28,FALSE()),"")) -> Migrate
A3: TD-0002 | B3: Orders table missing indexes | C3: Supply order queries degrading as volume grows, p95 over 2s. | D3: Order Management | E3: order-db | F3: Infrastructure | G3: Performance | H3: High | I3: High | J3: High | K3: M | L3: =IF(OR($B3="", $H3="", $I3="", $J3="", $K3=""),"",ROUND((VLOOKUP($H3,Lists!$E$2:$F$5,2,FALSE())*VLOOKUP($I3,Lists!$H$2:$I$4,2,FALSE())*VLOOKUP($J3,Lists!$K$2:$L$4,2,FALSE()))/VLOOKUP($K3,Lists!$N$2:$O$6,2,FALSE()),2)) -> 3 | M3: =IF($B3="","",IF($AC3<>"",$AC3,IF($H3="Critical","P0",IF(NOT(ISNUMBER($L3)),"",IF($L3>=Lists!$AM$2,"P0",IF($L3>=Lists!$AM$3,"P1",IF($L3>=Lists!$AM$4,"P2","P3"))))))) -> P1 | N3: Planned | O3: M. Chen | P3: Data | Q3: 45994 | R3: =IF($Q3="","", TODAY()-$Q3) -> 326 | S3: Next Sprint | V3: None | W3: JIRA-TD-1073 | AD3: =IF($B3="","",IF(ISNUMBER($T3),$T3,IF(OR(NOT(ISNUMBER($Q3)),$S3=""),"",IFERROR(IF(ISNUMBER(INDEX(Lists!$AJ$2:$AJ$7,MATCH($S3,Lists!$AI$2:$AI$7,0))),$Q3+INDEX(Lists!$AJ$2:$AJ$7,MATCH($S3,Lists!$AI$2:$AI$7,0)),""),"")))) -> 46008 | AE3: =IF($B3="","",IF(AND(ISNUMBER($AD3),N($AD3)<TODAY(),$N3<>"Done",$N3<>"Won't Fix",$N3<>"Duplicate"),"Yes","No")) -> Yes | AF3: APM-0002 | AG3: =IF($AF3="","",IFERROR(VLOOKUP($AF3,'Application Portfolio'!$A$2:$B$1000,2,FALSE()),"Unknown App ID")) -> Order Management System | AH3: =IF(OR($B3="",$AF3=""),"",IFERROR(VLOOKUP($AF3,'Application Portfolio'!$A$2:$AB$1000,28,FALSE()),"")) -> Invest
A4: TD-0003 | B4: Hardcoded config in payments | C4: Env values embedded in code, requires redeploy to change. | D4: Payments | E4: payment-processor | F4: Code Quality | G4: Maintainability | H4: High | I4: Medium | J4: High | K4: S | L4: =IF(OR($B4="", $H4="", $I4="", $J4="", $K4=""),"",ROUND((VLOOKUP($H4,Lists!$E$2:$F$5,2,FALSE())*VLOOKUP($I4,Lists!$H$2:$I$4,2,FALSE())*VLOOKUP($J4,Lists!$K$2:$L$4,2,FALSE()))/VLOOKUP($K4,Lists!$N$2:$O$6,2,FALSE()),2)) -> 3 | M4: =IF($B4="","",IF($AC4<>"",$AC4,IF($H4="Critical","P0",IF(NOT(ISNUMBER($L4)),"",IF($L4>=Lists!$AM$2,"P0",IF($L4>=Lists!$AM$3,"P1",IF($L4>=Lists!$AM$4,"P2","P3"))))))) -> P1 | N4: Triaged | O4: R. Singh | P4: Backend | Q4: 46030 | R4: =IF($Q4="","", TODAY()-$Q4) -> 290 | S4: Next 2 Sprints | V4: None | W4: JIRA-TD-1102 | AD4: =IF($B4="","",IF(ISNUMBER($T4),$T4,IF(OR(NOT(ISNUMBER($Q4)),$S4=""),"",IFERROR(IF(ISNUMBER(INDEX(Lists!$AJ$2:$AJ$7,MATCH($S4,Lists!$AI$2:$AI$7,0))),$Q4+INDEX(Lists!$AJ$2:$AJ$7,MATCH($S4,Lists!$AI$2:$AI$7,0)),""),"")))) -> 46058 | AE4: =IF($B4="","",IF(AND(ISNUMBER($AD4),N($AD4)<TODAY(),$N4<>"Done",$N4<>"Won't Fix",$N4<>"Duplicate"),"Yes","No")) -> Yes | AF4: APM-0003 | AG4: =IF($AF4="","",IFERROR(VLOOKUP($AF4,'Application Portfolio'!$A$2:$B$1000,2,FALSE()),"Unknown App ID")) -> Payment Processor | AH4: =IF(OR($B4="",$AF4=""),"",IFERROR(VLOOKUP($AF4,'Application Portfolio'!$A$2:$AB$1000,28,FALSE()),"")) -> Migrate
A5: TD-0004 | B5: No integration tests on billing | C5: Only unit tests, prod-only bugs found monthly. | D5: Billing | E5: billing-svc | F5: Test Coverage | G5: Reliability | H5: Medium | I5: High | J5: Medium | K5: L | L5: =IF(OR($B5="", $H5="", $I5="", $J5="", $K5=""),"",ROUND((VLOOKUP($H5,Lists!$E$2:$F$5,2,FALSE())*VLOOKUP($I5,Lists!$H$2:$I$4,2,FALSE())*VLOOKUP($J5,Lists!$K$2:$L$4,2,FALSE()))/VLOOKUP($K5,Lists!$N$2:$O$6,2,FALSE()),2)) -> 0.96 | M5: =IF($B5="","",IF($AC5<>"",$AC5,IF($H5="Critical","P0",IF(NOT(ISNUMBER($L5)),"",IF($L5>=Lists!$AM$2,"P0",IF($L5>=Lists!$AM$3,"P1",IF($L5>=Lists!$AM$4,"P2","P3"))))))) -> P3 | N5: New | P5: QA | Q5: 46065 | R5: =IF($Q5="","", TODAY()-$Q5) -> 255 | S5: Next Quarter | V5: Test data framework | X5: Owner TBD | AD5: =IF($B5="","",IF(ISNUMBER($T5),$T5,IF(OR(NOT(ISNUMBER($Q5)),$S5=""),"",IFERROR(IF(ISNUMBER(INDEX(Lists!$AJ$2:$AJ$7,MATCH($S5,Lists!$AI$2:$AI$7,0))),$Q5+INDEX(Lists!$AJ$2:$AJ$7,MATCH($S5,Lists!$AI$2:$AI$7,0)),""),"")))) -> 46245 | AE5: =IF($B5="","",IF(AND(ISNUMBER($AD5),N($AD5)<TODAY(),$N5<>"Done",$N5<>"Won't Fix",$N5<>"Duplicate"),"Yes","No")) -> Yes | AG5: =IF($AF5="","",IFERROR(VLOOKUP($AF5,'Application Portfolio'!$A$2:$B$1000,2,FALSE()),"Unknown App ID")) | AH5: =IF(OR($B5="",$AF5=""),"",IFERROR(VLOOKUP($AF5,'Application Portfolio'!$A$2:$AB$1000,28,FALSE()),""))
A6: TD-0005 | B6: React version 3 majors behind | C6: v16 in use, ecosystem moving to v19. | D6: Customer Portal | E6: web-ui | F6: Dependencies/Upgrades | G6: Developer Productivity | H6: Medium | I6: Medium | J6: High | K6: M | L6: =IF(OR($B6="", $H6="", $I6="", $J6="", $K6=""),"",ROUND((VLOOKUP($H6,Lists!$E$2:$F$5,2,FALSE())*VLOOKUP($I6,Lists!$H$2:$I$4,2,FALSE())*VLOOKUP($J6,Lists!$K$2:$L$4,2,FALSE()))/VLOOKUP($K6,Lists!$N$2:$O$6,2,FALSE()),2)) -> 1.33 | M6: =IF($B6="","",IF($AC6<>"",$AC6,IF($H6="Critical","P0",IF(NOT(ISNUMBER($L6)),"",IF($L6>=Lists!$AM$2,"P0",IF($L6>=Lists!$AM$3,"P1",IF($L6>=Lists!$AM$4,"P2","P3"))))))) -> P3 | N6: Planned | O6: L. Ramirez | P6: Frontend | Q6: 45952 | R6: =IF($Q6="","", TODAY()-$Q6) -> 368 | S6: Next Quarter | V6: Design system rework | W6: JIRA-TD-0994 | AD6: =IF($B6="","",IF(ISNUMBER($T6),$T6,IF(OR(NOT(ISNUMBER($Q6)),$S6=""),"",IFERROR(IF(ISNUMBER(INDEX(Lists!$AJ$2:$AJ$7,MATCH($S6,Lists!$AI$2:$AI$7,0))),$Q6+INDEX(Lists!$AJ$2:$AJ$7,MATCH($S6,Lists!$AI$2:$AI$7,0)),""),"")))) -> 46132 | AE6: =IF($B6="","",IF(AND(ISNUMBER($AD6),N($AD6)<TODAY(),$N6<>"Done",$N6<>"Won't Fix",$N6<>"Duplicate"),"Yes","No")) -> Yes | AF6: APM-0001 | AG6: =IF($AF6="","",IFERROR(VLOOKUP($AF6,'Application Portfolio'!$A$2:$B$1000,2,FALSE()),"Unknown App ID")) -> Customer Portal | AH6: =IF(OR($B6="",$AF6=""),"",IFERROR(VLOOKUP($AF6,'Application Portfolio'!$A$2:$AB$1000,28,FALSE()),"")) -> Migrate
A7: TD-0006 | B7: Observability gaps on batch jobs | C7: Nightly reconciliation has no alerting, failures found by users. | D7: Finance Ops | E7: recon-batch | F7: Observability | G7: Reliability | H7: High | I7: High | J7: Medium | K7: S | L7: =IF(OR($B7="", $H7="", $I7="", $J7="", $K7=""),"",ROUND((VLOOKUP($H7,Lists!$E$2:$F$5,2,FALSE())*VLOOKUP($I7,Lists!$H$2:$I$4,2,FALSE())*VLOOKUP($J7,Lists!$K$2:$L$4,2,FALSE()))/VLOOKUP($K7,Lists!$N$2:$O$6,2,FALSE()),2)) -> 3.6 | M7: =IF($B7="","",IF($AC7<>"",$AC7,IF($H7="Critical","P0",IF(NOT(ISNUMBER($L7)),"",IF($L7>=Lists!$AM$2,"P0",IF($L7>=Lists!$AM$3,"P1",IF($L7>=Lists!$AM$4,"P2","P3"))))))) -> P0 | N7: In Progress | O7: K. Osei | P7: DevOps | Q7: 46009 | R7: =IF($Q7="","", TODAY()-$Q7) -> 311 | S7: Next Sprint | V7: Grafana dashboards | W7: JIRA-TD-1128 | AD7: =IF($B7="","",IF(ISNUMBER($T7),$T7,IF(OR(NOT(ISNUMBER($Q7)),$S7=""),"",IFERROR(IF(ISNUMBER(INDEX(Lists!$AJ$2:$AJ$7,MATCH($S7,Lists!$AI$2:$AI$7,0))),$Q7+INDEX(Lists!$AJ$2:$AJ$7,MATCH($S7,Lists!$AI$2:$AI$7,0)),""),"")))) -> 46023 | AE7: =IF($B7="","",IF(AND(ISNUMBER($AD7),N($AD7)<TODAY(),$N7<>"Done",$N7<>"Won't Fix",$N7<>"Duplicate"),"Yes","No")) -> Yes | AF7: APM-0006 | AG7: =IF($AF7="","",IFERROR(VLOOKUP($AF7,'Application Portfolio'!$A$2:$B$1000,2,FALSE()),"Unknown App ID")) -> Financial Reconciliation | AH7: =IF(OR($B7="",$AF7=""),"",IFERROR(VLOOKUP($AF7,'Application Portfolio'!$A$2:$AB$1000,28,FALSE()),"")) -> Migrate
A8: TD-0007 | B8: Outdated API docs | C8: Swagger and FHIR capability statement not regenerated in 18 months; payer and lab integrations slowed. | D8: Partner API | E8: api-gateway | F8: Documentation | G8: Developer Productivity | H8: Low | I8: Medium | J8: High | K8: XS | L8: =IF(OR($B8="", $H8="", $I8="", $J8="", $K8=""),"",ROUND((VLOOKUP($H8,Lists!$E$2:$F$5,2,FALSE())*VLOOKUP($I8,Lists!$H$2:$I$4,2,FALSE())*VLOOKUP($J8,Lists!$K$2:$L$4,2,FALSE()))/VLOOKUP($K8,Lists!$N$2:$O$6,2,FALSE()),2)) -> 2 | M8: =IF($B8="","",IF($AC8<>"",$AC8,IF($H8="Critical","P0",IF(NOT(ISNUMBER($L8)),"",IF($L8>=Lists!$AM$2,"P0",IF($L8>=Lists!$AM$3,"P1",IF($L8>=Lists!$AM$4,"P2","P3"))))))) -> P2 | N8: New | O8: T. Morgan | P8: Backend | Q8: 46086 | R8: =IF($Q8="","", TODAY()-$Q8) -> 234 | S8: Backlog | V8: None | AD8: =IF($B8="","",IF(ISNUMBER($T8),$T8,IF(OR(NOT(ISNUMBER($Q8)),$S8=""),"",IFERROR(IF(ISNUMBER(INDEX(Lists!$AJ$2:$AJ$7,MATCH($S8,Lists!$AI$2:$AI$7,0))),$Q8+INDEX(Lists!$AJ$2:$AJ$7,MATCH($S8,Lists!$AI$2:$AI$7,0)),""),"")))) | AE8: =IF($B8="","",IF(AND(ISNUMBER($AD8),N($AD8)<TODAY(),$N8<>"Done",$N8<>"Won't Fix",$N8<>"Duplicate"),"Yes","No")) -> No | AF8: APM-0007 | AG8: =IF($AF8="","",IFERROR(VLOOKUP($AF8,'Application Portfolio'!$A$2:$B$1000,2,FALSE()),"Unknown App ID")) -> Partner API Gateway | AH8: =IF(OR($B8="",$AF8=""),"",IFERROR(VLOOKUP($AF8,'Application Portfolio'!$A$2:$AB$1000,28,FALSE()),"")) -> Invest
L9: =IF(OR($B9="", $H9="", $I9="", $J9="", $K9=""),"",ROUND((VLOOKUP($H9,Lists!$E$2:$F$5,2,FALSE())*VLOOKUP($I9,Lists!$H$2:$I$4,2,FALSE())*VLOOKUP($J9,Lists!$K$2:$L$4,2,FALSE()))/VLOOKUP($K9,Lists!$N$2:$O$6,2,FALSE()),2)) | M9: =IF($B9="","",IF($AC9<>"",$AC9,IF($H9="Critical","P0",IF(NOT(ISNUMBER($L9)),"",IF($L9>=Lists!$AM$2,"P0",IF($L9>=Lists!$AM$3,"P1",IF($L9>=Lists!$AM$4,"P2","P3"))))))) | R9: =IF($Q9="","", TODAY()-$Q9) | AD9: =IF($B9="","",IF(ISNUMBER($T9),$T9,IF(OR(NOT(ISNUMBER($Q9)),$S9=""),"",IFERROR(IF(ISNUMBER(INDEX(Lists!$AJ$2:$AJ$7,MATCH($S9,Lists!$AI$2:$AI$7,0))),$Q9+INDEX(Lists!$AJ$2:$AJ$7,MATCH($S9,Lists!$AI$2:$AI$7,0)),""),"")))) | AE9: =IF($B9="","",IF(AND(ISNUMBER($AD9),N($AD9)<TODAY(),$N9<>"Done",$N9<>"Won't Fix",$N9<>"Duplicate"),"Yes","No")) | AG9: =IF($AF9="","",IFERROR(VLOOKUP($AF9,'Application Portfolio'!$A$2:$B$1000,2,FALSE()),"Unknown App ID")) | AH9: =IF(OR($B9="",$AF9=""),"",IFERROR(VLOOKUP($AF9,'Application Portfolio'!$A$2:$AB$1000,28,FALSE()),""))
L10: =IF(OR($B10="", $H10="", $I10="", $J10="", $K10=""),"",ROUND((VLOOKUP($H10,Lists!$E$2:$F$5,2,FALSE())*VLOOKUP($I10,Lists!$H$2:$I$4,2,FALSE())*VLOOKUP($J10,Lists!$K$2:$L$4,2,FALSE()))/VLOOKUP($K10,Lists!$N$2:$O$6,2,FALSE()),2)) | M10: =IF($B10="","",IF($AC10<>"",$AC10,IF($H10="Critical","P0",IF(NOT(ISNUMBER($L10)),"",IF($L10>=Lists!$AM$2,"P0",IF($L10>=Lists!$AM$3,"P1",IF($L10>=Lists!$AM$4,"P2","P3"))))))) | R10: =IF($Q10="","", TODAY()-$Q10) | AD10: =IF($B10="","",IF(ISNUMBER($T10),$T10,IF(OR(NOT(ISNUMBER($Q10)),$S10=""),"",IFERROR(IF(ISNUMBER(INDEX(Lists!$AJ$2:$AJ$7,MATCH($S10,Lists!$AI$2:$AI$7,0))),$Q10+INDEX(Lists!$AJ$2:$AJ$7,MATCH($S10,Lists!$AI$2:$AI$7,0)),""),"")))) | AE10: =IF($B10="","",IF(AND(ISNUMBER($AD10),N($AD10)<TODAY(),$N10<>"Done",$N10<>"Won't Fix",$N10<>"Duplicate"),"Yes","No")) | AG10: =IF($AF10="","",IFERROR(VLOOKUP($AF10,'Application Portfolio'!$A$2:$B$1000,2,FALSE()),"Unknown App ID")) | AH10: =IF(OR($B10="",$AF10=""),"",IFERROR(VLOOKUP($AF10,'Application Portfolio'!$A$2:$AB$1000,28,FALSE()),""))
L11: =IF(OR($B11="", $H11="", $I11="", $J11="", $K11=""),"",ROUND((VLOOKUP($H11,Lists!$E$2:$F$5,2,FALSE())*VLOOKUP($I11,Lists!$H$2:$I$4,2,FALSE())*VLOOKUP($J11,Lists!$K$2:$L$4,2,FALSE()))/VLOOKUP($K11,Lists!$N$2:$O$6,2,FALSE()),2)) | M11: =IF($B11="","",IF($AC11<>"",$AC11,IF($H11="Critical","P0",IF(NOT(ISNUMBER($L11)),"",IF($L11>=Lists!$AM$2,"P0",IF($L11>=Lists!$AM$3,"P1",IF($L11>=Lists!$AM$4,"P2","P3"))))))) | R11: =IF($Q11="","", TODAY()-$Q11) | AD11: =IF($B11="","",IF(ISNUMBER($T11),$T11,IF(OR(NOT(ISNUMBER($Q11)),$S11=""),"",IFERROR(IF(ISNUMBER(INDEX(Lists!$AJ$2:$AJ$7,MATCH($S11,Lists!$AI$2:$AI$7,0))),$Q11+INDEX(Lists!$AJ$2:$AJ$7,MATCH($S11,Lists!$AI$2:$AI$7,0)),""),"")))) | AE11: =IF($B11="","",IF(AND(ISNUMBER($AD11),N($AD11)<TODAY(),$N11<>"Done",$N11<>"Won't Fix",$N11<>"Duplicate"),"Yes","No")) | AG11: =IF($AF11="","",IFERROR(VLOOKUP($AF11,'Application Portfolio'!$A$2:$B$1000,2,FALSE()),"Unknown App ID")) | AH11: =IF(OR($B11="",$AF11=""),"",IFERROR(VLOOKUP($AF11,'Application Portfolio'!$A$2:$AB$1000,28,FALSE()),""))
L12: =IF(OR($B12="", $H12="", $I12="", $J12="", $K12=""),"",ROUND((VLOOKUP($H12,Lists!$E$2:$F$5,2,FALSE())*VLOOKUP($I12,Lists!$H$2:$I$4,2,FALSE())*VLOOKUP($J12,Lists!$K$2:$L$4,2,FALSE()))/VLOOKUP($K12,Lists!$N$2:$O$6,2,FALSE()),2)) | M12: =IF($B12="","",IF($AC12<>"",$AC12,IF($H12="Critical","P0",IF(NOT(ISNUMBER($L12)),"",IF($L12>=Lists!$AM$2,"P0",IF($L12>=Lists!$AM$3,"P1",IF($L12>=Lists!$AM$4,"P2","P3"))))))) | R12: =IF($Q12="","", TODAY()-$Q12) | AD12: =IF($B12="","",IF(ISNUMBER($T12),$T12,IF(OR(NOT(ISNUMBER($Q12)),$S12=""),"",IFERROR(IF(ISNUMBER(INDEX(Lists!$AJ$2:$AJ$7,MATCH($S12,Lists!$AI$2:$AI$7,0))),$Q12+INDEX(Lists!$AJ$2:$AJ$7,MATCH($S12,Lists!$AI$2:$AI$7,0)),""),"")))) | AE12: =IF($B12="","",IF(AND(ISNUMBER($AD12),N($AD12)<TODAY(),$N12<>"Done",$N12<>"Won't Fix",$N12<>"Duplicate"),"Yes","No")) | AG12: =IF($AF12="","",IFERROR(VLOOKUP($AF12,'Application Portfolio'!$A$2:$B$1000,2,FALSE()),"Unknown App ID")) | AH12: =IF(OR($B12="",$AF12=""),"",IFERROR(VLOOKUP($AF12,'Application Portfolio'!$A$2:$AB$1000,28,FALSE()),""))
L13: =IF(OR($B13="", $H13="", $I13="", $J13="", $K13=""),"",ROUND((VLOOKUP($H13,Lists!$E$2:$F$5,2,FALSE())*VLOOKUP($I13,Lists!$H$2:$I$4,2,FALSE())*VLOOKUP($J13,Lists!$K$2:$L$4,2,FALSE()))/VLOOKUP($K13,Lists!$N$2:$O$6,2,FALSE()),2)) | M13: =IF($B13="","",IF($AC13<>"",$AC13,IF($H13="Critical","P0",IF(NOT(ISNUMBER($L13)),"",IF($L13>=Lists!$AM$2,"P0",IF($L13>=Lists!$AM$3,"P1",IF($L13>=Lists!$AM$4,"P2","P3"))))))) | R13: =IF($Q13="","", TODAY()-$Q13) | AD13: =IF($B13="","",IF(ISNUMBER($T13),$T13,IF(OR(NOT(ISNUMBER($Q13)),$S13=""),"",IFERROR(IF(ISNUMBER(INDEX(Lists!$AJ$2:$AJ$7,MATCH($S13,Lists!$AI$2:$AI$7,0))),$Q13+INDEX(Lists!$AJ$2:$AJ$7,MATCH($S13,Lists!$AI$2:$AI$7,0)),""),"")))) | AE13: =IF($B13="","",IF(AND(ISNUMBER($AD13),N($AD13)<TODAY(),$N13<>"Done",$N13<>"Won't Fix",$N13<>"Duplicate"),"Yes","No")) | AG13: =IF($AF13="","",IFERROR(VLOOKUP($AF13,'Application Portfolio'!$A$2:$B$1000,2,FALSE()),"Unknown App ID")) | AH13: =IF(OR($B13="",$AF13=""),"",IFERROR(VLOOKUP($AF13,'Application Portfolio'!$A$2:$AB$1000,28,FALSE()),""))
L14: =IF(OR($B14="", $H14="", $I14="", $J14="", $K14=""),"",ROUND((VLOOKUP($H14,Lists!$E$2:$F$5,2,FALSE())*VLOOKUP($I14,Lists!$H$2:$I$4,2,FALSE())*VLOOKUP($J14,Lists!$K$2:$L$4,2,FALSE()))/VLOOKUP($K14,Lists!$N$2:$O$6,2,FALSE()),2)) | M14: =IF($B14="","",IF($AC14<>"",$AC14,IF($H14="Critical","P0",IF(NOT(ISNUMBER($L14)),"",IF($L14>=Lists!$AM$2,"P0",IF($L14>=Lists!$AM$3,"P1",IF($L14>=Lists!$AM$4,"P2","P3"))))))) | R14: =IF($Q14="","", TODAY()-$Q14) | AD14: =IF($B14="","",IF(ISNUMBER($T14),$T14,IF(OR(NOT(ISNUMBER($Q14)),$S14=""),"",IFERROR(IF(ISNUMBER(INDEX(Lists!$AJ$2:$AJ$7,MATCH($S14,Lists!$AI$2:$AI$7,0))),$Q14+INDEX(Lists!$AJ$2:$AJ$7,MATCH($S14,Lists!$AI$2:$AI$7,0)),""),"")))) | AE14: =IF($B14="","",IF(AND(ISNUMBER($AD14),N($AD14)<TODAY(),$N14<>"Done",$N14<>"Won't Fix",$N14<>"Duplicate"),"Yes","No")) | AG14: =IF($AF14="","",IFERROR(VLOOKUP($AF14,'Application Portfolio'!$A$2:$B$1000,2,FALSE()),"Unknown App ID")) | AH14: =IF(OR($B14="",$AF14=""),"",IFERROR(VLOOKUP($AF14,'Application Portfolio'!$A$2:$AB$1000,28,FALSE()),""))
L15: =IF(OR($B15="", $H15="", $I15="", $J15="", $K15=""),"",ROUND((VLOOKUP($H15,Lists!$E$2:$F$5,2,FALSE())*VLOOKUP($I15,Lists!$H$2:$I$4,2,FALSE())*VLOOKUP($J15,Lists!$K$2:$L$4,2,FALSE()))/VLOOKUP($K15,Lists!$N$2:$O$6,2,FALSE()),2)) | M15: =IF($B15="","",IF($AC15<>"",$AC15,IF($H15="Critical","P0",IF(NOT(ISNUMBER($L15)),"",IF($L15>=Lists!$AM$2,"P0",IF($L15>=Lists!$AM$3,"P1",IF($L15>=Lists!$AM$4,"P2","P3"))))))) | R15: =IF($Q15="","", TODAY()-$Q15) | AD15: =IF($B15="","",IF(ISNUMBER($T15),$T15,IF(OR(NOT(ISNUMBER($Q15)),$S15=""),"",IFERROR(IF(ISNUMBER(INDEX(Lists!$AJ$2:$AJ$7,MATCH($S15,Lists!$AI$2:$AI$7,0))),$Q15+INDEX(Lists!$AJ$2:$AJ$7,MATCH($S15,Lists!$AI$2:$AI$7,0)),""),"")))) | AE15: =IF($B15="","",IF(AND(ISNUMBER($AD15),N($AD15)<TODAY(),$N15<>"Done",$N15<>"Won't Fix",$N15<>"Duplicate"),"Yes","No")) | AG15: =IF($AF15="","",IFERROR(VLOOKUP($AF15,'Application Portfolio'!$A$2:$B$1000,2,FALSE()),"Unknown App ID")) | AH15: =IF(OR($B15="",$AF15=""),"",IFERROR(VLOOKUP($AF15,'Application Portfolio'!$A$2:$AB$1000,28,FALSE()),""))
L16: =IF(OR($B16="", $H16="", $I16="", $J16="", $K16=""),"",ROUND((VLOOKUP($H16,Lists!$E$2:$F$5,2,FALSE())*VLOOKUP($I16,Lists!$H$2:$I$4,2,FALSE())*VLOOKUP($J16,Lists!$K$2:$L$4,2,FALSE()))/VLOOKUP($K16,Lists!$N$2:$O$6,2,FALSE()),2)) | M16: =IF($B16="","",IF($AC16<>"",$AC16,IF($H16="Critical","P0",IF(NOT(ISNUMBER($L16)),"",IF($L16>=Lists!$AM$2,"P0",IF($L16>=Lists!$AM$3,"P1",IF($L16>=Lists!$AM$4,"P2","P3"))))))) | R16: =IF($Q16="","", TODAY()-$Q16) | AD16: =IF($B16="","",IF(ISNUMBER($T16),$T16,IF(OR(NOT(ISNUMBER($Q16)),$S16=""),"",IFERROR(IF(ISNUMBER(INDEX(Lists!$AJ$2:$AJ$7,MATCH($S16,Lists!$AI$2:$AI$7,0))),$Q16+INDEX(Lists!$AJ$2:$AJ$7,MATCH($S16,Lists!$AI$2:$AI$7,0)),""),"")))) | AE16: =IF($B16="","",IF(AND(ISNUMBER($AD16),N($AD16)<TODAY(),$N16<>"Done",$N16<>"Won't Fix",$N16<>"Duplicate"),"Yes","No")) | AG16: =IF($AF16="","",IFERROR(VLOOKUP($AF16,'Application Portfolio'!$A$2:$B$1000,2,FALSE()),"Unknown App ID")) | AH16: =IF(OR($B16="",$AF16=""),"",IFERROR(VLOOKUP($AF16,'Application Portfolio'!$A$2:$AB$1000,28,FALSE()),""))
L17: =IF(OR($B17="", $H17="", $I17="", $J17="", $K17=""),"",ROUND((VLOOKUP($H17,Lists!$E$2:$F$5,2,FALSE())*VLOOKUP($I17,Lists!$H$2:$I$4,2,FALSE())*VLOOKUP($J17,Lists!$K$2:$L$4,2,FALSE()))/VLOOKUP($K17,Lists!$N$2:$O$6,2,FALSE()),2)) | M17: =IF($B17="","",IF($AC17<>"",$AC17,IF($H17="Critical","P0",IF(NOT(ISNUMBER($L17)),"",IF($L17>=Lists!$AM$2,"P0",IF($L17>=Lists!$AM$3,"P1",IF($L17>=Lists!$AM$4,"P2","P3"))))))) | R17: =IF($Q17="","", TODAY()-$Q17) | AD17: =IF($B17="","",IF(ISNUMBER($T17),$T17,IF(OR(NOT(ISNUMBER($Q17)),$S17=""),"",IFERROR(IF(ISNUMBER(INDEX(Lists!$AJ$2:$AJ$7,MATCH($S17,Lists!$AI$2:$AI$7,0))),$Q17+INDEX(Lists!$AJ$2:$AJ$7,MATCH($S17,Lists!$AI$2:$AI$7,0)),""),"")))) | AE17: =IF($B17="","",IF(AND(ISNUMBER($AD17),N($AD17)<TODAY(),$N17<>"Done",$N17<>"Won't Fix",$N17<>"Duplicate"),"Yes","No")) | AG17: =IF($AF17="","",IFERROR(VLOOKUP($AF17,'Application Portfolio'!$A$2:$B$1000,2,FALSE()),"Unknown App ID")) | AH17: =IF(OR($B17="",$AF17=""),"",IFERROR(VLOOKUP($AF17,'Application Portfolio'!$A$2:$AB$1000,28,FALSE()),""))
L18: =IF(OR($B18="", $H18="", $I18="", $J18="", $K18=""),"",ROUND((VLOOKUP($H18,Lists!$E$2:$F$5,2,FALSE())*VLOOKUP($I18,Lists!$H$2:$I$4,2,FALSE())*VLOOKUP($J18,Lists!$K$2:$L$4,2,FALSE()))/VLOOKUP($K18,Lists!$N$2:$O$6,2,FALSE()),2)) | M18: =IF($B18="","",IF($AC18<>"",$AC18,IF($H18="Critical","P0",IF(NOT(ISNUMBER($L18)),"",IF($L18>=Lists!$AM$2,"P0",IF($L18>=Lists!$AM$3,"P1",IF($L18>=Lists!$AM$4,"P2","P3"))))))) | R18: =IF($Q18="","", TODAY()-$Q18) | AD18: =IF($B18="","",IF(ISNUMBER($T18),$T18,IF(OR(NOT(ISNUMBER($Q18)),$S18=""),"",IFERROR(IF(ISNUMBER(INDEX(Lists!$AJ$2:$AJ$7,MATCH($S18,Lists!$AI$2:$AI$7,0))),$Q18+INDEX(Lists!$AJ$2:$AJ$7,MATCH($S18,Lists!$AI$2:$AI$7,0)),""),"")))) | AE18: =IF($B18="","",IF(AND(ISNUMBER($AD18),N($AD18)<TODAY(),$N18<>"Done",$N18<>"Won't Fix",$N18<>"Duplicate"),"Yes","No")) | AG18: =IF($AF18="","",IFERROR(VLOOKUP($AF18,'Application Portfolio'!$A$2:$B$1000,2,FALSE()),"Unknown App ID")) | AH18: =IF(OR($B18="",$AF18=""),"",IFERROR(VLOOKUP($AF18,'Application Portfolio'!$A$2:$AB$1000,28,FALSE()),""))
L19: =IF(OR($B19="", $H19="", $I19="", $J19="", $K19=""),"",ROUND((VLOOKUP($H19,Lists!$E$2:$F$5,2,FALSE())*VLOOKUP($I19,Lists!$H$2:$I$4,2,FALSE())*VLOOKUP($J19,Lists!$K$2:$L$4,2,FALSE()))/VLOOKUP($K19,Lists!$N$2:$O$6,2,FALSE()),2)) | M19: =IF($B19="","",IF($AC19<>"",$AC19,IF($H19="Critical","P0",IF(NOT(ISNUMBER($L19)),"",IF($L19>=Lists!$AM$2,"P0",IF($L19>=Lists!$AM$3,"P1",IF($L19>=Lists!$AM$4,"P2","P3"))))))) | R19: =IF($Q19="","", TODAY()-$Q19) | AD19: =IF($B19="","",IF(ISNUMBER($T19),$T19,IF(OR(NOT(ISNUMBER($Q19)),$S19=""),"",IFERROR(IF(ISNUMBER(INDEX(Lists!$AJ$2:$AJ$7,MATCH($S19,Lists!$AI$2:$AI$7,0))),$Q19+INDEX(Lists!$AJ$2:$AJ$7,MATCH($S19,Lists!$AI$2:$AI$7,0)),""),"")))) | AE19: =IF($B19="","",IF(AND(ISNUMBER($AD19),N($AD19)<TODAY(),$N19<>"Done",$N19<>"Won't Fix",$N19<>"Duplicate"),"Yes","No")) | AG19: =IF($AF19="","",IFERROR(VLOOKUP($AF19,'Application Portfolio'!$A$2:$B$1000,2,FALSE()),"Unknown App ID")) | AH19: =IF(OR($B19="",$AF19=""),"",IFERROR(VLOOKUP($AF19,'Application Portfolio'!$A$2:$AB$1000,28,FALSE()),""))
L20: =IF(OR($B20="", $H20="", $I20="", $J20="", $K20=""),"",ROUND((VLOOKUP($H20,Lists!$E$2:$F$5,2,FALSE())*VLOOKUP($I20,Lists!$H$2:$I$4,2,FALSE())*VLOOKUP($J20,Lists!$K$2:$L$4,2,FALSE()))/VLOOKUP($K20,Lists!$N$2:$O$6,2,FALSE()),2)) | M20: =IF($B20="","",IF($AC20<>"",$AC20,IF($H20="Critical","P0",IF(NOT(ISNUMBER($L20)),"",IF($L20>=Lists!$AM$2,"P0",IF($L20>=Lists!$AM$3,"P1",IF($L20>=Lists!$AM$4,"P2","P3"))))))) | R20: =IF($Q20="","", TODAY()-$Q20) | AD20: =IF($B20="","",IF(ISNUMBER($T20),$T20,IF(OR(NOT(ISNUMBER($Q20)),$S20=""),"",IFERROR(IF(ISNUMBER(INDEX(Lists!$AJ$2:$AJ$7,MATCH($S20,Lists!$AI$2:$AI$7,0))),$Q20+INDEX(Lists!$AJ$2:$AJ$7,MATCH($S20,Lists!$AI$2:$AI$7,0)),""),"")))) | AE20: =IF($B20="","",IF(AND(ISNUMBER($AD20),N($AD20)<TODAY(),$N20<>"Done",$N20<>"Won't Fix",$N20<>"Duplicate"),"Yes","No")) | AG20: =IF($AF20="","",IFERROR(VLOOKUP($AF20,'Application Portfolio'!$A$2:$B$1000,2,FALSE()),"Unknown App ID")) | AH20: =IF(OR($B20="",$AF20=""),"",IFERROR(VLOOKUP($AF20,'Application Portfolio'!$A$2:$AB$1000,28,FALSE()),""))
... L1000: =IF(OR($B1000="", $H1000="", $I1000="", $J1000="", $K1000=""),"",ROUND((VLOOKUP($H1000,Lists!$E$2:$F$5,2,FALSE())*VLOOKUP($I1000,Lists!$H$2:$I$4,2,FALSE())*VLOOKUP($J1000,Lists!$K$2:$L$4,2,FALSE()))/VLOOKUP($K1000,Lists!$N$2:$O$6,2,FALSE()),2)) | M1000: =IF($B1000="","",IF($AC1000<>"",$AC1000,IF($H1000="Critical","P0",IF(NOT(ISNUMBER($L1000)),"",IF($L1000>=Lists!$AM$2,"P0",IF($L1000>=Lists!$AM$3,"P1",IF($L1000>=Lists!$AM$4,"P2","P3"))))))) | R1000: =IF($Q1000="","", TODAY()-$Q1000) | AD1000: =IF($B1000="","",IF(ISNUMBER($T1000),$T1000,IF(OR(NOT(ISNUMBER($Q1000)),$S1000=""),"",IFERROR(IF(ISNUMBER(INDEX(Lists!$AJ$2:$AJ$7,MATCH($S1000,Lists!$AI$2:$AI$7,0))),$Q1000+INDEX(Lists!$AJ$2:$AJ$7,MATCH($S1000,Lists!$AI$2:$AI$7,0)),""),"")))) | AE1000: =IF($B1000="","",IF(AND(ISNUMBER($AD1000),N($AD1000)<TODAY(),$N1000<>"Done",$N1000<>"Won't Fix",$N1000<>"Duplicate"),"Yes","No")) | AG1000: =IF($AF1000="","",IFERROR(VLOOKUP($AF1000,'Application Portfolio'!$A$2:$B$1000,2,FALSE()),"Unknown App ID")) | AH1000: =IF(OR($B1000="",$AF1000=""),"",IFERROR(VLOOKUP($AF1000,'Application Portfolio'!$A$2:$AB$1000,28,FALSE()),""))

Sheet Risk Register
A1: Risk ID | B1: App ID | C1: Application Name | D1: Cybersecurity Risk (1-5) | E1: Compliance Risk (1-5) | F1: Operational Resilience (1-5) | G1: Vendor Risk (1-5) | H1: Knowledge Concentration (1-5) | I1: Risk Score (R) | J1: Owner | K1: Last Updated | L1: Notes
A2: R-0001 | B2: APM-0001 | C2: =IF($B2="","",IFERROR(VLOOKUP($B2,'Application Portfolio'!$A$2:$B$1000,2,FALSE()),"")) -> Customer Portal | D2: 5 | E2: 4 | F2: 3 | G2: 2 | H2: 3 | I2: =IF(OR($B2="", $D2="", $E2="", $F2="", $G2="", $H2=""),"",ROUND(($D2*Lists!$AD$20)+($E2*Lists!$AD$21)+($F2*Lists!$AD$22)+($G2*Lists!$AD$23)+($H2*Lists!$AD$24),2)) -> 3.4 | J2: Security Office | K2: 46127 | L2: High cyber risk due to exposed auth paths
A3: R-0002 | B3: APM-0002 | C3: =IF($B3="","",IFERROR(VLOOKUP($B3,'Application Portfolio'!$A$2:$B$1000,2,FALSE()),"")) -> Order Management System | D3: 2 | E3: 2 | F3: 3 | G3: 2 | H3: 2 | I3: =IF(OR($B3="", $D3="", $E3="", $F3="", $G3="", $H3=""),"",ROUND(($D3*Lists!$AD$20)+($E3*Lists!$AD$21)+($F3*Lists!$AD$22)+($G3*Lists!$AD$23)+($H3*Lists!$AD$24),2)) -> 2.2 | J3: J. Park | K3: 46127 | L3: Stable, well-managed
A4: R-0003 | B4: APM-0003 | C4: =IF($B4="","",IFERROR(VLOOKUP($B4,'Application Portfolio'!$A$2:$B$1000,2,FALSE()),"")) -> Payment Processor | D4: 4 | E4: 5 | F4: 4 | G4: 3 | H4: 4 | I4: =IF(OR($B4="", $D4="", $E4="", $F4="", $G4="", $H4=""),"",ROUND(($D4*Lists!$AD$20)+($E4*Lists!$AD$21)+($F4*Lists!$AD$22)+($G4*Lists!$AD$23)+($H4*Lists!$AD$24),2)) -> 4 | J4: R. Singh | K4: 46127 | L4: Compliance scope high, single-threaded ownership
A5: R-0004 | B5: APM-0004 | C5: =IF($B5="","",IFERROR(VLOOKUP($B5,'Application Portfolio'!$A$2:$B$1000,2,FALSE()),"")) -> Legacy CRM | D5: 3 | E5: 3 | F5: 4 | G5: 5 | H5: 5 | I5: =IF(OR($B5="", $D5="", $E5="", $F5="", $G5="", $H5=""),"",ROUND(($D5*Lists!$AD$20)+($E5*Lists!$AD$21)+($F5*Lists!$AD$22)+($G5*Lists!$AD$23)+($H5*Lists!$AD$24),2)) -> 4 | J5: M. Chen | K5: 46127 | L5: Vendor EOL announced; no internal expertise left
A6: R-0005 | B6: APM-0005 | C6: =IF($B6="","",IFERROR(VLOOKUP($B6,'Application Portfolio'!$A$2:$B$1000,2,FALSE()),"")) -> Marketing Analytics | D6: 2 | E6: 2 | F6: 2 | G6: 2 | H6: 3 | I6: =IF(OR($B6="", $D6="", $E6="", $F6="", $G6="", $H6=""),"",ROUND(($D6*Lists!$AD$20)+($E6*Lists!$AD$21)+($F6*Lists!$AD$22)+($G6*Lists!$AD$23)+($H6*Lists!$AD$24),2)) -> 2.2 | J6: L. Ramirez | K6: 46127 | L6: Low risk overall
A7: R-0006 | B7: APM-0006 | C7: =IF($B7="","",IFERROR(VLOOKUP($B7,'Application Portfolio'!$A$2:$B$1000,2,FALSE()),"")) -> Financial Reconciliation | D7: 4 | E7: 3 | F7: 4 | G7: 2 | H7: 3 | I7: =IF(OR($B7="", $D7="", $E7="", $F7="", $G7="", $H7=""),"",ROUND(($D7*Lists!$AD$20)+($E7*Lists!$AD$21)+($F7*Lists!$AD$22)+($G7*Lists!$AD$23)+($H7*Lists!$AD$24),2)) -> 3.2 | J7: K. Osei | K7: 46127 | L7: Ops resilience concerns - no DR tested
A8: R-0007 | B8: APM-0007 | C8: =IF($B8="","",IFERROR(VLOOKUP($B8,'Application Portfolio'!$A$2:$B$1000,2,FALSE()),"")) -> Partner API Gateway | D8: 3 | E8: 4 | F8: 3 | G8: 3 | H8: 2 | I8: =IF(OR($B8="", $D8="", $E8="", $F8="", $G8="", $H8=""),"",ROUND(($D8*Lists!$AD$20)+($E8*Lists!$AD$21)+($F8*Lists!$AD$22)+($G8*Lists!$AD$23)+($H8*Lists!$AD$24),2)) -> 3 | J8: T. Morgan | K8: 46127 | L8: Moderate - compliance attention needed
I9: =IF(OR($B9="", $D9="", $E9="", $F9="", $G9="", $H9=""),"",ROUND(($D9*Lists!$AD$20)+($E9*Lists!$AD$21)+($F9*Lists!$AD$22)+($G9*Lists!$AD$23)+($H9*Lists!$AD$24),2))
I10: =IF(OR($B10="", $D10="", $E10="", $F10="", $G10="", $H10=""),"",ROUND(($D10*Lists!$AD$20)+($E10*Lists!$AD$21)+($F10*Lists!$AD$22)+($G10*Lists!$AD$23)+($H10*Lists!$AD$24),2))
I11: =IF(OR($B11="", $D11="", $E11="", $F11="", $G11="", $H11=""),"",ROUND(($D11*Lists!$AD$20)+($E11*Lists!$AD$21)+($F11*Lists!$AD$22)+($G11*Lists!$AD$23)+($H11*Lists!$AD$24),2))
I12: =IF(OR($B12="", $D12="", $E12="", $F12="", $G12="", $H12=""),"",ROUND(($D12*Lists!$AD$20)+($E12*Lists!$AD$21)+($F12*Lists!$AD$22)+($G12*Lists!$AD$23)+($H12*Lists!$AD$24),2))
I13: =IF(OR($B13="", $D13="", $E13="", $F13="", $G13="", $H13=""),"",ROUND(($D13*Lists!$AD$20)+($E13*Lists!$AD$21)+($F13*Lists!$AD$22)+($G13*Lists!$AD$23)+($H13*Lists!$AD$24),2))
I14: =IF(OR($B14="", $D14="", $E14="", $F14="", $G14="", $H14=""),"",ROUND(($D14*Lists!$AD$20)+($E14*Lists!$AD$21)+($F14*Lists!$AD$22)+($G14*Lists!$AD$23)+($H14*Lists!$AD$24),2))
I15: =IF(OR($B15="", $D15="", $E15="", $F15="", $G15="", $H15=""),"",ROUND(($D15*Lists!$AD$20)+($E15*Lists!$AD$21)+($F15*Lists!$AD$22)+($G15*Lists!$AD$23)+($H15*Lists!$AD$24),2))
I16: =IF(OR($B16="", $D16="", $E16="", $F16="", $G16="", $H16=""),"",ROUND(($D16*Lists!$AD$20)+($E16*Lists!$AD$21)+($F16*Lists!$AD$22)+($G16*Lists!$AD$23)+($H16*Lists!$AD$24),2))
I17: =IF(OR($B17="", $D17="", $E17="", $F17="", $G17="", $H17=""),"",ROUND(($D17*Lists!$AD$20)+($E17*Lists!$AD$21)+($F17*Lists!$AD$22)+($G17*Lists!$AD$23)+($H17*Lists!$AD$24),2))
I18: =IF(OR($B18="", $D18="", $E18="", $F18="", $G18="", $H18=""),"",ROUND(($D18*Lists!$AD$20)+($E18*Lists!$AD$21)+($F18*Lists!$AD$22)+($G18*Lists!$AD$23)+($H18*Lists!$AD$24),2))
I19: =IF(OR($B19="", $D19="", $E19="", $F19="", $G19="", $H19=""),"",ROUND(($D19*Lists!$AD$20)+($E19*Lists!$AD$21)+($F19*Lists!$AD$22)+($G19*Lists!$AD$23)+($H19*Lists!$AD$24),2))
I20: =IF(OR($B20="", $D20="", $E20="", $F20="", $G20="", $H20=""),"",ROUND(($D20*Lists!$AD$20)+($E20*Lists!$AD$21)+($F20*Lists!$AD$22)+($G20*Lists!$AD$23)+($H20*Lists!$AD$24),2))
... I31: =IF(OR($B31="", $D31="", $E31="", $F31="", $G31="", $H31=""),"",ROUND(($D31*Lists!$AD$20)+($E31*Lists!$AD$21)+($F31*Lists!$AD$22)+($G31*Lists!$AD$23)+($H31*Lists!$AD$24),2))
C32: =IF($B32="","",IFERROR(VLOOKUP($B32,'Application Portfolio'!$A$2:$B$1000,2,FALSE()),"")) | I32: =IF(OR($B32="", $D32="", $E32="", $F32="", $G32="", $H32=""),"",ROUND(($D32*Lists!$AD$20)+($E32*Lists!$AD$21)+($F32*Lists!$AD$22)+($G32*Lists!$AD$23)+($H32*Lists!$AD$24),2))
C33: =IF($B33="","",IFERROR(VLOOKUP($B33,'Application Portfolio'!$A$2:$B$1000,2,FALSE()),"")) | I33: =IF(OR($B33="", $D33="", $E33="", $F33="", $G33="", $H33=""),"",ROUND(($D33*Lists!$AD$20)+($E33*Lists!$AD$21)+($F33*Lists!$AD$22)+($G33*Lists!$AD$23)+($H33*Lists!$AD$24),2))
C34: =IF($B34="","",IFERROR(VLOOKUP($B34,'Application Portfolio'!$A$2:$B$1000,2,FALSE()),"")) | I34: =IF(OR($B34="", $D34="", $E34="", $F34="", $G34="", $H34=""),"",ROUND(($D34*Lists!$AD$20)+($E34*Lists!$AD$21)+($F34*Lists!$AD$22)+($G34*Lists!$AD$23)+($H34*Lists!$AD$24),2))
C35: =IF($B35="","",IFERROR(VLOOKUP($B35,'Application Portfolio'!$A$2:$B$1000,2,FALSE()),"")) | I35: =IF(OR($B35="", $D35="", $E35="", $F35="", $G35="", $H35=""),"",ROUND(($D35*Lists!$AD$20)+($E35*Lists!$AD$21)+($F35*Lists!$AD$22)+($G35*Lists!$AD$23)+($H35*Lists!$AD$24),2))
C36: =IF($B36="","",IFERROR(VLOOKUP($B36,'Application Portfolio'!$A$2:$B$1000,2,FALSE()),"")) | I36: =IF(OR($B36="", $D36="", $E36="", $F36="", $G36="", $H36=""),"",ROUND(($D36*Lists!$AD$20)+($E36*Lists!$AD$21)+($F36*Lists!$AD$22)+($G36*Lists!$AD$23)+($H36*Lists!$AD$24),2))
C37: =IF($B37="","",IFERROR(VLOOKUP($B37,'Application Portfolio'!$A$2:$B$1000,2,FALSE()),"")) | I37: =IF(OR($B37="", $D37="", $E37="", $F37="", $G37="", $H37=""),"",ROUND(($D37*Lists!$AD$20)+($E37*Lists!$AD$21)+($F37*Lists!$AD$22)+($G37*Lists!$AD$23)+($H37*Lists!$AD$24),2))
C38: =IF($B38="","",IFERROR(VLOOKUP($B38,'Application Portfolio'!$A$2:$B$1000,2,FALSE()),"")) | I38: =IF(OR($B38="", $D38="", $E38="", $F38="", $G38="", $H38=""),"",ROUND(($D38*Lists!$AD$20)+($E38*Lists!$AD$21)+($F38*Lists!$AD$22)+($G38*Lists!$AD$23)+($H38*Lists!$AD$24),2))
C39: =IF($B39="","",IFERROR(VLOOKUP($B39,'Application Portfolio'!$A$2:$B$1000,2,FALSE()),"")) | I39: =IF(OR($B39="", $D39="", $E39="", $F39="", $G39="", $H39=""),"",ROUND(($D39*Lists!$AD$20)+($E39*Lists!$AD$21)+($F39*Lists!$AD$22)+($G39*Lists!$AD$23)+($H39*Lists!$AD$24),2))
C40: =IF($B40="","",IFERROR(VLOOKUP($B40,'Application Portfolio'!$A$2:$B$1000,2,FALSE()),"")) | I40: =IF(OR($B40="", $D40="", $E40="", $F40="", $G40="", $H40=""),"",ROUND(($D40*Lists!$AD$20)+($E40*Lists!$AD$21)+($F40*Lists!$AD$22)+($G40*Lists!$AD$23)+($H40*Lists!$AD$24),2))
C41: =IF($B41="","",IFERROR(VLOOKUP($B41,'Application Portfolio'!$A$2:$B$1000,2,FALSE()),"")) | I41: =IF(OR($B41="", $D41="", $E41="", $F41="", $G41="", $H41=""),"",ROUND(($D41*Lists!$AD$20)+($E41*Lists!$AD$21)+($F41*Lists!$AD$22)+($G41*Lists!$AD$23)+($H41*Lists!$AD$24),2))
C42: =IF($B42="","",IFERROR(VLOOKUP($B42,'Application Portfolio'!$A$2:$B$1000,2,FALSE()),"")) | I42: =IF(OR($B42="", $D42="", $E42="", $F42="", $G42="", $H42=""),"",ROUND(($D42*Lists!$AD$20)+($E42*Lists!$AD$21)+($F42*Lists!$AD$22)+($G42*Lists!$AD$23)+($H42*Lists!$AD$24),2))
C43: =IF($B43="","",IFERROR(VLOOKUP($B43,'Application Portfolio'!$A$2:$B$1000,2,FALSE()),"")) | I43: =IF(OR($B43="", $D43="", $E43="", $F43="", $G43="", $H43=""),"",ROUND(($D43*Lists!$AD$20)+($E43*Lists!$AD$21)+($F43*Lists!$AD$22)+($G43*Lists!$AD$23)+($H43*Lists!$AD$24),2))
... C1000: =IF($B1000="","",IFERROR(VLOOKUP($B1000,'Application Portfolio'!$A$2:$B$1000,2,FALSE()),"")) | I1000: =IF(OR($B1000="", $D1000="", $E1000="", $F1000="", $G1000="", $H1000=""),"",ROUND(($D1000*Lists!$AD$20)+($E1000*Lists!$AD$21)+($F1000*Lists!$AD$22)+($G1000*Lists!$AD$23)+($H1000*Lists!$AD$24),2))

Sheet Application Portfolio
A1: App ID | B1: Application Name | C1: Description | D1: Product/Service (Capability) | E1: Business Owner | F1: IT Owner | G1: Vendor | H1: Hosting Model | I1: Strategic Alignment (1-5) | J1: Clinical / Business Criticality (1-5) | K1: User Reach & Dependency (1-5) | L1: Differentiation (1-5) | M1: Regulatory Necessity (1-5) | N1: Business Value (BV) | O1: Risk Score (R) | P1: Annual Run Cost (1-5) | Q1: Cost Trend (1-5) | R1: Cost Transparency (1-5) | S1: Modernization Cost (1-5) | T1: Cost Score (C) | U1: Technology Currency (1-5) | V1: Architecture Quality (1-5) | W1: Integration Complexity (1-5) | X1: Data Architecture Fit (1-5) | Y1: Technical Debt (1-5) | Z1: Technical Health (TH) | AA1: Composite Portfolio Score (CPS) | AB1: TIME Classification | AC1: Clinical Criticality Flag | AD1: Compliance Exposure Flag | AE1: Quadrant (Value vs Risk) | AF1: Notes | AG1: Total Annual Cost ($) | AH1: Open Debt Items | AI1: Open Debt Score
A2: APM-0001 | B2: Customer Portal | C2: Patient and member self-service portal: appointments, bills, statements, and secure messaging. | D2: Patient Engagement | E2: VP Digital Health | F2: J. Park | G2: In-house | H2: Public Cloud | I2: 5 | J2: 5 | K2: 5 | L2: 4 | M2: 3 | N2: =IF(OR($B2="", $I2="", $J2="", $K2="", $L2="", $M2=""),"",ROUND(($I2*Lists!$AD$2)+($J2*Lists!$AD$3)+($K2*Lists!$AD$4)+($L2*Lists!$AD$5)+($M2*Lists!$AD$6),2)) -> 4.4 | O2: =IF($A2="","",IFERROR(VLOOKUP($A2,'Risk Register'!$B$2:$I$1000,8,FALSE()),"")) -> 3.4 | P2: 4 | Q2: 4 | R2: 3 | S2: 4 | T2: =IF(OR($B2="", $P2="", $Q2="", $R2="", $S2=""),"",ROUND(($P2*Lists!$AD$7)+($Q2*Lists!$AD$8)+($R2*Lists!$AD$9)+($S2*Lists!$AD$10),2)) -> 3.75 | U2: 2 | V2: 2 | W2: 2 | X2: 3 | Y2: 2 | Z2: =IF(OR($B2="", $U2="", $V2="", $W2="", $X2="", $Y2=""),"",ROUND(($U2*Lists!$AD$11)+($V2*Lists!$AD$12)+($W2*Lists!$AD$13)+($X2*Lists!$AD$14)+($Y2*Lists!$AD$15),2)) -> 2.2 | AA2: =IF(OR($B2="", $N2="", $O2="", $T2="", $Z2=""),"",ROUND(($N2*Lists!$AD$16)-($O2*Lists!$AD$17)-($T2*Lists!$AD$18)+($Z2*Lists!$AD$19),2)) -> -0.14 | AB2: =IF(OR($B2="", $N2="", $Z2=""),"",IF($N2>=Lists!$AG$2,IF($Z2>=Lists!$AG$3,"Invest","Migrate"),IF($Z2>=Lists!$AG$3,"Tolerate","Eliminate"))) -> Migrate | AC2: =IF($B2="","",IF($J2>=4,"Yes","")) -> Yes | AD2: =IF($A2="","",IFERROR(IF(VLOOKUP($A2,'Risk Register'!$B$2:$H$1000,4,FALSE())>=4,"Yes",""),"")) -> Yes | AE2: =IF(OR($N2="", $O2=""),"",IF($N2>=Lists!$AG$2,IF($O2>=Lists!$AG$4,"High Value / High Risk","High Value / Low Risk"),IF($O2>=Lists!$AG$4,"Low Value / High Risk","Low Value / Low Risk"))) -> High Value / Low Risk | AH2: =IF($B2="","",COUNTIFS('Debt Backlog'!$AF$2:$AF$1000,$A2,'Debt Backlog'!$B$2:$B$1000,"<>",'Debt Backlog'!$N$2:$N$1000,"<>Done",'Debt Backlog'!$N$2:$N$1000,"<>Won't Fix",'Debt Backlog'!$N$2:$N$1000,"<>Duplicate")) -> 2 | AI2: =IF($B2="","",ROUND(SUMIFS('Debt Backlog'!$L$2:$L$1000,'Debt Backlog'!$AF$2:$AF$1000,$A2,'Debt Backlog'!$B$2:$B$1000,"<>",'Debt Backlog'!$N$2:$N$1000,"<>Done",'Debt Backlog'!$N$2:$N$1000,"<>Won't Fix",'Debt Backlog'!$N$2:$N$1000,"<>Duplicate"),2)) -> 3.73
A3: APM-0002 | B3: Order Management System | C3: Supply and pharmacy order orchestration across hospitals, clinics, and distribution centers. | D3: Supply Chain | E3: COO | F3: M. Chen | G3: Oracle | H3: Private Cloud | I3: 5 | J3: 5 | K3: 4 | L3: 3 | M3: 3 | N3: =IF(OR($B3="", $I3="", $J3="", $K3="", $L3="", $M3=""),"",ROUND(($I3*Lists!$AD$2)+($J3*Lists!$AD$3)+($K3*Lists!$AD$4)+($L3*Lists!$AD$5)+($M3*Lists!$AD$6),2)) -> 4 | O3: =IF($A3="","",IFERROR(VLOOKUP($A3,'Risk Register'!$B$2:$I$1000,8,FALSE()),"")) -> 2.2 | P3: 3 | Q3: 3 | R3: 3 | S3: 3 | T3: =IF(OR($B3="", $P3="", $Q3="", $R3="", $S3=""),"",ROUND(($P3*Lists!$AD$7)+($Q3*Lists!$AD$8)+($R3*Lists!$AD$9)+($S3*Lists!$AD$10),2)) -> 3 | U3: 4 | V3: 4 | W3: 4 | X3: 4 | Y3: 3 | Z3: =IF(OR($B3="", $U3="", $V3="", $W3="", $X3="", $Y3=""),"",ROUND(($U3*Lists!$AD$11)+($V3*Lists!$AD$12)+($W3*Lists!$AD$13)+($X3*Lists!$AD$14)+($Y3*Lists!$AD$15),2)) -> 3.8 | AA3: =IF(OR($B3="", $N3="", $O3="", $T3="", $Z3=""),"",ROUND(($N3*Lists!$AD$16)-($O3*Lists!$AD$17)-($T3*Lists!$AD$18)+($Z3*Lists!$AD$19),2)) -> 0.65 | AB3: =IF(OR($B3="", $N3="", $Z3=""),"",IF($N3>=Lists!$AG$2,IF($Z3>=Lists!$AG$3,"Invest","Migrate"),IF($Z3>=Lists!$AG$3,"Tolerate","Eliminate"))) -> Invest | AC3: =IF($B3="","",IF($J3>=4,"Yes","")) -> Yes | AD3: =IF($A3="","",IFERROR(IF(VLOOKUP($A3,'Risk Register'!$B$2:$H$1000,4,FALSE())>=4,"Yes",""),"")) | AE3: =IF(OR($N3="", $O3=""),"",IF($N3>=Lists!$AG$2,IF($O3>=Lists!$AG$4,"High Value / High Risk","High Value / Low Risk"),IF($O3>=Lists!$AG$4,"Low Value / High Risk","Low Value / Low Risk"))) -> High Value / Low Risk | AH3: =IF($B3="","",COUNTIFS('Debt Backlog'!$AF$2:$AF$1000,$A3,'Debt Backlog'!$B$2:$B$1000,"<>",'Debt Backlog'!$N$2:$N$1000,"<>Done",'Debt Backlog'!$N$2:$N$1000,"<>Won't Fix",'Debt Backlog'!$N$2:$N$1000,"<>Duplicate")) -> 1 | AI3: =IF($B3="","",ROUND(SUMIFS('Debt Backlog'!$L$2:$L$1000,'Debt Backlog'!$AF$2:$AF$1000,$A3,'Debt Backlog'!$B$2:$B$1000,"<>",'Debt Backlog'!$N$2:$N$1000,"<>Done",'Debt Backlog'!$N$2:$N$1000,"<>Won't Fix",'Debt Backlog'!$N$2:$N$1000,"<>Duplicate"),2)) -> 3
A4: APM-0003 | B4: Payment Processor | C4: Patient payment gateway: card and HSA payments, payment plans, and fraud screening. | D4: Revenue Cycle | E4: VP Revenue Cycle | F4: R. Singh | G4: In-house | H4: Private Cloud | I4: 5 | J4: 5 | K4: 5 | L4: 5 | M4: 5 | N4: =IF(OR($B4="", $I4="", $J4="", $K4="", $L4="", $M4=""),"",ROUND(($I4*Lists!$AD$2)+($J4*Lists!$AD$3)+($K4*Lists!$AD$4)+($L4*Lists!$AD$5)+($M4*Lists!$AD$6),2)) -> 5 | O4: =IF($A4="","",IFERROR(VLOOKUP($A4,'Risk Register'!$B$2:$I$1000,8,FALSE()),"")) -> 4 | P4: 4 | Q4: 3 | R4: 3 | S4: 4 | T4: =IF(OR($B4="", $P4="", $Q4="", $R4="", $S4=""),"",ROUND(($P4*Lists!$AD$7)+($Q4*Lists!$AD$8)+($R4*Lists!$AD$9)+($S4*Lists!$AD$10),2)) -> 3.5 | U4: 3 | V4: 2 | W4: 2 | X4: 3 | Y4: 2 | Z4: =IF(OR($B4="", $U4="", $V4="", $W4="", $X4="", $Y4=""),"",ROUND(($U4*Lists!$AD$11)+($V4*Lists!$AD$12)+($W4*Lists!$AD$13)+($X4*Lists!$AD$14)+($Y4*Lists!$AD$15),2)) -> 2.4 | AA4: =IF(OR($B4="", $N4="", $O4="", $T4="", $Z4=""),"",ROUND(($N4*Lists!$AD$16)-($O4*Lists!$AD$17)-($T4*Lists!$AD$18)+($Z4*Lists!$AD$19),2)) -> -0.03 | AB4: =IF(OR($B4="", $N4="", $Z4=""),"",IF($N4>=Lists!$AG$2,IF($Z4>=Lists!$AG$3,"Invest","Migrate"),IF($Z4>=Lists!$AG$3,"Tolerate","Eliminate"))) -> Migrate | AC4: =IF($B4="","",IF($J4>=4,"Yes","")) -> Yes | AD4: =IF($A4="","",IFERROR(IF(VLOOKUP($A4,'Risk Register'!$B$2:$H$1000,4,FALSE())>=4,"Yes",""),"")) -> Yes | AE4: =IF(OR($N4="", $O4=""),"",IF($N4>=Lists!$AG$2,IF($O4>=Lists!$AG$4,"High Value / High Risk","High Value / Low Risk"),IF($O4>=Lists!$AG$4,"Low Value / High Risk","Low Value / Low Risk"))) -> High Value / High Risk | AH4: =IF($B4="","",COUNTIFS('Debt Backlog'!$AF$2:$AF$1000,$A4,'Debt Backlog'!$B$2:$B$1000,"<>",'Debt Backlog'!$N$2:$N$1000,"<>Done",'Debt Backlog'!$N$2:$N$1000,"<>Won't Fix",'Debt Backlog'!$N$2:$N$1000,"<>Duplicate")) -> 1 | AI4: =IF($B4="","",ROUND(SUMIFS('Debt Backlog'!$L$2:$L$1000,'Debt Backlog'!$AF$2:$AF$1000,$A4,'Debt Backlog'!$B$2:$B$1000,"<>",'Debt Backlog'!$N$2:$N$1000,"<>Done",'Debt Backlog'!$N$2:$N$1000,"<>Won't Fix",'Debt Backlog'!$N$2:$N$1000,"<>Duplicate"),2)) -> 3
A5: APM-0004 | B5: Legacy CRM | C5: Referral and provider-relations CRM in sunset. Superseded by the new cloud CRM; only 3 users remain. | D5: Provider Relations | E5: VP Network Development | F5: M. Chen | G5: Siebel | H5: On-Premise | I5: 1 | J5: 2 | K5: 1 | L5: 1 | M5: 1 | N5: =IF(OR($B5="", $I5="", $J5="", $K5="", $L5="", $M5=""),"",ROUND(($I5*Lists!$AD$2)+($J5*Lists!$AD$3)+($K5*Lists!$AD$4)+($L5*Lists!$AD$5)+($M5*Lists!$AD$6),2)) -> 1.2 | O5: =IF($A5="","",IFERROR(VLOOKUP($A5,'Risk Register'!$B$2:$I$1000,8,FALSE()),"")) -> 4 | P5: 4 | Q5: 5 | R5: 4 | S5: 5 | T5: =IF(OR($B5="", $P5="", $Q5="", $R5="", $S5=""),"",ROUND(($P5*Lists!$AD$7)+($Q5*Lists!$AD$8)+($R5*Lists!$AD$9)+($S5*Lists!$AD$10),2)) -> 4.5 | U5: 1 | V5: 1 | W5: 2 | X5: 1 | Y5: 1 | Z5: =IF(OR($B5="", $U5="", $V5="", $W5="", $X5="", $Y5=""),"",ROUND(($U5*Lists!$AD$11)+($V5*Lists!$AD$12)+($W5*Lists!$AD$13)+($X5*Lists!$AD$14)+($Y5*Lists!$AD$15),2)) -> 1.2 | AA5: =IF(OR($B5="", $N5="", $O5="", $T5="", $Z5=""),"",ROUND(($N5*Lists!$AD$16)-($O5*Lists!$AD$17)-($T5*Lists!$AD$18)+($Z5*Lists!$AD$19),2)) -> -1.53 | AB5: =IF(OR($B5="", $N5="", $Z5=""),"",IF($N5>=Lists!$AG$2,IF($Z5>=Lists!$AG$3,"Invest","Migrate"),IF($Z5>=Lists!$AG$3,"Tolerate","Eliminate"))) -> Eliminate | AC5: =IF($B5="","",IF($J5>=4,"Yes","")) | AD5: =IF($A5="","",IFERROR(IF(VLOOKUP($A5,'Risk Register'!$B$2:$H$1000,4,FALSE())>=4,"Yes",""),"")) | AE5: =IF(OR($N5="", $O5=""),"",IF($N5>=Lists!$AG$2,IF($O5>=Lists!$AG$4,"High Value / High Risk","High Value / Low Risk"),IF($O5>=Lists!$AG$4,"Low Value / High Risk","Low Value / Low Risk"))) -> Low Value / High Risk | AH5: =IF($B5="","",COUNTIFS('Debt Backlog'!$AF$2:$AF$1000,$A5,'Debt Backlog'!$B$2:$B$1000,"<>",'Debt Backlog'!$N$2:$N$1000,"<>Done",'Debt Backlog'!$N$2:$N$1000,"<>Won't Fix",'Debt Backlog'!$N$2:$N$1000,"<>Duplicate")) -> 0 | AI5: =IF($B5="","",ROUND(SUMIFS('Debt Backlog'!$L$2:$L$1000,'Debt Backlog'!$AF$2:$AF$1000,$A5,'Debt Backlog'!$B$2:$B$1000,"<>",'Debt Backlog'!$N$2:$N$1000,"<>Done",'Debt Backlog'!$N$2:$N$1000,"<>Won't Fix",'Debt Backlog'!$N$2:$N$1000,"<>Duplicate"),2)) -> 0
A6: APM-0005 | B6: Marketing Analytics | C6: Analytics for patient outreach campaigns and service-line marketing on de-identified data. | D6: Marketing | E6: VP Marketing | F6: L. Ramirez | G6: In-house | H6: Public Cloud | I6: 3 | J6: 2 | K6: 2 | L6: 3 | M6: 1 | N6: =IF(OR($B6="", $I6="", $J6="", $K6="", $L6="", $M6=""),"",ROUND(($I6*Lists!$AD$2)+($J6*Lists!$AD$3)+($K6*Lists!$AD$4)+($L6*Lists!$AD$5)+($M6*Lists!$AD$6),2)) -> 2.2 | O6: =IF($A6="","",IFERROR(VLOOKUP($A6,'Risk Register'!$B$2:$I$1000,8,FALSE()),"")) -> 2.2 | P6: 2 | Q6: 2 | R6: 3 | S6: 2 | T6: =IF(OR($B6="", $P6="", $Q6="", $R6="", $S6=""),"",ROUND(($P6*Lists!$AD$7)+($Q6*Lists!$AD$8)+($R6*Lists!$AD$9)+($S6*Lists!$AD$10),2)) -> 2.25 | U6: 4 | V6: 4 | W6: 4 | X6: 4 | Y6: 4 | Z6: =IF(OR($B6="", $U6="", $V6="", $W6="", $X6="", $Y6=""),"",ROUND(($U6*Lists!$AD$11)+($V6*Lists!$AD$12)+($W6*Lists!$AD$13)+($X6*Lists!$AD$14)+($Y6*Lists!$AD$15),2)) -> 4 | AA6: =IF(OR($B6="", $N6="", $O6="", $T6="", $Z6=""),"",ROUND(($N6*Lists!$AD$16)-($O6*Lists!$AD$17)-($T6*Lists!$AD$18)+($Z6*Lists!$AD$19),2)) -> 0.44 | AB6: =IF(OR($B6="", $N6="", $Z6=""),"",IF($N6>=Lists!$AG$2,IF($Z6>=Lists!$AG$3,"Invest","Migrate"),IF($Z6>=Lists!$AG$3,"Tolerate","Eliminate"))) -> Tolerate | AC6: =IF($B6="","",IF($J6>=4,"Yes","")) | AD6: =IF($A6="","",IFERROR(IF(VLOOKUP($A6,'Risk Register'!$B$2:$H$1000,4,FALSE())>=4,"Yes",""),"")) | AE6: =IF(OR($N6="", $O6=""),"",IF($N6>=Lists!$AG$2,IF($O6>=Lists!$AG$4,"High Value / High Risk","High Value / Low Risk"),IF($O6>=Lists!$AG$4,"Low Value / High Risk","Low Value / Low Risk"))) -> Low Value / Low Risk | AH6: =IF($B6="","",COUNTIFS('Debt Backlog'!$AF$2:$AF$1000,$A6,'Debt Backlog'!$B$2:$B$1000,"<>",'Debt Backlog'!$N$2:$N$1000,"<>Done",'Debt Backlog'!$N$2:$N$1000,"<>Won't Fix",'Debt Backlog'!$N$2:$N$1000,"<>Duplicate")) -> 0 | AI6: =IF($B6="","",ROUND(SUMIFS('Debt Backlog'!$L$2:$L$1000,'Debt Backlog'!$AF$2:$AF$1000,$A6,'Debt Backlog'!$B$2:$B$1000,"<>",'Debt Backlog'!$N$2:$N$1000,"<>Done",'Debt Backlog'!$N$2:$N$1000,"<>Won't Fix",'Debt Backlog'!$N$2:$N$1000,"<>Duplicate"),2)) -> 0
A7: APM-0006 | B7: Financial Reconciliation | C7: Nightly reconciliation between patient billing, payments, and the general ledger. | D7: Finance Ops | E7: Controller | F7: K. Osei | G7: In-house | H7: Private Cloud | I7: 4 | J7: 5 | K7: 3 | L7: 2 | M7: 5 | N7: =IF(OR($B7="", $I7="", $J7="", $K7="", $L7="", $M7=""),"",ROUND(($I7*Lists!$AD$2)+($J7*Lists!$AD$3)+($K7*Lists!$AD$4)+($L7*Lists!$AD$5)+($M7*Lists!$AD$6),2)) -> 3.8 | O7: =IF($A7="","",IFERROR(VLOOKUP($A7,'Risk Register'!$B$2:$I$1000,8,FALSE()),"")) -> 3.2 | P7: 3 | Q7: 3 | R7: 2 | S7: 3 | T7: =IF(OR($B7="", $P7="", $Q7="", $R7="", $S7=""),"",ROUND(($P7*Lists!$AD$7)+($Q7*Lists!$AD$8)+($R7*Lists!$AD$9)+($S7*Lists!$AD$10),2)) -> 2.75 | U7: 3 | V7: 3 | W7: 2 | X7: 3 | Y7: 2 | Z7: =IF(OR($B7="", $U7="", $V7="", $W7="", $X7="", $Y7=""),"",ROUND(($U7*Lists!$AD$11)+($V7*Lists!$AD$12)+($W7*Lists!$AD$13)+($X7*Lists!$AD$14)+($Y7*Lists!$AD$15),2)) -> 2.6 | AA7: =IF(OR($B7="", $N7="", $O7="", $T7="", $Z7=""),"",ROUND(($N7*Lists!$AD$16)-($O7*Lists!$AD$17)-($T7*Lists!$AD$18)+($Z7*Lists!$AD$19),2)) -> 0.11 | AB7: =IF(OR($B7="", $N7="", $Z7=""),"",IF($N7>=Lists!$AG$2,IF($Z7>=Lists!$AG$3,"Invest","Migrate"),IF($Z7>=Lists!$AG$3,"Tolerate","Eliminate"))) -> Migrate | AC7: =IF($B7="","",IF($J7>=4,"Yes","")) -> Yes | AD7: =IF($A7="","",IFERROR(IF(VLOOKUP($A7,'Risk Register'!$B$2:$H$1000,4,FALSE())>=4,"Yes",""),"")) | AE7: =IF(OR($N7="", $O7=""),"",IF($N7>=Lists!$AG$2,IF($O7>=Lists!$AG$4,"High Value / High Risk","High Value / Low Risk"),IF($O7>=Lists!$AG$4,"Low Value / High Risk","Low Value / Low Risk"))) -> High Value / Low Risk | AH7: =IF($B7="","",COUNTIFS('Debt Backlog'!$AF$2:$AF$1000,$A7,'Debt Backlog'!$B$2:$B$1000,"<>",'Debt Backlog'!$N$2:$N$1000,"<>Done",'Debt Backlog'!$N$2:$N$1000,"<>Won't Fix",'Debt Backlog'!$N$2:$N$1000,"<>Duplicate")) -> 1 | AI7: =IF($B7="","",ROUND(SUMIFS('Debt Backlog'!$L$2:$L$1000,'Debt Backlog'!$AF$2:$AF$1000,$A7,'Debt Backlog'!$B$2:$B$1000,"<>",'Debt Backlog'!$N$2:$N$1000,"<>Done",'Debt Backlog'!$N$2:$N$1000,"<>Won't Fix",'Debt Backlog'!$N$2:$N$1000,"<>Duplicate"),2)) -> 3.6
A8: APM-0007 | B8: Partner API Gateway | C8: Integration layer exposing FHIR and REST APIs to payers, labs, and partner health systems. | D8: Interoperability | E8: VP Partnerships | F8: T. Morgan | G8: Kong | H8: Public Cloud | I8: 4 | J8: 3 | K8: 3 | L8: 4 | M8: 3 | N8: =IF(OR($B8="", $I8="", $J8="", $K8="", $L8="", $M8=""),"",ROUND(($I8*Lists!$AD$2)+($J8*Lists!$AD$3)+($K8*Lists!$AD$4)+($L8*Lists!$AD$5)+($M8*Lists!$AD$6),2)) -> 3.4 | O8: =IF($A8="","",IFERROR(VLOOKUP($A8,'Risk Register'!$B$2:$I$1000,8,FALSE()),"")) -> 3 | P8: 3 | Q8: 3 | R8: 3 | S8: 3 | T8: =IF(OR($B8="", $P8="", $Q8="", $R8="", $S8=""),"",ROUND(($P8*Lists!$AD$7)+($Q8*Lists!$AD$8)+($R8*Lists!$AD$9)+($S8*Lists!$AD$10),2)) -> 3 | U8: 4 | V8: 4 | W8: 3 | X8: 4 | Y8: 4 | Z8: =IF(OR($B8="", $U8="", $V8="", $W8="", $X8="", $Y8=""),"",ROUND(($U8*Lists!$AD$11)+($V8*Lists!$AD$12)+($W8*Lists!$AD$13)+($X8*Lists!$AD$14)+($Y8*Lists!$AD$15),2)) -> 3.8 | AA8: =IF(OR($B8="", $N8="", $O8="", $T8="", $Z8=""),"",ROUND(($N8*Lists!$AD$16)-($O8*Lists!$AD$17)-($T8*Lists!$AD$18)+($Z8*Lists!$AD$19),2)) -> 0.3 | AB8: =IF(OR($B8="", $N8="", $Z8=""),"",IF($N8>=Lists!$AG$2,IF($Z8>=Lists!$AG$3,"Invest","Migrate"),IF($Z8>=Lists!$AG$3,"Tolerate","Eliminate"))) -> Invest | AC8: =IF($B8="","",IF($J8>=4,"Yes","")) | AD8: =IF($A8="","",IFERROR(IF(VLOOKUP($A8,'Risk Register'!$B$2:$H$1000,4,FALSE())>=4,"Yes",""),"")) -> Yes | AE8: =IF(OR($N8="", $O8=""),"",IF($N8>=Lists!$AG$2,IF($O8>=Lists!$AG$4,"High Value / High Risk","High Value / Low Risk"),IF($O8>=Lists!$AG$4,"Low Value / High Risk","Low Value / Low Risk"))) -> High Value / Low Risk | AH8: =IF($B8="","",COUNTIFS('Debt Backlog'!$AF$2:$AF$1000,$A8,'Debt Backlog'!$B$2:$B$1000,"<>",'Debt Backlog'!$N$2:$N$1000,"<>Done",'Debt Backlog'!$N$2:$N$1000,"<>Won't Fix",'Debt Backlog'!$N$2:$N$1000,"<>Duplicate")) -> 1 | AI8: =IF($B8="","",ROUND(SUMIFS('Debt Backlog'!$L$2:$L$1000,'Debt Backlog'!$AF$2:$AF$1000,$A8,'Debt Backlog'!$B$2:$B$1000,"<>",'Debt Backlog'!$N$2:$N$1000,"<>Done",'Debt Backlog'!$N$2:$N$1000,"<>Won't Fix",'Debt Backlog'!$N$2:$N$1000,"<>Duplicate"),2)) -> 2
N9: =IF(OR($B9="", $I9="", $J9="", $K9="", $L9="", $M9=""),"",ROUND(($I9*Lists!$AD$2)+($J9*Lists!$AD$3)+($K9*Lists!$AD$4)+($L9*Lists!$AD$5)+($M9*Lists!$AD$6),2)) | T9: =IF(OR($B9="", $P9="", $Q9="", $R9="", $S9=""),"",ROUND(($P9*Lists!$AD$7)+($Q9*Lists!$AD$8)+($R9*Lists!$AD$9)+($S9*Lists!$AD$10),2)) | Z9: =IF(OR($B9="", $U9="", $V9="", $W9="", $X9="", $Y9=""),"",ROUND(($U9*Lists!$AD$11)+($V9*Lists!$AD$12)+($W9*Lists!$AD$13)+($X9*Lists!$AD$14)+($Y9*Lists!$AD$15),2)) | AA9: =IF(OR($B9="", $N9="", $O9="", $T9="", $Z9=""),"",ROUND(($N9*Lists!$AD$16)-($O9*Lists!$AD$17)-($T9*Lists!$AD$18)+($Z9*Lists!$AD$19),2)) | AB9: =IF(OR($B9="", $N9="", $Z9=""),"",IF($N9>=Lists!$AG$2,IF($Z9>=Lists!$AG$3,"Invest","Migrate"),IF($Z9>=Lists!$AG$3,"Tolerate","Eliminate"))) | AE9: =IF(OR($N9="", $O9=""),"",IF($N9>=Lists!$AG$2,IF($O9>=Lists!$AG$4,"High Value / High Risk","High Value / Low Risk"),IF($O9>=Lists!$AG$4,"Low Value / High Risk","Low Value / Low Risk"))) | AH9: =IF($B9="","",COUNTIFS('Debt Backlog'!$AF$2:$AF$1000,$A9,'Debt Backlog'!$B$2:$B$1000,"<>",'Debt Backlog'!$N$2:$N$1000,"<>Done",'Debt Backlog'!$N$2:$N$1000,"<>Won't Fix",'Debt Backlog'!$N$2:$N$1000,"<>Duplicate")) | AI9: =IF($B9="","",ROUND(SUMIFS('Debt Backlog'!$L$2:$L$1000,'Debt Backlog'!$AF$2:$AF$1000,$A9,'Debt Backlog'!$B$2:$B$1000,"<>",'Debt Backlog'!$N$2:$N$1000,"<>Done",'Debt Backlog'!$N$2:$N$1000,"<>Won't Fix",'Debt Backlog'!$N$2:$N$1000,"<>Duplicate"),2))
N10: =IF(OR($B10="", $I10="", $J10="", $K10="", $L10="", $M10=""),"",ROUND(($I10*Lists!$AD$2)+($J10*Lists!$AD$3)+($K10*Lists!$AD$4)+($L10*Lists!$AD$5)+($M10*Lists!$AD$6),2)) | T10: =IF(OR($B10="", $P10="", $Q10="", $R10="", $S10=""),"",ROUND(($P10*Lists!$AD$7)+($Q10*Lists!$AD$8)+($R10*Lists!$AD$9)+($S10*Lists!$AD$10),2)) | Z10: =IF(OR($B10="", $U10="", $V10="", $W10="", $X10="", $Y10=""),"",ROUND(($U10*Lists!$AD$11)+($V10*Lists!$AD$12)+($W10*Lists!$AD$13)+($X10*Lists!$AD$14)+($Y10*Lists!$AD$15),2)) | AA10: =IF(OR($B10="", $N10="", $O10="", $T10="", $Z10=""),"",ROUND(($N10*Lists!$AD$16)-($O10*Lists!$AD$17)-($T10*Lists!$AD$18)+($Z10*Lists!$AD$19),2)) | AB10: =IF(OR($B10="", $N10="", $Z10=""),"",IF($N10>=Lists!$AG$2,IF($Z10>=Lists!$AG$3,"Invest","Migrate"),IF($Z10>=Lists!$AG$3,"Tolerate","Eliminate"))) | AE10: =IF(OR($N10="", $O10=""),"",IF($N10>=Lists!$AG$2,IF($O10>=Lists!$AG$4,"High Value / High Risk","High Value / Low Risk"),IF($O10>=Lists!$AG$4,"Low Value / High Risk","Low Value / Low Risk"))) | AH10: =IF($B10="","",COUNTIFS('Debt Backlog'!$AF$2:$AF$1000,$A10,'Debt Backlog'!$B$2:$B$1000,"<>",'Debt Backlog'!$N$2:$N$1000,"<>Done",'Debt Backlog'!$N$2:$N$1000,"<>Won't Fix",'Debt Backlog'!$N$2:$N$1000,"<>Duplicate")) | AI10: =IF($B10="","",ROUND(SUMIFS('Debt Backlog'!$L$2:$L$1000,'Debt Backlog'!$AF$2:$AF$1000,$A10,'Debt Backlog'!$B$2:$B$1000,"<>",'Debt Backlog'!$N$2:$N$1000,"<>Done",'Debt Backlog'!$N$2:$N$1000,"<>Won't Fix",'Debt Backlog'!$N$2:$N$1000,"<>Duplicate"),2))
N11: =IF(OR($B11="", $I11="", $J11="", $K11="", $L11="", $M11=""),"",ROUND(($I11*Lists!$AD$2)+($J11*Lists!$AD$3)+($K11*Lists!$AD$4)+($L11*Lists!$AD$5)+($M11*Lists!$AD$6),2)) | T11: =IF(OR($B11="", $P11="", $Q11="", $R11="", $S11=""),"",ROUND(($P11*Lists!$AD$7)+($Q11*Lists!$AD$8)+($R11*Lists!$AD$9)+($S11*Lists!$AD$10),2)) | Z11: =IF(OR($B11="", $U11="", $V11="", $W11="", $X11="", $Y11=""),"",ROUND(($U11*Lists!$AD$11)+($V11*Lists!$AD$12)+($W11*Lists!$AD$13)+($X11*Lists!$AD$14)+($Y11*Lists!$AD$15),2)) | AA11: =IF(OR($B11="", $N11="", $O11="", $T11="", $Z11=""),"",ROUND(($N11*Lists!$AD$16)-($O11*Lists!$AD$17)-($T11*Lists!$AD$18)+($Z11*Lists!$AD$19),2)) | AB11: =IF(OR($B11="", $N11="", $Z11=""),"",IF($N11>=Lists!$AG$2,IF($Z11>=Lists!$AG$3,"Invest","Migrate"),IF($Z11>=Lists!$AG$3,"Tolerate","Eliminate"))) | AE11: =IF(OR($N11="", $O11=""),"",IF($N11>=Lists!$AG$2,IF($O11>=Lists!$AG$4,"High Value / High Risk","High Value / Low Risk"),IF($O11>=Lists!$AG$4,"Low Value / High Risk","Low Value / Low Risk"))) | AH11: =IF($B11="","",COUNTIFS('Debt Backlog'!$AF$2:$AF$1000,$A11,'Debt Backlog'!$B$2:$B$1000,"<>",'Debt Backlog'!$N$2:$N$1000,"<>Done",'Debt Backlog'!$N$2:$N$1000,"<>Won't Fix",'Debt Backlog'!$N$2:$N$1000,"<>Duplicate")) | AI11: =IF($B11="","",ROUND(SUMIFS('Debt Backlog'!$L$2:$L$1000,'Debt Backlog'!$AF$2:$AF$1000,$A11,'Debt Backlog'!$B$2:$B$1000,"<>",'Debt Backlog'!$N$2:$N$1000,"<>Done",'Debt Backlog'!$N$2:$N$1000,"<>Won't Fix",'Debt Backlog'!$N$2:$N$1000,"<>Duplicate"),2))
N12: =IF(OR($B12="", $I12="", $J12="", $K12="", $L12="", $M12=""),"",ROUND(($I12*Lists!$AD$2)+($J12*Lists!$AD$3)+($K12*Lists!$AD$4)+($L12*Lists!$AD$5)+($M12*Lists!$AD$6),2)) | T12: =IF(OR($B12="", $P12="", $Q12="", $R12="", $S12=""),"",ROUND(($P12*Lists!$AD$7)+($Q12*Lists!$AD$8)+($R12*Lists!$AD$9)+($S12*Lists!$AD$10),2)) | Z12: =IF(OR($B12="", $U12="", $V12="", $W12="", $X12="", $Y12=""),"",ROUND(($U12*Lists!$AD$11)+($V12*Lists!$AD$12)+($W12*Lists!$AD$13)+($X12*Lists!$AD$14)+($Y12*Lists!$AD$15),2)) | AA12: =IF(OR($B12="", $N12="", $O12="", $T12="", $Z12=""),"",ROUND(($N12*Lists!$AD$16)-($O12*Lists!$AD$17)-($T12*Lists!$AD$18)+($Z12*Lists!$AD$19),2)) | AB12: =IF(OR($B12="", $N12="", $Z12=""),"",IF($N12>=Lists!$AG$2,IF($Z12>=Lists!$AG$3,"Invest","Migrate"),IF($Z12>=Lists!$AG$3,"Tolerate","Eliminate"))) | AE12: =IF(OR($N12="", $O12=""),"",IF($N12>=Lists!$AG$2,IF($O12>=Lists!$AG$4,"High Value / High Risk","High Value / Low Risk"),IF($O12>=Lists!$AG$4,"Low Value / High Risk","Low Value / Low Risk"))) | AH12: =IF($B12="","",COUNTIFS('Debt Backlog'!$AF$2:$AF$1000,$A12,'Debt Backlog'!$B$2:$B$1000,"<>",'Debt Backlog'!$N$2:$N$1000,"<>Done",'Debt Backlog'!$N$2:$N$1000,"<>Won't Fix",'Debt Backlog'!$N$2:$N$1000,"<>Duplicate")) | AI12: =IF($B12="","",ROUND(SUMIFS('Debt Backlog'!$L$2:$L$1000,'Debt Backlog'!$AF$2:$AF$1000,$A12,'Debt Backlog'!$B$2:$B$1000,"<>",'Debt Backlog'!$N$2:$N$1000,"<>Done",'Debt Backlog'!$N$2:$N$1000,"<>Won't Fix",'Debt Backlog'!$N$2:$N$1000,"<>Duplicate"),2))
N13: =IF(OR($B13="", $I13="", $J13="", $K13="", $L13="", $M13=""),"",ROUND(($I13*Lists!$AD$2)+($J13*Lists!$AD$3)+($K13*Lists!$AD$4)+($L13*Lists!$AD$5)+($M13*Lists!$AD$6),2)) | T13: =IF(OR($B13="", $P13="", $Q13="", $R13="", $S13=""),"",ROUND(($P13*Lists!$AD$7)+($Q13*Lists!$AD$8)+($R13*Lists!$AD$9)+($S13*Lists!$AD$10),2)) | Z13: =IF(OR($B13="", $U13="", $V13="", $W13="", $X13="", $Y13=""),"",ROUND(($U13*Lists!$AD$11)+($V13*Lists!$AD$12)+($W13*Lists!$AD$13)+($X13*Lists!$AD$14)+($Y13*Lists!$AD$15),2)) | AA13: =IF(OR($B13="", $N13="", $O13="", $T13="", $Z13=""),"",ROUND(($N13*Lists!$AD$16)-($O13*Lists!$AD$17)-($T13*Lists!$AD$18)+($Z13*Lists!$AD$19),2)) | AB13: =IF(OR($B13="", $N13="", $Z13=""),"",IF($N13>=Lists!$AG$2,IF($Z13>=Lists!$AG$3,"Invest","Migrate"),IF($Z13>=Lists!$AG$3,"Tolerate","Eliminate"))) | AE13: =IF(OR($N13="", $O13=""),"",IF($N13>=Lists!$AG$2,IF($O13>=Lists!$AG$4,"High Value / High Risk","High Value / Low Risk"),IF($O13>=Lists!$AG$4,"Low Value / High Risk","Low Value / Low Risk"))) | AH13: =IF($B13="","",COUNTIFS('Debt Backlog'!$AF$2:$AF$1000,$A13,'Debt Backlog'!$B$2:$B$1000,"<>",'Debt Backlog'!$N$2:$N$1000,"<>Done",'Debt Backlog'!$N$2:$N$1000,"<>Won't Fix",'Debt Backlog'!$N$2:$N$1000,"<>Duplicate")) | AI13: =IF($B13="","",ROUND(SUMIFS('Debt Backlog'!$L$2:$L$1000,'Debt Backlog'!$AF$2:$AF$1000,$A13,'Debt Backlog'!$B$2:$B$1000,"<>",'Debt Backlog'!$N$2:$N$1000,"<>Done",'Debt Backlog'!$N$2:$N$1000,"<>Won't Fix",'Debt Backlog'!$N$2:$N$1000,"<>Duplicate"),2))
N14: =IF(OR($B14="", $I14="", $J14="", $K14="", $L14="", $M14=""),"",ROUND(($I14*Lists!$AD$2)+($J14*Lists!$AD$3)+($K14*Lists!$AD$4)+($L14*Lists!$AD$5)+($M14*Lists!$AD$6),2)) | T14: =IF(OR($B14="", $P14="", $Q14="", $R14="", $S14=""),"",ROUND(($P14*Lists!$AD$7)+($Q14*Lists!$AD$8)+($R14*Lists!$AD$9)+($S14*Lists!$AD$10),2)) | Z14: =IF(OR($B14="", $U14="", $V14="", $W14="", $X14="", $Y14=""),"",ROUND(($U14*Lists!$AD$11)+($V14*Lists!$AD$12)+($W14*Lists!$AD$13)+($X14*Lists!$AD$14)+($Y14*Lists!$AD$15),2)) | AA14: =IF(OR($B14="", $N14="", $O14="", $T14="", $Z14=""),"",ROUND(($N14*Lists!$AD$16)-($O14*Lists!$AD$17)-($T14*Lists!$AD$18)+($Z14*Lists!$AD$19),2)) | AB14: =IF(OR($B14="", $N14="", $Z14=""),"",IF($N14>=Lists!$AG$2,IF($Z14>=Lists!$AG$3,"Invest","Migrate"),IF($Z14>=Lists!$AG$3,"Tolerate","Eliminate"))) | AE14: =IF(OR($N14="", $O14=""),"",IF($N14>=Lists!$AG$2,IF($O14>=Lists!$AG$4,"High Value / High Risk","High Value / Low Risk"),IF($O14>=Lists!$AG$4,"Low Value / High Risk","Low Value / Low Risk"))) | AH14: =IF($B14="","",COUNTIFS('Debt Backlog'!$AF$2:$AF$1000,$A14,'Debt Backlog'!$B$2:$B$1000,"<>",'Debt Backlog'!$N$2:$N$1000,"<>Done",'Debt Backlog'!$N$2:$N$1000,"<>Won't Fix",'Debt Backlog'!$N$2:$N$1000,"<>Duplicate")) | AI14: =IF($B14="","",ROUND(SUMIFS('Debt Backlog'!$L$2:$L$1000,'Debt Backlog'!$AF$2:$AF$1000,$A14,'Debt Backlog'!$B$2:$B$1000,"<>",'Debt Backlog'!$N$2:$N$1000,"<>Done",'Debt Backlog'!$N$2:$N$1000,"<>Won't Fix",'Debt Backlog'!$N$2:$N$1000,"<>Duplicate"),2))
N15: =IF(OR($B15="", $I15="", $J15="", $K15="", $L15="", $M15=""),"",ROUND(($I15*Lists!$AD$2)+($J15*Lists!$AD$3)+($K15*Lists!$AD$4)+($L15*Lists!$AD$5)+($M15*Lists!$AD$6),2)) | T15: =IF(OR($B15="", $P15="", $Q15="", $R15="", $S15=""),"",ROUND(($P15*Lists!$AD$7)+($Q15*Lists!$AD$8)+($R15*Lists!$AD$9)+($S15*Lists!$AD$10),2)) | Z15: =IF(OR($B15="", $U15="", $V15="", $W15="", $X15="", $Y15=""),"",ROUND(($U15*Lists!$AD$11)+($V15*Lists!$AD$12)+($W15*Lists!$AD$13)+($X15*Lists!$AD$14)+($Y15*Lists!$AD$15),2)) | AA15: =IF(OR($B15="", $N15="", $O15="", $T15="", $Z15=""),"",ROUND(($N15*Lists!$AD$16)-($O15*Lists!$AD$17)-($T15*Lists!$AD$18)+($Z15*Lists!$AD$19),2)) | AB15: =IF(OR($B15="", $N15="", $Z15=""),"",IF($N15>=Lists!$AG$2,IF($Z15>=Lists!$AG$3,"Invest","Migrate"),IF($Z15>=Lists!$AG$3,"Tolerate","Eliminate"))) | AE15: =IF(OR($N15="", $O15=""),"",IF($N15>=Lists!$AG$2,IF($O15>=Lists!$AG$4,"High Value / High Risk","High Value / Low Risk"),IF($O15>=Lists!$AG$4,"Low Value / High Risk","Low Value / Low Risk"))) | AH15: =IF($B15="","",COUNTIFS('Debt Backlog'!$AF$2:$AF$1000,$A15,'Debt Backlog'!$B$2:$B$1000,"<>",'Debt Backlog'!$N$2:$N$1000,"<>Done",'Debt Backlog'!$N$2:$N$1000,"<>Won't Fix",'Debt Backlog'!$N$2:$N$1000,"<>Duplicate")) | AI15: =IF($B15="","",ROUND(SUMIFS('Debt Backlog'!$L$2:$L$1000,'Debt Backlog'!$AF$2:$AF$1000,$A15,'Debt Backlog'!$B$2:$B$1000,"<>",'Debt Backlog'!$N$2:$N$1000,"<>Done",'Debt Backlog'!$N$2:$N$1000,"<>Won't Fix",'Debt Backlog'!$N$2:$N$1000,"<>Duplicate"),2))
N16: =IF(OR($B16="", $I16="", $J16="", $K16="", $L16="", $M16=""),"",ROUND(($I16*Lists!$AD$2)+($J16*Lists!$AD$3)+($K16*Lists!$AD$4)+($L16*Lists!$AD$5)+($M16*Lists!$AD$6),2)) | T16: =IF(OR($B16="", $P16="", $Q16="", $R16="", $S16=""),"",ROUND(($P16*Lists!$AD$7)+($Q16*Lists!$AD$8)+($R16*Lists!$AD$9)+($S16*Lists!$AD$10),2)) | Z16: =IF(OR($B16="", $U16="", $V16="", $W16="", $X16="", $Y16=""),"",ROUND(($U16*Lists!$AD$11)+($V16*Lists!$AD$12)+($W16*Lists!$AD$13)+($X16*Lists!$AD$14)+($Y16*Lists!$AD$15),2)) | AA16: =IF(OR($B16="", $N16="", $O16="", $T16="", $Z16=""),"",ROUND(($N16*Lists!$AD$16)-($O16*Lists!$AD$17)-($T16*Lists!$AD$18)+($Z16*Lists!$AD$19),2)) | AB16: =IF(OR($B16="", $N16="", $Z16=""),"",IF($N16>=Lists!$AG$2,IF($Z16>=Lists!$AG$3,"Invest","Migrate"),IF($Z16>=Lists!$AG$3,"Tolerate","Eliminate"))) | AE16: =IF(OR($N16="", $O16=""),"",IF($N16>=Lists!$AG$2,IF($O16>=Lists!$AG$4,"High Value / High Risk","High Value / Low Risk"),IF($O16>=Lists!$AG$4,"Low Value / High Risk","Low Value / Low Risk"))) | AH16: =IF($B16="","",COUNTIFS('Debt Backlog'!$AF$2:$AF$1000,$A16,'Debt Backlog'!$B$2:$B$1000,"<>",'Debt Backlog'!$N$2:$N$1000,"<>Done",'Debt Backlog'!$N$2:$N$1000,"<>Won't Fix",'Debt Backlog'!$N$2:$N$1000,"<>Duplicate")) | AI16: =IF($B16="","",ROUND(SUMIFS('Debt Backlog'!$L$2:$L$1000,'Debt Backlog'!$AF$2:$AF$1000,$A16,'Debt Backlog'!$B$2:$B$1000,"<>",'Debt Backlog'!$N$2:$N$1000,"<>Done",'Debt Backlog'!$N$2:$N$1000,"<>Won't Fix",'Debt Backlog'!$N$2:$N$1000,"<>Duplicate"),2))
N17: =IF(OR($B17="", $I17="", $J17="", $K17="", $L17="", $M17=""),"",ROUND(($I17*Lists!$AD$2)+($J17*Lists!$AD$3)+($K17*Lists!$AD$4)+($L17*Lists!$AD$5)+($M17*Lists!$AD$6),2)) | T17: =IF(OR($B17="", $P17="", $Q17="", $R17="", $S17=""),"",ROUND(($P17*Lists!$AD$7)+($Q17*Lists!$AD$8)+($R17*Lists!$AD$9)+($S17*Lists!$AD$10),2)) | Z17: =IF(OR($B17="", $U17="", $V17="", $W17="", $X17="", $Y17=""),"",ROUND(($U17*Lists!$AD$11)+($V17*Lists!$AD$12)+($W17*Lists!$AD$13)+($X17*Lists!$AD$14)+($Y17*Lists!$AD$15),2)) | AA17: =IF(OR($B17="", $N17="", $O17="", $T17="", $Z17=""),"",ROUND(($N17*Lists!$AD$16)-($O17*Lists!$AD$17)-($T17*Lists!$AD$18)+($Z17*Lists!$AD$19),2)) | AB17: =IF(OR($B17="", $N17="", $Z17=""),"",IF($N17>=Lists!$AG$2,IF($Z17>=Lists!$AG$3,"Invest","Migrate"),IF($Z17>=Lists!$AG$3,"Tolerate","Eliminate"))) | AE17: =IF(OR($N17="", $O17=""),"",IF($N17>=Lists!$AG$2,IF($O17>=Lists!$AG$4,"High Value / High Risk","High Value / Low Risk"),IF($O17>=Lists!$AG$4,"Low Value / High Risk","Low Value / Low Risk"))) | AH17: =IF($B17="","",COUNTIFS('Debt Backlog'!$AF$2:$AF$1000,$A17,'Debt Backlog'!$B$2:$B$1000,"<>",'Debt Backlog'!$N$2:$N$1000,"<>Done",'Debt Backlog'!$N$2:$N$1000,"<>Won't Fix",'Debt Backlog'!$N$2:$N$1000,"<>Duplicate")) | AI17: =IF($B17="","",ROUND(SUMIFS('Debt Backlog'!$L$2:$L$1000,'Debt Backlog'!$AF$2:$AF$1000,$A17,'Debt Backlog'!$B$2:$B$1000,"<>",'Debt Backlog'!$N$2:$N$1000,"<>Done",'Debt Backlog'!$N$2:$N$1000,"<>Won't Fix",'Debt Backlog'!$N$2:$N$1000,"<>Duplicate"),2))
N18: =IF(OR($B18="", $I18="", $J18="", $K18="", $L18="", $M18=""),"",ROUND(($I18*Lists!$AD$2)+($J18*Lists!$AD$3)+($K18*Lists!$AD$4)+($L18*Lists!$AD$5)+($M18*Lists!$AD$6),2)) | T18: =IF(OR($B18="", $P18="", $Q18="", $R18="", $S18=""),"",ROUND(($P18*Lists!$AD$7)+($Q18*Lists!$AD$8)+($R18*Lists!$AD$9)+($S18*Lists!$AD$10),2)) | Z18: =IF(OR($B18="", $U18="", $V18="", $W18="", $X18="", $Y18=""),"",ROUND(($U18*Lists!$AD$11)+($V18*Lists!$AD$12)+($W18*Lists!$AD$13)+($X18*Lists!$AD$14)+($Y18*Lists!$AD$15),2)) | AA18: =IF(OR($B18="", $N18="", $O18="", $T18="", $Z18=""),"",ROUND(($N18*Lists!$AD$16)-($O18*Lists!$AD$17)-($T18*Lists!$AD$18)+($Z18*Lists!$AD$19),2)) | AB18: =IF(OR($B18="", $N18="", $Z18=""),"",IF($N18>=Lists!$AG$2,IF($Z18>=Lists!$AG$3,"Invest","Migrate"),IF($Z18>=Lists!$AG$3,"Tolerate","Eliminate"))) | AE18: =IF(OR($N18="", $O18=""),"",IF($N18>=Lists!$AG$2,IF($O18>=Lists!$AG$4,"High Value / High Risk","High Value / Low Risk"),IF($O18>=Lists!$AG$4,"Low Value / High Risk","Low Value / Low Risk"))) | AH18: =IF($B18="","",COUNTIFS('Debt Backlog'!$AF$2:$AF$1000,$A18,'Debt Backlog'!$B$2:$B$1000,"<>",'Debt Backlog'!$N$2:$N$1000,"<>Done",'Debt Backlog'!$N$2:$N$1000,"<>Won't Fix",'Debt Backlog'!$N$2:$N$1000,"<>Duplicate")) | AI18: =IF($B18="","",ROUND(SUMIFS('Debt Backlog'!$L$2:$L$1000,'Debt Backlog'!$AF$2:$AF$1000,$A18,'Debt Backlog'!$B$2:$B$1000,"<>",'Debt Backlog'!$N$2:$N$1000,"<>Done",'Debt Backlog'!$N$2:$N$1000,"<>Won't Fix",'Debt Backlog'!$N$2:$N$1000,"<>Duplicate"),2))
N19: =IF(OR($B19="", $I19="", $J19="", $K19="", $L19="", $M19=""),"",ROUND(($I19*Lists!$AD$2)+($J19*Lists!$AD$3)+($K19*Lists!$AD$4)+($L19*Lists!$AD$5)+($M19*Lists!$AD$6),2)) | T19: =IF(OR($B19="", $P19="", $Q19="", $R19="", $S19=""),"",ROUND(($P19*Lists!$AD$7)+($Q19*Lists!$AD$8)+($R19*Lists!$AD$9)+($S19*Lists!$AD$10),2)) | Z19: =IF(OR($B19="", $U19="", $V19="", $W19="", $X19="", $Y19=""),"",ROUND(($U19*Lists!$AD$11)+($V19*Lists!$AD$12)+($W19*Lists!$AD$13)+($X19*Lists!$AD$14)+($Y19*Lists!$AD$15),2)) | AA19: =IF(OR($B19="", $N19="", $O19="", $T19="", $Z19=""),"",ROUND(($N19*Lists!$AD$16)-($O19*Lists!$AD$17)-($T19*Lists!$AD$18)+($Z19*Lists!$AD$19),2)) | AB19: =IF(OR($B19="", $N19="", $Z19=""),"",IF($N19>=Lists!$AG$2,IF($Z19>=Lists!$AG$3,"Invest","Migrate"),IF($Z19>=Lists!$AG$3,"Tolerate","Eliminate"))) | AE19: =IF(OR($N19="", $O19=""),"",IF($N19>=Lists!$AG$2,IF($O19>=Lists!$AG$4,"High Value / High Risk","High Value / Low Risk"),IF($O19>=Lists!$AG$4,"Low Value / High Risk","Low Value / Low Risk"))) | AH19: =IF($B19="","",COUNTIFS('Debt Backlog'!$AF$2:$AF$1000,$A19,'Debt Backlog'!$B$2:$B$1000,"<>",'Debt Backlog'!$N$2:$N$1000,"<>Done",'Debt Backlog'!$N$2:$N$1000,"<>Won't Fix",'Debt Backlog'!$N$2:$N$1000,"<>Duplicate")) | AI19: =IF($B19="","",ROUND(SUMIFS('Debt Backlog'!$L$2:$L$1000,'Debt Backlog'!$AF$2:$AF$1000,$A19,'Debt Backlog'!$B$2:$B$1000,"<>",'Debt Backlog'!$N$2:$N$1000,"<>Done",'Debt Backlog'!$N$2:$N$1000,"<>Won't Fix",'Debt Backlog'!$N$2:$N$1000,"<>Duplicate"),2))
N20: =IF(OR($B20="", $I20="", $J20="", $K20="", $L20="", $M20=""),"",ROUND(($I20*Lists!$AD$2)+($J20*Lists!$AD$3)+($K20*Lists!$AD$4)+($L20*Lists!$AD$5)+($M20*Lists!$AD$6),2)) | T20: =IF(OR($B20="", $P20="", $Q20="", $R20="", $S20=""),"",ROUND(($P20*Lists!$AD$7)+($Q20*Lists!$AD$8)+($R20*Lists!$AD$9)+($S20*Lists!$AD$10),2)) | Z20: =IF(OR($B20="", $U20="", $V20="", $W20="", $X20="", $Y20=""),"",ROUND(($U20*Lists!$AD$11)+($V20*Lists!$AD$12)+($W20*Lists!$AD$13)+($X20*Lists!$AD$14)+($Y20*Lists!$AD$15),2)) | AA20: =IF(OR($B20="", $N20="", $O20="", $T20="", $Z20=""),"",ROUND(($N20*Lists!$AD$16)-($O20*Lists!$AD$17)-($T20*Lists!$AD$18)+($Z20*Lists!$AD$19),2)) | AB20: =IF(OR($B20="", $N20="", $Z20=""),"",IF($N20>=Lists!$AG$2,IF($Z20>=Lists!$AG$3,"Invest","Migrate"),IF($Z20>=Lists!$AG$3,"Tolerate","Eliminate"))) | AE20: =IF(OR($N20="", $O20=""),"",IF($N20>=Lists!$AG$2,IF($O20>=Lists!$AG$4,"High Value / High Risk","High Value / Low Risk"),IF($O20>=Lists!$AG$4,"Low Value / High Risk","Low Value / Low Risk"))) | AH20: =IF($B20="","",COUNTIFS('Debt Backlog'!$AF$2:$AF$1000,$A20,'Debt Backlog'!$B$2:$B$1000,"<>",'Debt Backlog'!$N$2:$N$1000,"<>Done",'Debt Backlog'!$N$2:$N$1000,"<>Won't Fix",'Debt Backlog'!$N$2:$N$1000,"<>Duplicate")) | AI20: =IF($B20="","",ROUND(SUMIFS('Debt Backlog'!$L$2:$L$1000,'Debt Backlog'!$AF$2:$AF$1000,$A20,'Debt Backlog'!$B$2:$B$1000,"<>",'Debt Backlog'!$N$2:$N$1000,"<>Done",'Debt Backlog'!$N$2:$N$1000,"<>Won't Fix",'Debt Backlog'!$N$2:$N$1000,"<>Duplicate"),2))
... N86: =IF(OR($B86="", $I86="", $J86="", $K86="", $L86="", $M86=""),"",ROUND(($I86*Lists!$AD$2)+($J86*Lists!$AD$3)+($K86*Lists!$AD$4)+($L86*Lists!$AD$5)+($M86*Lists!$AD$6),2)) | T86: =IF(OR($B86="", $P86="", $Q86="", $R86="", $S86=""),"",ROUND(($P86*Lists!$AD$7)+($Q86*Lists!$AD$8)+($R86*Lists!$AD$9)+($S86*Lists!$AD$10),2)) | Z86: =IF(OR($B86="", $U86="", $V86="", $W86="", $X86="", $Y86=""),"",ROUND(($U86*Lists!$AD$11)+($V86*Lists!$AD$12)+($W86*Lists!$AD$13)+($X86*Lists!$AD$14)+($Y86*Lists!$AD$15),2)) | AA86: =IF(OR($B86="", $N86="", $O86="", $T86="", $Z86=""),"",ROUND(($N86*Lists!$AD$16)-($O86*Lists!$AD$17)-($T86*Lists!$AD$18)+($Z86*Lists!$AD$19),2)) | AB86: =IF(OR($B86="", $N86="", $Z86=""),"",IF($N86>=Lists!$AG$2,IF($Z86>=Lists!$AG$3,"Invest","Migrate"),IF($Z86>=Lists!$AG$3,"Tolerate","Eliminate"))) | AE86: =IF(OR($N86="", $O86=""),"",IF($N86>=Lists!$AG$2,IF($O86>=Lists!$AG$4,"High Value / High Risk","High Value / Low Risk"),IF($O86>=Lists!$AG$4,"Low Value / High Risk","Low Value / Low Risk"))) | AH86: =IF($B86="","",COUNTIFS('Debt Backlog'!$AF$2:$AF$1000,$A86,'Debt Backlog'!$B$2:$B$1000,"<>",'Debt Backlog'!$N$2:$N$1000,"<>Done",'Debt Backlog'!$N$2:$N$1000,"<>Won't Fix",'Debt Backlog'!$N$2:$N$1000,"<>Duplicate")) | AI86: =IF($B86="","",ROUND(SUMIFS('Debt Backlog'!$L$2:$L$1000,'Debt Backlog'!$AF$2:$AF$1000,$A86,'Debt Backlog'!$B$2:$B$1000,"<>",'Debt Backlog'!$N$2:$N$1000,"<>Done",'Debt Backlog'!$N$2:$N$1000,"<>Won't Fix",'Debt Backlog'!$N$2:$N$1000,"<>Duplicate"),2))
N87: =IF(OR($B87="", $I87="", $J87="", $K87="", $L87="", $M87=""),"",ROUND(($I87*Lists!$AD$2)+($J87*Lists!$AD$3)+($K87*Lists!$AD$4)+($L87*Lists!$AD$5)+($M87*Lists!$AD$6),2)) | O87: =IF($A87="","",IFERROR(VLOOKUP($A87,'Risk Register'!$B$2:$I$1000,8,FALSE()),"")) | T87: =IF(OR($B87="", $P87="", $Q87="", $R87="", $S87=""),"",ROUND(($P87*Lists!$AD$7)+($Q87*Lists!$AD$8)+($R87*Lists!$AD$9)+($S87*Lists!$AD$10),2)) | Z87: =IF(OR($B87="", $U87="", $V87="", $W87="", $X87="", $Y87=""),"",ROUND(($U87*Lists!$AD$11)+($V87*Lists!$AD$12)+($W87*Lists!$AD$13)+($X87*Lists!$AD$14)+($Y87*Lists!$AD$15),2)) | AA87: =IF(OR($B87="", $N87="", $O87="", $T87="", $Z87=""),"",ROUND(($N87*Lists!$AD$16)-($O87*Lists!$AD$17)-($T87*Lists!$AD$18)+($Z87*Lists!$AD$19),2)) | AB87: =IF(OR($B87="", $N87="", $Z87=""),"",IF($N87>=Lists!$AG$2,IF($Z87>=Lists!$AG$3,"Invest","Migrate"),IF($Z87>=Lists!$AG$3,"Tolerate","Eliminate"))) | AC87: =IF($B87="","",IF($J87>=4,"Yes","")) | AD87: =IF($A87="","",IFERROR(IF(VLOOKUP($A87,'Risk Register'!$B$2:$H$1000,4,FALSE())>=4,"Yes",""),"")) | AE87: =IF(OR($N87="", $O87=""),"",IF($N87>=Lists!$AG$2,IF($O87>=Lists!$AG$4,"High Value / High Risk","High Value / Low Risk"),IF($O87>=Lists!$AG$4,"Low Value / High Risk","Low Value / Low Risk"))) | AH87: =IF($B87="","",COUNTIFS('Debt Backlog'!$AF$2:$AF$1000,$A87,'Debt Backlog'!$B$2:$B$1000,"<>",'Debt Backlog'!$N$2:$N$1000,"<>Done",'Debt Backlog'!$N$2:$N$1000,"<>Won't Fix",'Debt Backlog'!$N$2:$N$1000,"<>Duplicate")) | AI87: =IF($B87="","",ROUND(SUMIFS('Debt Backlog'!$L$2:$L$1000,'Debt Backlog'!$AF$2:$AF$1000,$A87,'Debt Backlog'!$B$2:$B$1000,"<>",'Debt Backlog'!$N$2:$N$1000,"<>Done",'Debt Backlog'!$N$2:$N$1000,"<>Won't Fix",'Debt Backlog'!$N$2:$N$1000,"<>Duplicate"),2))
N88: =IF(OR($B88="", $I88="", $J88="", $K88="", $L88="", $M88=""),"",ROUND(($I88*Lists!$AD$2)+($J88*Lists!$AD$3)+($K88*Lists!$AD$4)+($L88*Lists!$AD$5)+($M88*Lists!$AD$6),2)) | O88: =IF($A88="","",IFERROR(VLOOKUP($A88,'Risk Register'!$B$2:$I$1000,8,FALSE()),"")) | T88: =IF(OR($B88="", $P88="", $Q88="", $R88="", $S88=""),"",ROUND(($P88*Lists!$AD$7)+($Q88*Lists!$AD$8)+($R88*Lists!$AD$9)+($S88*Lists!$AD$10),2)) | Z88: =IF(OR($B88="", $U88="", $V88="", $W88="", $X88="", $Y88=""),"",ROUND(($U88*Lists!$AD$11)+($V88*Lists!$AD$12)+($W88*Lists!$AD$13)+($X88*Lists!$AD$14)+($Y88*Lists!$AD$15),2)) | AA88: =IF(OR($B88="", $N88="", $O88="", $T88="", $Z88=""),"",ROUND(($N88*Lists!$AD$16)-($O88*Lists!$AD$17)-($T88*Lists!$AD$18)+($Z88*Lists!$AD$19),2)) | AB88: =IF(OR($B88="", $N88="", $Z88=""),"",IF($N88>=Lists!$AG$2,IF($Z88>=Lists!$AG$3,"Invest","Migrate"),IF($Z88>=Lists!$AG$3,"Tolerate","Eliminate"))) | AC88: =IF($B88="","",IF($J88>=4,"Yes","")) | AD88: =IF($A88="","",IFERROR(IF(VLOOKUP($A88,'Risk Register'!$B$2:$H$1000,4,FALSE())>=4,"Yes",""),"")) | AE88: =IF(OR($N88="", $O88=""),"",IF($N88>=Lists!$AG$2,IF($O88>=Lists!$AG$4,"High Value / High Risk","High Value / Low Risk"),IF($O88>=Lists!$AG$4,"Low Value / High Risk","Low Value / Low Risk"))) | AH88: =IF($B88="","",COUNTIFS('Debt Backlog'!$AF$2:$AF$1000,$A88,'Debt Backlog'!$B$2:$B$1000,"<>",'Debt Backlog'!$N$2:$N$1000,"<>Done",'Debt Backlog'!$N$2:$N$1000,"<>Won't Fix",'Debt Backlog'!$N$2:$N$1000,"<>Duplicate")) | AI88: =IF($B88="","",ROUND(SUMIFS('Debt Backlog'!$L$2:$L$1000,'Debt Backlog'!$AF$2:$AF$1000,$A88,'Debt Backlog'!$B$2:$B$1000,"<>",'Debt Backlog'!$N$2:$N$1000,"<>Done",'Debt Backlog'!$N$2:$N$1000,"<>Won't Fix",'Debt Backlog'!$N$2:$N$1000,"<>Duplicate"),2))
N89: =IF(OR($B89="", $I89="", $J89="", $K89="", $L89="", $M89=""),"",ROUND(($I89*Lists!$AD$2)+($J89*Lists!$AD$3)+($K89*Lists!$AD$4)+($L89*Lists!$AD$5)+($M89*Lists!$AD$6),2)) | O89: =IF($A89="","",IFERROR(VLOOKUP($A89,'Risk Register'!$B$2:$I$1000,8,FALSE()),"")) | T89: =IF(OR($B89="", $P89="", $Q89="", $R89="", $S89=""),"",ROUND(($P89*Lists!$AD$7)+($Q89*Lists!$AD$8)+($R89*Lists!$AD$9)+($S89*Lists!$AD$10),2)) | Z89: =IF(OR($B89="", $U89="", $V89="", $W89="", $X89="", $Y89=""),"",ROUND(($U89*Lists!$AD$11)+($V89*Lists!$AD$12)+($W89*Lists!$AD$13)+($X89*Lists!$AD$14)+($Y89*Lists!$AD$15),2)) | AA89: =IF(OR($B89="", $N89="", $O89="", $T89="", $Z89=""),"",ROUND(($N89*Lists!$AD$16)-($O89*Lists!$AD$17)-($T89*Lists!$AD$18)+($Z89*Lists!$AD$19),2)) | AB89: =IF(OR($B89="", $N89="", $Z89=""),"",IF($N89>=Lists!$AG$2,IF($Z89>=Lists!$AG$3,"Invest","Migrate"),IF($Z89>=Lists!$AG$3,"Tolerate","Eliminate"))) | AC89: =IF($B89="","",IF($J89>=4,"Yes","")) | AD89: =IF($A89="","",IFERROR(IF(VLOOKUP($A89,'Risk Register'!$B$2:$H$1000,4,FALSE())>=4,"Yes",""),"")) | AE89: =IF(OR($N89="", $O89=""),"",IF($N89>=Lists!$AG$2,IF($O89>=Lists!$AG$4,"High Value / High Risk","High Value / Low Risk"),IF($O89>=Lists!$AG$4,"Low Value / High Risk","Low Value / Low Risk"))) | AH89: =IF($B89="","",COUNTIFS('Debt Backlog'!$AF$2:$AF$1000,$A89,'Debt Backlog'!$B$2:$B$1000,"<>",'Debt Backlog'!$N$2:$N$1000,"<>Done",'Debt Backlog'!$N$2:$N$1000,"<>Won't Fix",'Debt Backlog'!$N$2:$N$1000,"<>Duplicate")) | AI89: =IF($B89="","",ROUND(SUMIFS('Debt Backlog'!$L$2:$L$1000,'Debt Backlog'!$AF$2:$AF$1000,$A89,'Debt Backlog'!$B$2:$B$1000,"<>",'Debt Backlog'!$N$2:$N$1000,"<>Done",'Debt Backlog'!$N$2:$N$1000,"<>Won't Fix",'Debt Backlog'!$N$2:$N$1000,"<>Duplicate"),2))
N90: =IF(OR($B90="", $I90="", $J90="", $K90="", $L90="", $M90=""),"",ROUND(($I90*Lists!$AD$2)+($J90*Lists!$AD$3)+($K90*Lists!$AD$4)+($L90*Lists!$AD$5)+($M90*Lists!$AD$6),2)) | O90: =IF($A90="","",IFERROR(VLOOKUP($A90,'Risk Register'!$B$2:$I$1000,8,FALSE()),"")) | T90: =IF(OR($B90="", $P90="", $Q90="", $R90="", $S90=""),"",ROUND(($P90*Lists!$AD$7)+($Q90*Lists!$AD$8)+($R90*Lists!$AD$9)+($S90*Lists!$AD$10),2)) | Z90: =IF(OR($B90="", $U90="", $V90="", $W90="", $X90="", $Y90=""),"",ROUND(($U90*Lists!$AD$11)+($V90*Lists!$AD$12)+($W90*Lists!$AD$13)+($X90*Lists!$AD$14)+($Y90*Lists!$AD$15),2)) | AA90: =IF(OR($B90="", $N90="", $O90="", $T90="", $Z90=""),"",ROUND(($N90*Lists!$AD$16)-($O90*Lists!$AD$17)-($T90*Lists!$AD$18)+($Z90*Lists!$AD$19),2)) | AB90: =IF(OR($B90="", $N90="", $Z90=""),"",IF($N90>=Lists!$AG$2,IF($Z90>=Lists!$AG$3,"Invest","Migrate"),IF($Z90>=Lists!$AG$3,"Tolerate","Eliminate"))) | AC90: =IF($B90="","",IF($J90>=4,"Yes","")) | AD90: =IF($A90="","",IFERROR(IF(VLOOKUP($A90,'Risk Register'!$B$2:$H$1000,4,FALSE())>=4,"Yes",""),"")) | AE90: =IF(OR($N90="", $O90=""),"",IF($N90>=Lists!$AG$2,IF($O90>=Lists!$AG$4,"High Value / High Risk","High Value / Low Risk"),IF($O90>=Lists!$AG$4,"Low Value / High Risk","Low Value / Low Risk"))) | AH90: =IF($B90="","",COUNTIFS('Debt Backlog'!$AF$2:$AF$1000,$A90,'Debt Backlog'!$B$2:$B$1000,"<>",'Debt Backlog'!$N$2:$N$1000,"<>Done",'Debt Backlog'!$N$2:$N$1000,"<>Won't Fix",'Debt Backlog'!$N$2:$N$1000,"<>Duplicate")) | AI90: =IF($B90="","",ROUND(SUMIFS('Debt Backlog'!$L$2:$L$1000,'Debt Backlog'!$AF$2:$AF$1000,$A90,'Debt Backlog'!$B$2:$B$1000,"<>",'Debt Backlog'!$N$2:$N$1000,"<>Done",'Debt Backlog'!$N$2:$N$1000,"<>Won't Fix",'Debt Backlog'!$N$2:$N$1000,"<>Duplicate"),2))
N91: =IF(OR($B91="", $I91="", $J91="", $K91="", $L91="", $M91=""),"",ROUND(($I91*Lists!$AD$2)+($J91*Lists!$AD$3)+($K91*Lists!$AD$4)+($L91*Lists!$AD$5)+($M91*Lists!$AD$6),2)) | O91: =IF($A91="","",IFERROR(VLOOKUP($A91,'Risk Register'!$B$2:$I$1000,8,FALSE()),"")) | T91: =IF(OR($B91="", $P91="", $Q91="", $R91="", $S91=""),"",ROUND(($P91*Lists!$AD$7)+($Q91*Lists!$AD$8)+($R91*Lists!$AD$9)+($S91*Lists!$AD$10),2)) | Z91: =IF(OR($B91="", $U91="", $V91="", $W91="", $X91="", $Y91=""),"",ROUND(($U91*Lists!$AD$11)+($V91*Lists!$AD$12)+($W91*Lists!$AD$13)+($X91*Lists!$AD$14)+($Y91*Lists!$AD$15),2)) | AA91: =IF(OR($B91="", $N91="", $O91="", $T91="", $Z91=""),"",ROUND(($N91*Lists!$AD$16)-($O91*Lists!$AD$17)-($T91*Lists!$AD$18)+($Z91*Lists!$AD$19),2)) | AB91: =IF(OR($B91="", $N91="", $Z91=""),"",IF($N91>=Lists!$AG$2,IF($Z91>=Lists!$AG$3,"Invest","Migrate"),IF($Z91>=Lists!$AG$3,"Tolerate","Eliminate"))) | AC91: =IF($B91="","",IF($J91>=4,"Yes","")) | AD91: =IF($A91="","",IFERROR(IF(VLOOKUP($A91,'Risk Register'!$B$2:$H$1000,4,FALSE())>=4,"Yes",""),"")) | AE91: =IF(OR($N91="", $O91=""),"",IF($N91>=Lists!$AG$2,IF($O91>=Lists!$AG$4,"High Value / High Risk","High Value / Low Risk"),IF($O91>=Lists!$AG$4,"Low Value / High Risk","Low Value / Low Risk"))) | AH91: =IF($B91="","",COUNTIFS('Debt Backlog'!$AF$2:$AF$1000,$A91,'Debt Backlog'!$B$2:$B$1000,"<>",'Debt Backlog'!$N$2:$N$1000,"<>Done",'Debt Backlog'!$N$2:$N$1000,"<>Won't Fix",'Debt Backlog'!$N$2:$N$1000,"<>Duplicate")) | AI91: =IF($B91="","",ROUND(SUMIFS('Debt Backlog'!$L$2:$L$1000,'Debt Backlog'!$AF$2:$AF$1000,$A91,'Debt Backlog'!$B$2:$B$1000,"<>",'Debt Backlog'!$N$2:$N$1000,"<>Done",'Debt Backlog'!$N$2:$N$1000,"<>Won't Fix",'Debt Backlog'!$N$2:$N$1000,"<>Duplicate"),2))
N92: =IF(OR($B92="", $I92="", $J92="", $K92="", $L92="", $M92=""),"",ROUND(($I92*Lists!$AD$2)+($J92*Lists!$AD$3)+($K92*Lists!$AD$4)+($L92*Lists!$AD$5)+($M92*Lists!$AD$6),2)) | O92: =IF($A92="","",IFERROR(VLOOKUP($A92,'Risk Register'!$B$2:$I$1000,8,FALSE()),"")) | T92: =IF(OR($B92="", $P92="", $Q92="", $R92="", $S92=""),"",ROUND(($P92*Lists!$AD$7)+($Q92*Lists!$AD$8)+($R92*Lists!$AD$9)+($S92*Lists!$AD$10),2)) | Z92: =IF(OR($B92="", $U92="", $V92="", $W92="", $X92="", $Y92=""),"",ROUND(($U92*Lists!$AD$11)+($V92*Lists!$AD$12)+($W92*Lists!$AD$13)+($X92*Lists!$AD$14)+($Y92*Lists!$AD$15),2)) | AA92: =IF(OR($B92="", $N92="", $O92="", $T92="", $Z92=""),"",ROUND(($N92*Lists!$AD$16)-($O92*Lists!$AD$17)-($T92*Lists!$AD$18)+($Z92*Lists!$AD$19),2)) | AB92: =IF(OR($B92="", $N92="", $Z92=""),"",IF($N92>=Lists!$AG$2,IF($Z92>=Lists!$AG$3,"Invest","Migrate"),IF($Z92>=Lists!$AG$3,"Tolerate","Eliminate"))) | AC92: =IF($B92="","",IF($J92>=4,"Yes","")) | AD92: =IF($A92="","",IFERROR(IF(VLOOKUP($A92,'Risk Register'!$B$2:$H$1000,4,FALSE())>=4,"Yes",""),"")) | AE92: =IF(OR($N92="", $O92=""),"",IF($N92>=Lists!$AG$2,IF($O92>=Lists!$AG$4,"High Value / High Risk","High Value / Low Risk"),IF($O92>=Lists!$AG$4,"Low Value / High Risk","Low Value / Low Risk"))) | AH92: =IF($B92="","",COUNTIFS('Debt Backlog'!$AF$2:$AF$1000,$A92,'Debt Backlog'!$B$2:$B$1000,"<>",'Debt Backlog'!$N$2:$N$1000,"<>Done",'Debt Backlog'!$N$2:$N$1000,"<>Won't Fix",'Debt Backlog'!$N$2:$N$1000,"<>Duplicate")) | AI92: =IF($B92="","",ROUND(SUMIFS('Debt Backlog'!$L$2:$L$1000,'Debt Backlog'!$AF$2:$AF$1000,$A92,'Debt Backlog'!$B$2:$B$1000,"<>",'Debt Backlog'!$N$2:$N$1000,"<>Done",'Debt Backlog'!$N$2:$N$1000,"<>Won't Fix",'Debt Backlog'!$N$2:$N$1000,"<>Duplicate"),2))
N93: =IF(OR($B93="", $I93="", $J93="", $K93="", $L93="", $M93=""),"",ROUND(($I93*Lists!$AD$2)+($J93*Lists!$AD$3)+($K93*Lists!$AD$4)+($L93*Lists!$AD$5)+($M93*Lists!$AD$6),2)) | O93: =IF($A93="","",IFERROR(VLOOKUP($A93,'Risk Register'!$B$2:$I$1000,8,FALSE()),"")) | T93: =IF(OR($B93="", $P93="", $Q93="", $R93="", $S93=""),"",ROUND(($P93*Lists!$AD$7)+($Q93*Lists!$AD$8)+($R93*Lists!$AD$9)+($S93*Lists!$AD$10),2)) | Z93: =IF(OR($B93="", $U93="", $V93="", $W93="", $X93="", $Y93=""),"",ROUND(($U93*Lists!$AD$11)+($V93*Lists!$AD$12)+($W93*Lists!$AD$13)+($X93*Lists!$AD$14)+($Y93*Lists!$AD$15),2)) | AA93: =IF(OR($B93="", $N93="", $O93="", $T93="", $Z93=""),"",ROUND(($N93*Lists!$AD$16)-($O93*Lists!$AD$17)-($T93*Lists!$AD$18)+($Z93*Lists!$AD$19),2)) | AB93: =IF(OR($B93="", $N93="", $Z93=""),"",IF($N93>=Lists!$AG$2,IF($Z93>=Lists!$AG$3,"Invest","Migrate"),IF($Z93>=Lists!$AG$3,"Tolerate","Eliminate"))) | AC93: =IF($B93="","",IF($J93>=4,"Yes","")) | AD93: =IF($A93="","",IFERROR(IF(VLOOKUP($A93,'Risk Register'!$B$2:$H$1000,4,FALSE())>=4,"Yes",""),"")) | AE93: =IF(OR($N93="", $O93=""),"",IF($N93>=Lists!$AG$2,IF($O93>=Lists!$AG$4,"High Value / High Risk","High Value / Low Risk"),IF($O93>=Lists!$AG$4,"Low Value / High Risk","Low Value / Low Risk"))) | AH93: =IF($B93="","",COUNTIFS('Debt Backlog'!$AF$2:$AF$1000,$A93,'Debt Backlog'!$B$2:$B$1000,"<>",'Debt Backlog'!$N$2:$N$1000,"<>Done",'Debt Backlog'!$N$2:$N$1000,"<>Won't Fix",'Debt Backlog'!$N$2:$N$1000,"<>Duplicate")) | AI93: =IF($B93="","",ROUND(SUMIFS('Debt Backlog'!$L$2:$L$1000,'Debt Backlog'!$AF$2:$AF$1000,$A93,'Debt Backlog'!$B$2:$B$1000,"<>",'Debt Backlog'!$N$2:$N$1000,"<>Done",'Debt Backlog'!$N$2:$N$1000,"<>Won't Fix",'Debt Backlog'!$N$2:$N$1000,"<>Duplicate"),2))
N94: =IF(OR($B94="", $I94="", $J94="", $K94="", $L94="", $M94=""),"",ROUND(($I94*Lists!$AD$2)+($J94*Lists!$AD$3)+($K94*Lists!$AD$4)+($L94*Lists!$AD$5)+($M94*Lists!$AD$6),2)) | O94: =IF($A94="","",IFERROR(VLOOKUP($A94,'Risk Register'!$B$2:$I$1000,8,FALSE()),"")) | T94: =IF(OR($B94="", $P94="", $Q94="", $R94="", $S94=""),"",ROUND(($P94*Lists!$AD$7)+($Q94*Lists!$AD$8)+($R94*Lists!$AD$9)+($S94*Lists!$AD$10),2)) | Z94: =IF(OR($B94="", $U94="", $V94="", $W94="", $X94="", $Y94=""),"",ROUND(($U94*Lists!$AD$11)+($V94*Lists!$AD$12)+($W94*Lists!$AD$13)+($X94*Lists!$AD$14)+($Y94*Lists!$AD$15),2)) | AA94: =IF(OR($B94="", $N94="", $O94="", $T94="", $Z94=""),"",ROUND(($N94*Lists!$AD$16)-($O94*Lists!$AD$17)-($T94*Lists!$AD$18)+($Z94*Lists!$AD$19),2)) | AB94: =IF(OR($B94="", $N94="", $Z94=""),"",IF($N94>=Lists!$AG$2,IF($Z94>=Lists!$AG$3,"Invest","Migrate"),IF($Z94>=Lists!$AG$3,"Tolerate","Eliminate"))) | AC94: =IF($B94="","",IF($J94>=4,"Yes","")) | AD94: =IF($A94="","",IFERROR(IF(VLOOKUP($A94,'Risk Register'!$B$2:$H$1000,4,FALSE())>=4,"Yes",""),"")) | AE94: =IF(OR($N94="", $O94=""),"",IF($N94>=Lists!$AG$2,IF($O94>=Lists!$AG$4,"High Value / High Risk","High Value / Low Risk"),IF($O94>=Lists!$AG$4,"Low Value / High Risk","Low Value / Low Risk"))) | AH94: =IF($B94="","",COUNTIFS('Debt Backlog'!$AF$2:$AF$1000,$A94,'Debt Backlog'!$B$2:$B$1000,"<>",'Debt Backlog'!$N$2:$N$1000,"<>Done",'Debt Backlog'!$N$2:$N$1000,"<>Won't Fix",'Debt Backlog'!$N$2:$N$1000,"<>Duplicate")) | AI94: =IF($B94="","",ROUND(SUMIFS('Debt Backlog'!$L$2:$L$1000,'Debt Backlog'!$AF$2:$AF$1000,$A94,'Debt Backlog'!$B$2:$B$1000,"<>",'Debt Backlog'!$N$2:$N$1000,"<>Done",'Debt Backlog'!$N$2:$N$1000,"<>Won't Fix",'Debt Backlog'!$N$2:$N$1000,"<>Duplicate"),2))
N95: =IF(OR($B95="", $I95="", $J95="", $K95="", $L95="", $M95=""),"",ROUND(($I95*Lists!$AD$2)+($J95*Lists!$AD$3)+($K95*Lists!$AD$4)+($L95*Lists!$AD$5)+($M95*Lists!$AD$6),2)) | O95: =IF($A95="","",IFERROR(VLOOKUP($A95,'Risk Register'!$B$2:$I$1000,8,FALSE()),"")) | T95: =IF(OR($B95="", $P95="", $Q95="", $R95="", $S95=""),"",ROUND(($P95*Lists!$AD$7)+($Q95*Lists!$AD$8)+($R95*Lists!$AD$9)+($S95*Lists!$AD$10),2)) | Z95: =IF(OR($B95="", $U95="", $V95="", $W95="", $X95="", $Y95=""),"",ROUND(($U95*Lists!$AD$11)+($V95*Lists!$AD$12)+($W95*Lists!$AD$13)+($X95*Lists!$AD$14)+($Y95*Lists!$AD$15),2)) | AA95: =IF(OR($B95="", $N95="", $O95="", $T95="", $Z95=""),"",ROUND(($N95*Lists!$AD$16)-($O95*Lists!$AD$17)-($T95*Lists!$AD$18)+($Z95*Lists!$AD$19),2)) | AB95: =IF(OR($B95="", $N95="", $Z95=""),"",IF($N95>=Lists!$AG$2,IF($Z95>=Lists!$AG$3,"Invest","Migrate"),IF($Z95>=Lists!$AG$3,"Tolerate","Eliminate"))) | AC95: =IF($B95="","",IF($J95>=4,"Yes","")) | AD95: =IF($A95="","",IFERROR(IF(VLOOKUP($A95,'Risk Register'!$B$2:$H$1000,4,FALSE())>=4,"Yes",""),"")) | AE95: =IF(OR($N95="", $O95=""),"",IF($N95>=Lists!$AG$2,IF($O95>=Lists!$AG$4,"High Value / High Risk","High Value / Low Risk"),IF($O95>=Lists!$AG$4,"Low Value / High Risk","Low Value / Low Risk"))) | AH95: =IF($B95="","",COUNTIFS('Debt Backlog'!$AF$2:$AF$1000,$A95,'Debt Backlog'!$B$2:$B$1000,"<>",'Debt Backlog'!$N$2:$N$1000,"<>Done",'Debt Backlog'!$N$2:$N$1000,"<>Won't Fix",'Debt Backlog'!$N$2:$N$1000,"<>Duplicate")) | AI95: =IF($B95="","",ROUND(SUMIFS('Debt Backlog'!$L$2:$L$1000,'Debt Backlog'!$AF$2:$AF$1000,$A95,'Debt Backlog'!$B$2:$B$1000,"<>",'Debt Backlog'!$N$2:$N$1000,"<>Done",'Debt Backlog'!$N$2:$N$1000,"<>Won't Fix",'Debt Backlog'!$N$2:$N$1000,"<>Duplicate"),2))
N96: =IF(OR($B96="", $I96="", $J96="", $K96="", $L96="", $M96=""),"",ROUND(($I96*Lists!$AD$2)+($J96*Lists!$AD$3)+($K96*Lists!$AD$4)+($L96*Lists!$AD$5)+($M96*Lists!$AD$6),2)) | O96: =IF($A96="","",IFERROR(VLOOKUP($A96,'Risk Register'!$B$2:$I$1000,8,FALSE()),"")) | T96: =IF(OR($B96="", $P96="", $Q96="", $R96="", $S96=""),"",ROUND(($P96*Lists!$AD$7)+($Q96*Lists!$AD$8)+($R96*Lists!$AD$9)+($S96*Lists!$AD$10),2)) | Z96: =IF(OR($B96="", $U96="", $V96="", $W96="", $X96="", $Y96=""),"",ROUND(($U96*Lists!$AD$11)+($V96*Lists!$AD$12)+($W96*Lists!$AD$13)+($X96*Lists!$AD$14)+($Y96*Lists!$AD$15),2)) | AA96: =IF(OR($B96="", $N96="", $O96="", $T96="", $Z96=""),"",ROUND(($N96*Lists!$AD$16)-($O96*Lists!$AD$17)-($T96*Lists!$AD$18)+($Z96*Lists!$AD$19),2)) | AB96: =IF(OR($B96="", $N96="", $Z96=""),"",IF($N96>=Lists!$AG$2,IF($Z96>=Lists!$AG$3,"Invest","Migrate"),IF($Z96>=Lists!$AG$3,"Tolerate","Eliminate"))) | AC96: =IF($B96="","",IF($J96>=4,"Yes","")) | AD96: =IF($A96="","",IFERROR(IF(VLOOKUP($A96,'Risk Register'!$B$2:$H$1000,4,FALSE())>=4,"Yes",""),"")) | AE96: =IF(OR($N96="", $O96=""),"",IF($N96>=Lists!$AG$2,IF($O96>=Lists!$AG$4,"High Value / High Risk","High Value / Low Risk"),IF($O96>=Lists!$AG$4,"Low Value / High Risk","Low Value / Low Risk"))) | AH96: =IF($B96="","",COUNTIFS('Debt Backlog'!$AF$2:$AF$1000,$A96,'Debt Backlog'!$B$2:$B$1000,"<>",'Debt Backlog'!$N$2:$N$1000,"<>Done",'Debt Backlog'!$N$2:$N$1000,"<>Won't Fix",'Debt Backlog'!$N$2:$N$1000,"<>Duplicate")) | AI96: =IF($B96="","",ROUND(SUMIFS('Debt Backlog'!$L$2:$L$1000,'Debt Backlog'!$AF$2:$AF$1000,$A96,'Debt Backlog'!$B$2:$B$1000,"<>",'Debt Backlog'!$N$2:$N$1000,"<>Done",'Debt Backlog'!$N$2:$N$1000,"<>Won't Fix",'Debt Backlog'!$N$2:$N$1000,"<>Duplicate"),2))
N97: =IF(OR($B97="", $I97="", $J97="", $K97="", $L97="", $M97=""),"",ROUND(($I97*Lists!$AD$2)+($J97*Lists!$AD$3)+($K97*Lists!$AD$4)+($L97*Lists!$AD$5)+($M97*Lists!$AD$6),2)) | O97: =IF($A97="","",IFERROR(VLOOKUP($A97,'Risk Register'!$B$2:$I$1000,8,FALSE()),"")) | T97: =IF(OR($B97="", $P97="", $Q97="", $R97="", $S97=""),"",ROUND(($P97*Lists!$AD$7)+($Q97*Lists!$AD$8)+($R97*Lists!$AD$9)+($S97*Lists!$AD$10),2)) | Z97: =IF(OR($B97="", $U97="", $V97="", $W97="", $X97="", $Y97=""),"",ROUND(($U97*Lists!$AD$11)+($V97*Lists!$AD$12)+($W97*Lists!$AD$13)+($X97*Lists!$AD$14)+($Y97*Lists!$AD$15),2)) | AA97: =IF(OR($B97="", $N97="", $O97="", $T97="", $Z97=""),"",ROUND(($N97*Lists!$AD$16)-($O97*Lists!$AD$17)-($T97*Lists!$AD$18)+($Z97*Lists!$AD$19),2)) | AB97: =IF(OR($B97="", $N97="", $Z97=""),"",IF($N97>=Lists!$AG$2,IF($Z97>=Lists!$AG$3,"Invest","Migrate"),IF($Z97>=Lists!$AG$3,"Tolerate","Eliminate"))) | AC97: =IF($B97="","",IF($J97>=4,"Yes","")) | AD97: =IF($A97="","",IFERROR(IF(VLOOKUP($A97,'Risk Register'!$B$2:$H$1000,4,FALSE())>=4,"Yes",""),"")) | AE97: =IF(OR($N97="", $O97=""),"",IF($N97>=Lists!$AG$2,IF($O97>=Lists!$AG$4,"High Value / High Risk","High Value / Low Risk"),IF($O97>=Lists!$AG$4,"Low Value / High Risk","Low Value / Low Risk"))) | AH97: =IF($B97="","",COUNTIFS('Debt Backlog'!$AF$2:$AF$1000,$A97,'Debt Backlog'!$B$2:$B$1000,"<>",'Debt Backlog'!$N$2:$N$1000,"<>Done",'Debt Backlog'!$N$2:$N$1000,"<>Won't Fix",'Debt Backlog'!$N$2:$N$1000,"<>Duplicate")) | AI97: =IF($B97="","",ROUND(SUMIFS('Debt Backlog'!$L$2:$L$1000,'Debt Backlog'!$AF$2:$AF$1000,$A97,'Debt Backlog'!$B$2:$B$1000,"<>",'Debt Backlog'!$N$2:$N$1000,"<>Done",'Debt Backlog'!$N$2:$N$1000,"<>Won't Fix",'Debt Backlog'!$N$2:$N$1000,"<>Duplicate"),2))
N98: =IF(OR($B98="", $I98="", $J98="", $K98="", $L98="", $M98=""),"",ROUND(($I98*Lists!$AD$2)+($J98*Lists!$AD$3)+($K98*Lists!$AD$4)+($L98*Lists!$AD$5)+($M98*Lists!$AD$6),2)) | O98: =IF($A98="","",IFERROR(VLOOKUP($A98,'Risk Register'!$B$2:$I$1000,8,FALSE()),"")) | T98: =IF(OR($B98="", $P98="", $Q98="", $R98="", $S98=""),"",ROUND(($P98*Lists!$AD$7)+($Q98*Lists!$AD$8)+($R98*Lists!$AD$9)+($S98*Lists!$AD$10),2)) | Z98: =IF(OR($B98="", $U98="", $V98="", $W98="", $X98="", $Y98=""),"",ROUND(($U98*Lists!$AD$11)+($V98*Lists!$AD$12)+($W98*Lists!$AD$13)+($X98*Lists!$AD$14)+($Y98*Lists!$AD$15),2)) | AA98: =IF(OR($B98="", $N98="", $O98="", $T98="", $Z98=""),"",ROUND(($N98*Lists!$AD$16)-($O98*Lists!$AD$17)-($T98*Lists!$AD$18)+($Z98*Lists!$AD$19),2)) | AB98: =IF(OR($B98="", $N98="", $Z98=""),"",IF($N98>=Lists!$AG$2,IF($Z98>=Lists!$AG$3,"Invest","Migrate"),IF($Z98>=Lists!$AG$3,"Tolerate","Eliminate"))) | AC98: =IF($B98="","",IF($J98>=4,"Yes","")) | AD98: =IF($A98="","",IFERROR(IF(VLOOKUP($A98,'Risk Register'!$B$2:$H$1000,4,FALSE())>=4,"Yes",""),"")) | AE98: =IF(OR($N98="", $O98=""),"",IF($N98>=Lists!$AG$2,IF($O98>=Lists!$AG$4,"High Value / High Risk","High Value / Low Risk"),IF($O98>=Lists!$AG$4,"Low Value / High Risk","Low Value / Low Risk"))) | AH98: =IF($B98="","",COUNTIFS('Debt Backlog'!$AF$2:$AF$1000,$A98,'Debt Backlog'!$B$2:$B$1000,"<>",'Debt Backlog'!$N$2:$N$1000,"<>Done",'Debt Backlog'!$N$2:$N$1000,"<>Won't Fix",'Debt Backlog'!$N$2:$N$1000,"<>Duplicate")) | AI98: =IF($B98="","",ROUND(SUMIFS('Debt Backlog'!$L$2:$L$1000,'Debt Backlog'!$AF$2:$AF$1000,$A98,'Debt Backlog'!$B$2:$B$1000,"<>",'Debt Backlog'!$N$2:$N$1000,"<>Done",'Debt Backlog'!$N$2:$N$1000,"<>Won't Fix",'Debt Backlog'!$N$2:$N$1000,"<>Duplicate"),2))
... N1000: =IF(OR($B1000="", $I1000="", $J1000="", $K1000="", $L1000="", $M1000=""),"",ROUND(($I1000*Lists!$AD$2)+($J1000*Lists!$AD$3)+($K1000*Lists!$AD$4)+($L1000*Lists!$AD$5)+($M1000*Lists!$AD$6),2)) | O1000: =IF($A1000="","",IFERROR(VLOOKUP($A1000,'Risk Register'!$B$2:$I$1000,8,FALSE()),"")) | T1000: =IF(OR($B1000="", $P1000="", $Q1000="", $R1000="", $S1000=""),"",ROUND(($P1000*Lists!$AD$7)+($Q1000*Lists!$AD$8)+($R1000*Lists!$AD$9)+($S1000*Lists!$AD$10),2)) | Z1000: =IF(OR($B1000="", $U1000="", $V1000="", $W1000="", $X1000="", $Y1000=""),"",ROUND(($U1000*Lists!$AD$11)+($V1000*Lists!$AD$12)+($W1000*Lists!$AD$13)+($X1000*Lists!$AD$14)+($Y1000*Lists!$AD$15),2)) | AA1000: =IF(OR($B1000="", $N1000="", $O1000="", $T1000="", $Z1000=""),"",ROUND(($N1000*Lists!$AD$16)-($O1000*Lists!$AD$17)-($T1000*Lists!$AD$18)+($Z1000*Lists!$AD$19),2)) | AB1000: =IF(OR($B1000="", $N1000="", $Z1000=""),"",IF($N1000>=Lists!$AG$2,IF($Z1000>=Lists!$AG$3,"Invest","Migrate"),IF($Z1000>=Lists!$AG$3,"Tolerate","Eliminate"))) | AC1000: =IF($B1000="","",IF($J1000>=4,"Yes","")) | AD1000: =IF($A1000="","",IFERROR(IF(VLOOKUP($A1000,'Risk Register'!$B$2:$H$1000,4,FALSE())>=4,"Yes",""),"")) | AE1000: =IF(OR($N1000="", $O1000=""),"",IF($N1000>=Lists!$AG$2,IF($O1000>=Lists!$AG$4,"High Value / High Risk","High Value / Low Risk"),IF($O1000>=Lists!$AG$4,"Low Value / High Risk","Low Value / Low Risk"))) | AH1000: =IF($B1000="","",COUNTIFS('Debt Backlog'!$AF$2:$AF$1000,$A1000,'Debt Backlog'!$B$2:$B$1000,"<>",'Debt Backlog'!$N$2:$N$1000,"<>Done",'Debt Backlog'!$N$2:$N$1000,"<>Won't Fix",'Debt Backlog'!$N$2:$N$1000,"<>Duplicate")) | AI1000: =IF($B1000="","",ROUND(SUMIFS('Debt Backlog'!$L$2:$L$1000,'Debt Backlog'!$AF$2:$AF$1000,$A1000,'Debt Backlog'!$B$2:$B$1000,"<>",'Debt Backlog'!$N$2:$N$1000,"<>Done",'Debt Backlog'!$N$2:$N$1000,"<>Won't Fix",'Debt Backlog'!$N$2:$N$1000,"<>Duplicate"),2))

Sheet Lists
A1: Debt Type | C1: Impact Area | E1: Severity | F1: SeverityPts | H1: Impact | I1: ImpactPts | K1: Confidence | L1: ConfidenceWt | N1: Effort | O1: EffortPts | Q1: Priority | S1: Status | U1: Team | W1: Target Window | Y1: Score (1-5) | AA1: TIME Classification | AC1: Scoring Weights | AD1: Weight | AF1: APM Threshold | AG1: Value (>=) | AI1: Target Window | AJ1: Target Days | AL1: Debt Priority | AM1: Debt Score (>=) | AO1: Weight Check | AP1: Sum | AQ1: OK
A2: Code Quality | C2: Reliability | E2: Critical | F2: 4 | H2: High | I2: 3 | K2: High | L2: 1 | N2: XS | O2: 1 | Q2: P0 | S2: New | U2: Platform | W2: Backlog | Y2: 1 | AA2: Invest | AC2: BV: Strategic Alignment | AD2: 0.2 | AF2: High Business Value | AG2: 3 | AI2: Backlog | AL2: P0 | AM2: 3.5 | AO2: Business Value | AP2: =SUM(AD2:AD6) -> 1 | AQ2: =IF(ABS(AP2-1)<0.0001,"Yes","No") -> Yes
A3: Architecture | C3: Scalability | E3: High | F3: 3 | H3: Medium | I3: 2 | K3: Medium | L3: 0.8 | N3: S | O3: 2 | Q3: P1 | S3: Triaged | U3: Backend | W3: Next Sprint | Y3: 2 | AA3: Tolerate | AC3: BV: Clinical / Business Criticality | AD3: 0.2 | AF3: High Technical Health | AG3: 3 | AI3: Next Sprint | AJ3: 14 | AL3: P1 | AM3: 2.5 | AO3: Cost | AP3: =SUM(AD7:AD10) -> 1 | AQ3: =IF(ABS(AP3-1)<0.0001,"Yes","No") -> Yes
A4: Infrastructure | C4: Security | E4: Medium | F4: 2 | H4: Low | I4: 1 | K4: Low | L4: 0.6 | N4: M | O4: 3 | Q4: P2 | S4: Planned | U4: Frontend | W4: Next 2 Sprints | Y4: 3 | AA4: Migrate | AC4: BV: User Reach & Dependency | AD4: 0.2 | AF4: High Risk | AG4: 3.5 | AI4: Next 2 Sprints | AJ4: 28 | AL4: P2 | AM4: 1.5 | AO4: Technical Health | AP4: =SUM(AD11:AD15) -> 1 | AQ4: =IF(ABS(AP4-1)<0.0001,"Yes","No") -> Yes
A5: Security | C5: Performance | E5: Low | F5: 1 | N5: L | O5: 5 | Q5: P3 | S5: In Progress | U5: Mobile | W5: This Quarter | Y5: 4 | AA5: Eliminate | AC5: BV: Differentiation | AD5: 0.2 | AF5: Moderate Risk | AG5: 2.5 | AI5: This Quarter | AJ5: 90 | AL5: P3 | AO5: Risk | AP5: =SUM(AD20:AD24) -> 1 | AQ5: =IF(ABS(AP5-1)<0.0001,"Yes","No") -> Yes
A6: Observability | C6: Maintainability | N6: XL | O6: 8 | S6: Blocked | U6: Data | W6: Next Quarter | Y6: 5 | AC6: BV: Regulatory Necessity | AD6: 0.2 | AF6: High Cost | AG6: 3.5 | AI6: Next Quarter | AJ6: 180
A7: Test Coverage | C7: Developer Productivity | S7: Done | U7: DevOps | W7: TBD | AC7: Cost: Annual Run Cost | AD7: 0.25 | AI7: TBD
A8: Documentation | C8: Compliance | S8: Won't Fix | U8: Security | AC8: Cost: Cost Trend | AD8: 0.25
A9: Dependencies/Upgrades | C9: Cost | S9: Duplicate | U9: QA | AC9: Cost: Cost Transparency | AD9: 0.25
A10: Performance | C10: User Experience | U10: Other | AC10: Cost: Modernization Cost | AD10: 0.25
A11: UX | C11: Other | AC11: TH: Technology Currency | AD11: 0.2
A12: Process | AC12: TH: Architecture Quality | AD12: 0.2
A13: Other | AC13: TH: Integration Complexity | AD13: 0.2
AC14: TH: Data Architecture Fit | AD14: 0.2
AC15: TH: Technical Debt | AD15: 0.2
AC16: CPS: Business Value (+) | AD16: 0.25
AC17: CPS: Risk (-) | AD17: 0.25
AC18: CPS: Cost (-) | AD18: 0.25
AC19: CPS: Technical Health (+) | AD19: 0.25
AC20: Risk: Cybersecurity | AD20: 0.2
AC21: Risk: Compliance | AD21: 0.2
AC22: Risk: Operational Resilience | AD22: 0.2
AC23: Risk: Vendor | AD23: 0.2
AC24: Risk: Knowledge Concentration | AD24: 0.2
AC26: Even defaults. Each group should sum to 1.00 (CPS weights are applied with the signs shown). Calibrated weights are part of the full simulator.
