Workbook

Sheet Overview
A1: Technical Debt Carry Cost Optimizer (Preview)
A2: The carry-cost math and priority ranking, per item, for a portfolio of up to 40 debt items. The full version adds the constrained multi-year sequencer.
A3: Inputs live on Parameters and Debt Portfolio (shaded cells). Everything here recalculates from them.
A5: Plan Parameters | E5: Portfolio at a Glance
A6: Organization | B6: =Parameters!B6 -> Example Healthcare Software Co | E6: Items in portfolio | F6: =COUNTA('Debt Portfolio'!B2:B41) -> 12
A7: Planning horizon (years) | B7: =Parameters!B7 -> 5 | E7: Open items | F7: =COUNTIFS('Debt Portfolio'!B2:B41,"<>",'Debt Portfolio'!E2:E41,"Open") -> 12
A8: Annual budget ($) | B8: =Parameters!B8 -> 2000000 | E8: Open items ranked | F8: =COUNT('Debt Portfolio'!Z2:Z41) -> 12
A9: Annual capacity (engineer-days) | B9: =Parameters!B9 -> 750 | E9: Items others depend on | F9: =COUNTIFS('Debt Portfolio'!W2:W41,"Yes",'Debt Portfolio'!E2:E41,"Open") -> 1
A10: Discount rate | B10: =Parameters!B10 -> 0.08 | E10: Total remediation cost, open items ($) | F10: =SUMIFS('Debt Portfolio'!F2:F41,'Debt Portfolio'!E2:E41,"Open") -> 3885000
A12: Cost of Doing Nothing | E12: Open Items by Priority
A13: Annual cost of doing nothing, today ($) | B13: =SUMIFS('Debt Portfolio'!M2:M41,'Debt Portfolio'!E2:E41,"Open") -> 8547000 | E13: High | F13: =COUNTIFS('Debt Portfolio'!X2:X41,"High",'Debt Portfolio'!E2:E41,"Open") -> 6
A14: NPV cost if nothing is remediated ($) | B14: =SUMIFS('Debt Portfolio'!N2:N41,'Debt Portfolio'!E2:E41,"Open") -> 39659039 | E14: Medium | F14: =COUNTIFS('Debt Portfolio'!X2:X41,"Medium",'Debt Portfolio'!E2:E41,"Open") -> 5
A15: NPV savings if everything were fixed in year 1 ($) | B15: =SUMIFS('Debt Portfolio'!O2:O41,'Debt Portfolio'!E2:E41,"Open") -> 28147928 | E15: Low | F15: =COUNTIFS('Debt Portfolio'!X2:X41,"Low",'Debt Portfolio'!E2:E41,"Open") -> 1
A16: Items that pay back within the horizon | B16: =COUNTIFS('Debt Portfolio'!U2:U41,">0",'Debt Portfolio'!E2:E41,"Open") -> 11
A17: Items to accept as carry (no payback) | B17: =COUNTIFS('Debt Portfolio'!T2:T41,"Accept",'Debt Portfolio'!E2:E41,"Open") -> 1
A19: Ranked List (top 12 by priority, then NPV savings)
A20: Rank | B20: ID | C20: Name | D20: Priority | E20: Best Year | F20: Best NPV Savings ($)
A21: 1 | B21: =IFERROR(INDEX('Debt Portfolio'!$A$2:$A$41,MATCH(1,'Debt Portfolio'!$Z$2:$Z$41,0)),"") -> OPS-001 | C21: =IFERROR(INDEX('Debt Portfolio'!$B$2:$B$41,MATCH(1,'Debt Portfolio'!$Z$2:$Z$41,0)),"") -> Cloud cost waste - 24/7 dev environments and no RIs | D21: =IFERROR(INDEX('Debt Portfolio'!$X$2:$X$41,MATCH(1,'Debt Portfolio'!$Z$2:$Z$41,0)),"") -> High | E21: =IFERROR(INDEX('Debt Portfolio'!$T$2:$T$41,MATCH(1,'Debt Portfolio'!$Z$2:$Z$41,0)),"") -> 1 | F21: =IFERROR(INDEX('Debt Portfolio'!$U$2:$U$41,MATCH(1,'Debt Portfolio'!$Z$2:$Z$41,0)),"") -> 16160474
A22: 2 | B22: =IFERROR(INDEX('Debt Portfolio'!$A$2:$A$41,MATCH(2,'Debt Portfolio'!$Z$2:$Z$41,0)),"") -> SEC-001 | C22: =IFERROR(INDEX('Debt Portfolio'!$B$2:$B$41,MATCH(2,'Debt Portfolio'!$Z$2:$Z$41,0)),"") -> SOC 2 Type II expired - access control remediation needed | D22: =IFERROR(INDEX('Debt Portfolio'!$X$2:$X$41,MATCH(2,'Debt Portfolio'!$Z$2:$Z$41,0)),"") -> High | E22: =IFERROR(INDEX('Debt Portfolio'!$T$2:$T$41,MATCH(2,'Debt Portfolio'!$Z$2:$Z$41,0)),"") -> 1 | F22: =IFERROR(INDEX('Debt Portfolio'!$U$2:$U$41,MATCH(2,'Debt Portfolio'!$Z$2:$Z$41,0)),"") -> 5184561.7
A23: 3 | B23: =IFERROR(INDEX('Debt Portfolio'!$A$2:$A$41,MATCH(3,'Debt Portfolio'!$Z$2:$Z$41,0)),"") -> PEOPLE-001 | C23: =IFERROR(INDEX('Debt Portfolio'!$B$2:$B$41,MATCH(3,'Debt Portfolio'!$Z$2:$Z$41,0)),"") -> Key person concentration on platform code | D23: =IFERROR(INDEX('Debt Portfolio'!$X$2:$X$41,MATCH(3,'Debt Portfolio'!$Z$2:$Z$41,0)),"") -> High | E23: =IFERROR(INDEX('Debt Portfolio'!$T$2:$T$41,MATCH(3,'Debt Portfolio'!$Z$2:$Z$41,0)),"") -> 1 | F23: =IFERROR(INDEX('Debt Portfolio'!$U$2:$U$41,MATCH(3,'Debt Portfolio'!$Z$2:$Z$41,0)),"") -> 1938187.6
A24: 4 | B24: =IFERROR(INDEX('Debt Portfolio'!$A$2:$A$41,MATCH(4,'Debt Portfolio'!$Z$2:$Z$41,0)),"") -> IP-001 | C24: =IFERROR(INDEX('Debt Portfolio'!$B$2:$B$41,MATCH(4,'Debt Portfolio'!$Z$2:$Z$41,0)),"") -> Missing IP assignments for 12 engineers | D24: =IFERROR(INDEX('Debt Portfolio'!$X$2:$X$41,MATCH(4,'Debt Portfolio'!$Z$2:$Z$41,0)),"") -> High | E24: =IFERROR(INDEX('Debt Portfolio'!$T$2:$T$41,MATCH(4,'Debt Portfolio'!$Z$2:$Z$41,0)),"") -> 1 | F24: =IFERROR(INDEX('Debt Portfolio'!$U$2:$U$41,MATCH(4,'Debt Portfolio'!$Z$2:$Z$41,0)),"") -> 1573434.5
A25: 5 | B25: =IFERROR(INDEX('Debt Portfolio'!$A$2:$A$41,MATCH(5,'Debt Portfolio'!$Z$2:$Z$41,0)),"") -> OPS-002 | C25: =IFERROR(INDEX('Debt Portfolio'!$B$2:$B$41,MATCH(5,'Debt Portfolio'!$Z$2:$Z$41,0)),"") -> DR plan never validated | D25: =IFERROR(INDEX('Debt Portfolio'!$X$2:$X$41,MATCH(5,'Debt Portfolio'!$Z$2:$Z$41,0)),"") -> High | E25: =IFERROR(INDEX('Debt Portfolio'!$T$2:$T$41,MATCH(5,'Debt Portfolio'!$Z$2:$Z$41,0)),"") -> 1 | F25: =IFERROR(INDEX('Debt Portfolio'!$U$2:$U$41,MATCH(5,'Debt Portfolio'!$Z$2:$Z$41,0)),"") -> 1429366.1
A26: 6 | B26: =IFERROR(INDEX('Debt Portfolio'!$A$2:$A$41,MATCH(6,'Debt Portfolio'!$Z$2:$Z$41,0)),"") -> SEC-002 | C26: =IFERROR(INDEX('Debt Portfolio'!$B$2:$B$41,MATCH(6,'Debt Portfolio'!$Z$2:$Z$41,0)),"") -> Two unremediated High pen test findings | D26: =IFERROR(INDEX('Debt Portfolio'!$X$2:$X$41,MATCH(6,'Debt Portfolio'!$Z$2:$Z$41,0)),"") -> High | E26: =IFERROR(INDEX('Debt Portfolio'!$T$2:$T$41,MATCH(6,'Debt Portfolio'!$Z$2:$Z$41,0)),"") -> 1 | F26: =IFERROR(INDEX('Debt Portfolio'!$U$2:$U$41,MATCH(6,'Debt Portfolio'!$Z$2:$Z$41,0)),"") -> 633812.16
A27: 7 | B27: =IFERROR(INDEX('Debt Portfolio'!$A$2:$A$41,MATCH(7,'Debt Portfolio'!$Z$2:$Z$41,0)),"") -> ARCH-001 | C27: =IFERROR(INDEX('Debt Portfolio'!$B$2:$B$41,MATCH(7,'Debt Portfolio'!$Z$2:$Z$41,0)),"") -> Multi-tenancy migration abandoned mid-flight | D27: =IFERROR(INDEX('Debt Portfolio'!$X$2:$X$41,MATCH(7,'Debt Portfolio'!$Z$2:$Z$41,0)),"") -> Medium | E27: =IFERROR(INDEX('Debt Portfolio'!$T$2:$T$41,MATCH(7,'Debt Portfolio'!$Z$2:$Z$41,0)),"") -> 1 | F27: =IFERROR(INDEX('Debt Portfolio'!$U$2:$U$41,MATCH(7,'Debt Portfolio'!$Z$2:$Z$41,0)),"") -> 583984.38
A28: 8 | B28: =IFERROR(INDEX('Debt Portfolio'!$A$2:$A$41,MATCH(8,'Debt Portfolio'!$Z$2:$Z$41,0)),"") -> ARCH-002 | C28: =IFERROR(INDEX('Debt Portfolio'!$B$2:$B$41,MATCH(8,'Debt Portfolio'!$Z$2:$Z$41,0)),"") -> PostgreSQL 11 EOL - upgrade required | D28: =IFERROR(INDEX('Debt Portfolio'!$X$2:$X$41,MATCH(8,'Debt Portfolio'!$Z$2:$Z$41,0)),"") -> Medium | E28: =IFERROR(INDEX('Debt Portfolio'!$T$2:$T$41,MATCH(8,'Debt Portfolio'!$Z$2:$Z$41,0)),"") -> 1 | F28: =IFERROR(INDEX('Debt Portfolio'!$U$2:$U$41,MATCH(8,'Debt Portfolio'!$Z$2:$Z$41,0)),"") -> 345563.18
A29: 9 | B29: =IFERROR(INDEX('Debt Portfolio'!$A$2:$A$41,MATCH(9,'Debt Portfolio'!$Z$2:$Z$41,0)),"") -> DATA-002 | C29: =IFERROR(INDEX('Debt Portfolio'!$B$2:$B$41,MATCH(9,'Debt Portfolio'!$Z$2:$Z$41,0)),"") -> Three different MAU definitions across teams | D29: =IFERROR(INDEX('Debt Portfolio'!$X$2:$X$41,MATCH(9,'Debt Portfolio'!$Z$2:$Z$41,0)),"") -> Medium | E29: =IFERROR(INDEX('Debt Portfolio'!$T$2:$T$41,MATCH(9,'Debt Portfolio'!$Z$2:$Z$41,0)),"") -> 1 | F29: =IFERROR(INDEX('Debt Portfolio'!$U$2:$U$41,MATCH(9,'Debt Portfolio'!$Z$2:$Z$41,0)),"") -> 171306.29
A30: 10 | B30: =IFERROR(INDEX('Debt Portfolio'!$A$2:$A$41,MATCH(10,'Debt Portfolio'!$Z$2:$Z$41,0)),"") -> DATA-001 | C30: =IFERROR(INDEX('Debt Portfolio'!$B$2:$B$41,MATCH(10,'Debt Portfolio'!$Z$2:$Z$41,0)),"") -> Customer churn calculation bug | D30: =IFERROR(INDEX('Debt Portfolio'!$X$2:$X$41,MATCH(10,'Debt Portfolio'!$Z$2:$Z$41,0)),"") -> Medium | E30: =IFERROR(INDEX('Debt Portfolio'!$T$2:$T$41,MATCH(10,'Debt Portfolio'!$Z$2:$Z$41,0)),"") -> 1 | F30: =IFERROR(INDEX('Debt Portfolio'!$U$2:$U$41,MATCH(10,'Debt Portfolio'!$Z$2:$Z$41,0)),"") -> 133900.79
A31: 11 | B31: =IFERROR(INDEX('Debt Portfolio'!$A$2:$A$41,MATCH(11,'Debt Portfolio'!$Z$2:$Z$41,0)),"") -> PROCESS-001 | C31: =IFERROR(INDEX('Debt Portfolio'!$B$2:$B$41,MATCH(11,'Debt Portfolio'!$Z$2:$Z$41,0)),"") -> No DORA metrics tracking | D31: =IFERROR(INDEX('Debt Portfolio'!$X$2:$X$41,MATCH(11,'Debt Portfolio'!$Z$2:$Z$41,0)),"") -> Medium | E31: =IFERROR(INDEX('Debt Portfolio'!$T$2:$T$41,MATCH(11,'Debt Portfolio'!$Z$2:$Z$41,0)),"") -> 1 | F31: =IFERROR(INDEX('Debt Portfolio'!$U$2:$U$41,MATCH(11,'Debt Portfolio'!$Z$2:$Z$41,0)),"") -> 60318.017
A32: 12 | B32: =IFERROR(INDEX('Debt Portfolio'!$A$2:$A$41,MATCH(12,'Debt Portfolio'!$Z$2:$Z$41,0)),"") -> ARCH-003 | C32: =IFERROR(INDEX('Debt Portfolio'!$B$2:$B$41,MATCH(12,'Debt Portfolio'!$Z$2:$Z$41,0)),"") -> Code modernization to support multi-tenancy | D32: =IFERROR(INDEX('Debt Portfolio'!$X$2:$X$41,MATCH(12,'Debt Portfolio'!$Z$2:$Z$41,0)),"") -> Low | E32: =IFERROR(INDEX('Debt Portfolio'!$T$2:$T$41,MATCH(12,'Debt Portfolio'!$Z$2:$Z$41,0)),"") -> Accept | F32: =IFERROR(INDEX('Debt Portfolio'!$U$2:$U$41,MATCH(12,'Debt Portfolio'!$Z$2:$Z$41,0)),"") -> -66980.771
A34: What the full optimizer adds
A35: A multi-year remediation plan: each item placed in the first year where annual budget, engineering capacity, and its dependency chain allow, with items that fit nowhere marked as deferred and their carried cost reported as accepted risk.
A36: A rationale per item explaining why it landed in its year, the year-by-year budget and capacity utilization, and the NPV of the plan against no action.
A37: In the production version: a learned priority scorer, skill-mix capacity pools, sensitivity ranges on cost inputs, and quarterly replanning. Available through direct engagement.

Sheet Parameters
A1: Technical Debt Carry Cost Optimizer (Preview)
A2: Multi-year remediation sequencing that minimizes carry cost plus remediation cost plus expected incident cost, within an annual budget and engineering capacity.
A3: Shaded cells on this sheet and on Debt Portfolio are inputs. Everything else is calculated. Lists holds the dropdown options and priority thresholds.
A5: Plan Parameters
A6: Organization | B6: Example Healthcare Software Co
A7: Planning horizon (years, 1 to 5) | B7: 5
A8: Annual remediation budget ($) | B8: 2000000
A9: Annual capacity (engineer-days) | B9: 750
A10: Discount rate | B10: 0.08
A11: Loaded cost per engineer-day ($, reference only) | B11: 1200
A13: How the math works
A14: Cost if never remediated, over the horizon T: sum over years t of carry x (1+growth)^(t-1) x discount(t), plus incident probability x incident cost x discount(t).
A15: Cost if remediated in year Y: the same carry and incident terms for years 1 to Y, plus remediation cost x discount(Y).
A16: NPV savings of remediating in year Y = cost if never minus cost if remediated in year Y. Best year is the Y with the highest savings.
A17: Priority class comes from the savings ratio (year-1 NPV savings divided by remediation cost) against the thresholds on Lists, with a bump for items that others depend on.
A18: The plan is a greedy allocation: items are ranked by priority class, then NPV savings, then carry growth; the full version places each in the first year where budget, capacity, and its dependency allow.
A19: This preview stops at the ranking. The multi-year sequencer, the rationale generator, and the production optimizer are available through direct engagement.

Sheet Lists
A1: Domain | C1: Status | E1: Priority | F1: Savings Ratio >= | G1: Sort Order | I1: Dependency-target bump (added to savings ratio)
A2: Architecture | C2: Open | E2: High | F2: 3 | G2: 1 | I2: 1
A3: Code | C3: Done | E3: Medium | F3: 1 | G3: 2
A4: Infrastructure | C4: Accepted | E4: Low | F4: -1000000000 | G4: 3
A5: Data
A6: Security | E6: Priority thresholds: an item is High if its savings ratio is at or above the High threshold, Medium if at or above the Medium threshold, otherwise Low. Edit the shaded cells.
A7: People
A8: Process
A9: General

Sheet Debt Portfolio
A1: ID | B1: Name | C1: Domain | D1: Description | E1: Status | F1: Remediation Cost ($) | G1: Annual Carry Cost ($) | H1: Carry Growth Rate | I1: Incident Probability / yr | J1: Incident Cost ($) | K1: Effort (engineer-days) | L1: Depends On (ID) | M1: Expected Annual Loss ($) | N1: NPV Cost If Never ($) | O1: NPV Savings Y1 ($) | P1: NPV Savings Y2 ($) | Q1: NPV Savings Y3 ($) | R1: NPV Savings Y4 ($) | S1: NPV Savings Y5 ($) | T1: Best Year | U1: Best NPV Savings ($) | V1: Savings Ratio | W1: Depended On By Others | X1: Priority | Y1: Sort Key | Z1: Rank | AA1: Planned Year (full version) | AB1: NPV Cost Fix Y1 ($) | AC1: NPV Cost Fix Y2 ($) | AD1: NPV Cost Fix Y3 ($) | AE1: NPV Cost Fix Y4 ($) | AF1: NPV Cost Fix Y5 ($) | AG1: Carry Y1 ($) | AH1: Carry Y2 ($) | AI1: Carry Y3 ($) | AJ1: Carry Y4 ($) | AK1: Carry Y5 ($)
A2: ARCH-001 | B2: Multi-tenancy migration abandoned mid-flight | C2: Architecture | D2: Single-tenant deployment requires manual provisioning, blocks enterprise expansion | E2: Open | F2: 1500000 | G2: 350000 | H2: 0.12 | I2: 0.06 | J2: 3000000 | K2: 360 | M2: =IF($B2="","",$G2+$I2*$J2) -> 530000 | N2: =IF($B2="","",IF(Parameters!$B$7<=0,0,IF(ABS((1+$H2)/(1+Parameters!$B$10)-1)<0.000001,Parameters!$B$7*$G2/(1+Parameters!$B$10),$G2/(1+Parameters!$B$10)*(1-((1+$H2)/(1+Parameters!$B$10))^Parameters!$B$7)/(1-(1+$H2)/(1+Parameters!$B$10))))+IF(Parameters!$B$7<=0,0,IF(Parameters!$B$10=0,Parameters!$B$7*$I2*$J2,$I2*$J2*(1-(1/(1+Parameters!$B$10))^Parameters!$B$7)/Parameters!$B$10))) -> 2463614 | O2: =IF(OR($B2="",1>Parameters!$B$7),"",$N2-AB2) -> 583984.38 | P2: =IF(OR($B2="",2>Parameters!$B$7),"",$N2-AC2) -> 196467.23 | Q2: =IF(OR($B2="",3>Parameters!$B$7),"",$N2-AD2) -> -199686.81 | R2: =IF(OR($B2="",4>Parameters!$B$7),"",$N2-AE2) -> -605221.01 | S2: =IF(OR($B2="",5>Parameters!$B$7),"",$N2-AF2) -> -1020874.8 | T2: =IF($B2="","",IF(MAX($O2:$S2)<0,"Accept",MATCH(MAX($O2:$S2),$O2:$S2,0))) -> 1 | U2: =IF($B2="","",MAX($O2:$S2)) -> 583984.38 | V2: =IF($B2="","",IF($F2>0,ROUND($O2/$F2,2),IF(N($O2)>0,Lists!$F$2,0))+IF($W2="Yes",Lists!$I$2,0)) -> 1.39 | W2: =IF($B2="","",IF(COUNTIFS($L$2:$L$41,$A2,$E$2:$E$41,"Open",$A$2:$A$41,"<>"&$A2)>0,"Yes","No")) -> Yes | X2: =IF($B2="","",IF($V2>=Lists!$F$2,"High",IF($V2>=Lists!$F$3,"Medium","Low"))) -> Medium | Y2: =IF(OR($B2="",$E2<>"Open"),"",IF($L2="",(INDEX(Lists!$G$2:$G$4,MATCH($X2,Lists!$E$2:$E$4,0))*1000000000000-$U2-$H2),IFERROR(MAX((INDEX(Lists!$G$2:$G$4,MATCH($X2,Lists!$E$2:$E$4,0))*1000000000000-$U2-$H2),INDEX($Y$2:$Y$41,MATCH($L2,$A$2:$A$41,0))+1),(INDEX(Lists!$G$2:$G$4,MATCH($X2,Lists!$E$2:$E$4,0))*1000000000000-$U2-$H2)))) -> 1.9999994e+12 | Z2: =IF($Y2="","",RANK($Y2,$Y$2:$Y$41,1)+COUNTIF($Y$2:$Y2,$Y2)-1) -> 7 | AA2: ="" | AB2: =IF(OR($B2="",1>Parameters!$B$7),"",IF(1<=0,0,IF(ABS((1+$H2)/(1+Parameters!$B$10)-1)<0.000001,1*$G2/(1+Parameters!$B$10),$G2/(1+Parameters!$B$10)*(1-((1+$H2)/(1+Parameters!$B$10))^1)/(1-(1+$H2)/(1+Parameters!$B$10))))+$F2/(1+Parameters!$B$10)^1+IF(1<=0,0,IF(Parameters!$B$10=0,1*$I2*$J2,$I2*$J2*(1-(1/(1+Parameters!$B$10))^1)/Parameters!$B$10))) -> 1879629.6 | AC2: =IF(OR($B2="",2>Parameters!$B$7),"",IF(2<=0,0,IF(ABS((1+$H2)/(1+Parameters!$B$10)-1)<0.000001,2*$G2/(1+Parameters!$B$10),$G2/(1+Parameters!$B$10)*(1-((1+$H2)/(1+Parameters!$B$10))^2)/(1-(1+$H2)/(1+Parameters!$B$10))))+$F2/(1+Parameters!$B$10)^2+IF(2<=0,0,IF(Parameters!$B$10=0,2*$I2*$J2,$I2*$J2*(1-(1/(1+Parameters!$B$10))^2)/Parameters!$B$10))) -> 2267146.8 | AD2: =IF(OR($B2="",3>Parameters!$B$7),"",IF(3<=0,0,IF(ABS((1+$H2)/(1+Parameters!$B$10)-1)<0.000001,3*$G2/(1+Parameters!$B$10),$G2/(1+Parameters!$B$10)*(1-((1+$H2)/(1+Parameters!$B$10))^3)/(1-(1+$H2)/(1+Parameters!$B$10))))+$F2/(1+Parameters!$B$10)^3+IF(3<=0,0,IF(Parameters!$B$10=0,3*$I2*$J2,$I2*$J2*(1-(1/(1+Parameters!$B$10))^3)/Parameters!$B$10))) -> 2663300.8 | AE2: =IF(OR($B2="",4>Parameters!$B$7),"",IF(4<=0,0,IF(ABS((1+$H2)/(1+Parameters!$B$10)-1)<0.000001,4*$G2/(1+Parameters!$B$10),$G2/(1+Parameters!$B$10)*(1-((1+$H2)/(1+Parameters!$B$10))^4)/(1-(1+$H2)/(1+Parameters!$B$10))))+$F2/(1+Parameters!$B$10)^4+IF(4<=0,0,IF(Parameters!$B$10=0,4*$I2*$J2,$I2*$J2*(1-(1/(1+Parameters!$B$10))^4)/Parameters!$B$10))) -> 3068835 | AF2: =IF(OR($B2="",5>Parameters!$B$7),"",IF(5<=0,0,IF(ABS((1+$H2)/(1+Parameters!$B$10)-1)<0.000001,5*$G2/(1+Parameters!$B$10),$G2/(1+Parameters!$B$10)*(1-((1+$H2)/(1+Parameters!$B$10))^5)/(1-(1+$H2)/(1+Parameters!$B$10))))+$F2/(1+Parameters!$B$10)^5+IF(5<=0,0,IF(Parameters!$B$10=0,5*$I2*$J2,$I2*$J2*(1-(1/(1+Parameters!$B$10))^5)/Parameters!$B$10))) -> 3484488.8 | AG2: =IF(OR($B2="",1>Parameters!$B$7),"",$G2*(1+$H2)^(1-1)) -> 350000 | AH2: =IF(OR($B2="",2>Parameters!$B$7),"",$G2*(1+$H2)^(2-1)) -> 392000 | AI2: =IF(OR($B2="",3>Parameters!$B$7),"",$G2*(1+$H2)^(3-1)) -> 439040 | AJ2: =IF(OR($B2="",4>Parameters!$B$7),"",$G2*(1+$H2)^(4-1)) -> 491724.8 | AK2: =IF(OR($B2="",5>Parameters!$B$7),"",$G2*(1+$H2)^(5-1)) -> 550731.78
A3: SEC-001 | B3: SOC 2 Type II expired - access control remediation needed | C3: Security | D3: Enterprise pipeline blocked, growing as more customers require SOC 2 | E3: Open | F3: 250000 | G3: 800000 | H3: 0.2 | I3: 0.1 | J3: 5000000 | K3: 90 | M3: =IF($B3="","",$G3+$I3*$J3) -> 1300000 | N3: =IF($B3="","",IF(Parameters!$B$7<=0,0,IF(ABS((1+$H3)/(1+Parameters!$B$10)-1)<0.000001,Parameters!$B$7*$G3/(1+Parameters!$B$10),$G3/(1+Parameters!$B$10)*(1-((1+$H3)/(1+Parameters!$B$10))^Parameters!$B$7)/(1-(1+$H3)/(1+Parameters!$B$10))))+IF(Parameters!$B$7<=0,0,IF(Parameters!$B$10=0,Parameters!$B$7*$I3*$J3,$I3*$J3*(1-(1/(1+Parameters!$B$10))^Parameters!$B$7)/Parameters!$B$10))) -> 6619746.9 | O3: =IF(OR($B3="",1>Parameters!$B$7),"",$N3-AB3) -> 5184561.7 | P3: =IF(OR($B3="",2>Parameters!$B$7),"",$N3-AC3) -> 3949993.8 | Q3: =IF(OR($B3="",3>Parameters!$B$7),"",$N3-AD3) -> 2654459.6 | R3: =IF(OR($B3="",4>Parameters!$B$7),"",$N3-AE3) -> 1285540 | S3: =IF(OR($B3="",5>Parameters!$B$7),"",$N3-AF3) -> -170145.8 | T3: =IF($B3="","",IF(MAX($O3:$S3)<0,"Accept",MATCH(MAX($O3:$S3),$O3:$S3,0))) -> 1 | U3: =IF($B3="","",MAX($O3:$S3)) -> 5184561.7 | V3: =IF($B3="","",IF($F3>0,ROUND($O3/$F3,2),IF(N($O3)>0,Lists!$F$2,0))+IF($W3="Yes",Lists!$I$2,0)) -> 20.74 | W3: =IF($B3="","",IF(COUNTIFS($L$2:$L$41,$A3,$E$2:$E$41,"Open",$A$2:$A$41,"<>"&$A3)>0,"Yes","No")) -> No | X3: =IF($B3="","",IF($V3>=Lists!$F$2,"High",IF($V3>=Lists!$F$3,"Medium","Low"))) -> High | Y3: =IF(OR($B3="",$E3<>"Open"),"",IF($L3="",(INDEX(Lists!$G$2:$G$4,MATCH($X3,Lists!$E$2:$E$4,0))*1000000000000-$U3-$H3),IFERROR(MAX((INDEX(Lists!$G$2:$G$4,MATCH($X3,Lists!$E$2:$E$4,0))*1000000000000-$U3-$H3),INDEX($Y$2:$Y$41,MATCH($L3,$A$2:$A$41,0))+1),(INDEX(Lists!$G$2:$G$4,MATCH($X3,Lists!$E$2:$E$4,0))*1000000000000-$U3-$H3)))) -> 9.9999482e+11 | Z3: =IF($Y3="","",RANK($Y3,$Y$2:$Y$41,1)+COUNTIF($Y$2:$Y3,$Y3)-1) -> 2 | AA3: ="" | AB3: =IF(OR($B3="",1>Parameters!$B$7),"",IF(1<=0,0,IF(ABS((1+$H3)/(1+Parameters!$B$10)-1)<0.000001,1*$G3/(1+Parameters!$B$10),$G3/(1+Parameters!$B$10)*(1-((1+$H3)/(1+Parameters!$B$10))^1)/(1-(1+$H3)/(1+Parameters!$B$10))))+$F3/(1+Parameters!$B$10)^1+IF(1<=0,0,IF(Parameters!$B$10=0,1*$I3*$J3,$I3*$J3*(1-(1/(1+Parameters!$B$10))^1)/Parameters!$B$10))) -> 1435185.2 | AC3: =IF(OR($B3="",2>Parameters!$B$7),"",IF(2<=0,0,IF(ABS((1+$H3)/(1+Parameters!$B$10)-1)<0.000001,2*$G3/(1+Parameters!$B$10),$G3/(1+Parameters!$B$10)*(1-((1+$H3)/(1+Parameters!$B$10))^2)/(1-(1+$H3)/(1+Parameters!$B$10))))+$F3/(1+Parameters!$B$10)^2+IF(2<=0,0,IF(Parameters!$B$10=0,2*$I3*$J3,$I3*$J3*(1-(1/(1+Parameters!$B$10))^2)/Parameters!$B$10))) -> 2669753.1 | AD3: =IF(OR($B3="",3>Parameters!$B$7),"",IF(3<=0,0,IF(ABS((1+$H3)/(1+Parameters!$B$10)-1)<0.000001,3*$G3/(1+Parameters!$B$10),$G3/(1+Parameters!$B$10)*(1-((1+$H3)/(1+Parameters!$B$10))^3)/(1-(1+$H3)/(1+Parameters!$B$10))))+$F3/(1+Parameters!$B$10)^3+IF(3<=0,0,IF(Parameters!$B$10=0,3*$I3*$J3,$I3*$J3*(1-(1/(1+Parameters!$B$10))^3)/Parameters!$B$10))) -> 3965287.3 | AE3: =IF(OR($B3="",4>Parameters!$B$7),"",IF(4<=0,0,IF(ABS((1+$H3)/(1+Parameters!$B$10)-1)<0.000001,4*$G3/(1+Parameters!$B$10),$G3/(1+Parameters!$B$10)*(1-((1+$H3)/(1+Parameters!$B$10))^4)/(1-(1+$H3)/(1+Parameters!$B$10))))+$F3/(1+Parameters!$B$10)^4+IF(4<=0,0,IF(Parameters!$B$10=0,4*$I3*$J3,$I3*$J3*(1-(1/(1+Parameters!$B$10))^4)/Parameters!$B$10))) -> 5334206.9 | AF3: =IF(OR($B3="",5>Parameters!$B$7),"",IF(5<=0,0,IF(ABS((1+$H3)/(1+Parameters!$B$10)-1)<0.000001,5*$G3/(1+Parameters!$B$10),$G3/(1+Parameters!$B$10)*(1-((1+$H3)/(1+Parameters!$B$10))^5)/(1-(1+$H3)/(1+Parameters!$B$10))))+$F3/(1+Parameters!$B$10)^5+IF(5<=0,0,IF(Parameters!$B$10=0,5*$I3*$J3,$I3*$J3*(1-(1/(1+Parameters!$B$10))^5)/Parameters!$B$10))) -> 6789892.7 | AG3: =IF(OR($B3="",1>Parameters!$B$7),"",$G3*(1+$H3)^(1-1)) -> 800000 | AH3: =IF(OR($B3="",2>Parameters!$B$7),"",$G3*(1+$H3)^(2-1)) -> 960000 | AI3: =IF(OR($B3="",3>Parameters!$B$7),"",$G3*(1+$H3)^(3-1)) -> 1152000 | AJ3: =IF(OR($B3="",4>Parameters!$B$7),"",$G3*(1+$H3)^(4-1)) -> 1382400 | AK3: =IF(OR($B3="",5>Parameters!$B$7),"",$G3*(1+$H3)^(5-1)) -> 1658880
A4: SEC-002 | B4: Two unremediated High pen test findings | C4: Security | D4: Risk acceptance memos missing, regulatory exposure | E4: Open | F4: 80000 | G4: 50000 | H4: 0.15 | I4: 0.08 | J4: 2000000 | K4: 30 | M4: =IF($B4="","",$G4+$I4*$J4) -> 210000 | N4: =IF($B4="","",IF(Parameters!$B$7<=0,0,IF(ABS((1+$H4)/(1+Parameters!$B$10)-1)<0.000001,Parameters!$B$7*$G4/(1+Parameters!$B$10),$G4/(1+Parameters!$B$10)*(1-((1+$H4)/(1+Parameters!$B$10))^Parameters!$B$7)/(1-(1+$H4)/(1+Parameters!$B$10))))+IF(Parameters!$B$7<=0,0,IF(Parameters!$B$10=0,Parameters!$B$7*$I4*$J4,$I4*$J4*(1-(1/(1+Parameters!$B$10))^Parameters!$B$7)/Parameters!$B$10))) -> 902330.68 | O4: =IF(OR($B4="",1>Parameters!$B$7),"",$N4-AB4) -> 633812.16 | P4: =IF(OR($B4="",2>Parameters!$B$7),"",$N4-AC4) -> 452827.94 | Q4: =IF(OR($B4="",3>Parameters!$B$7),"",$N4-AD4) -> 278403.15 | R4: =IF(OR($B4="",4>Parameters!$B$7),"",$N4-AE4) -> 109608.14 | S4: =IF(OR($B4="",5>Parameters!$B$7),"",$N4-AF4) -> -54446.656 | T4: =IF($B4="","",IF(MAX($O4:$S4)<0,"Accept",MATCH(MAX($O4:$S4),$O4:$S4,0))) -> 1 | U4: =IF($B4="","",MAX($O4:$S4)) -> 633812.16 | V4: =IF($B4="","",IF($F4>0,ROUND($O4/$F4,2),IF(N($O4)>0,Lists!$F$2,0))+IF($W4="Yes",Lists!$I$2,0)) -> 7.92 | W4: =IF($B4="","",IF(COUNTIFS($L$2:$L$41,$A4,$E$2:$E$41,"Open",$A$2:$A$41,"<>"&$A4)>0,"Yes","No")) -> No | X4: =IF($B4="","",IF($V4>=Lists!$F$2,"High",IF($V4>=Lists!$F$3,"Medium","Low"))) -> High | Y4: =IF(OR($B4="",$E4<>"Open"),"",IF($L4="",(INDEX(Lists!$G$2:$G$4,MATCH($X4,Lists!$E$2:$E$4,0))*1000000000000-$U4-$H4),IFERROR(MAX((INDEX(Lists!$G$2:$G$4,MATCH($X4,Lists!$E$2:$E$4,0))*1000000000000-$U4-$H4),INDEX($Y$2:$Y$41,MATCH($L4,$A$2:$A$41,0))+1),(INDEX(Lists!$G$2:$G$4,MATCH($X4,Lists!$E$2:$E$4,0))*1000000000000-$U4-$H4)))) -> 9.9999937e+11 | Z4: =IF($Y4="","",RANK($Y4,$Y$2:$Y$41,1)+COUNTIF($Y$2:$Y4,$Y4)-1) -> 6 | AA4: ="" | AB4: =IF(OR($B4="",1>Parameters!$B$7),"",IF(1<=0,0,IF(ABS((1+$H4)/(1+Parameters!$B$10)-1)<0.000001,1*$G4/(1+Parameters!$B$10),$G4/(1+Parameters!$B$10)*(1-((1+$H4)/(1+Parameters!$B$10))^1)/(1-(1+$H4)/(1+Parameters!$B$10))))+$F4/(1+Parameters!$B$10)^1+IF(1<=0,0,IF(Parameters!$B$10=0,1*$I4*$J4,$I4*$J4*(1-(1/(1+Parameters!$B$10))^1)/Parameters!$B$10))) -> 268518.52 | AC4: =IF(OR($B4="",2>Parameters!$B$7),"",IF(2<=0,0,IF(ABS((1+$H4)/(1+Parameters!$B$10)-1)<0.000001,2*$G4/(1+Parameters!$B$10),$G4/(1+Parameters!$B$10)*(1-((1+$H4)/(1+Parameters!$B$10))^2)/(1-(1+$H4)/(1+Parameters!$B$10))))+$F4/(1+Parameters!$B$10)^2+IF(2<=0,0,IF(Parameters!$B$10=0,2*$I4*$J4,$I4*$J4*(1-(1/(1+Parameters!$B$10))^2)/Parameters!$B$10))) -> 449502.74 | AD4: =IF(OR($B4="",3>Parameters!$B$7),"",IF(3<=0,0,IF(ABS((1+$H4)/(1+Parameters!$B$10)-1)<0.000001,3*$G4/(1+Parameters!$B$10),$G4/(1+Parameters!$B$10)*(1-((1+$H4)/(1+Parameters!$B$10))^3)/(1-(1+$H4)/(1+Parameters!$B$10))))+$F4/(1+Parameters!$B$10)^3+IF(3<=0,0,IF(Parameters!$B$10=0,3*$I4*$J4,$I4*$J4*(1-(1/(1+Parameters!$B$10))^3)/Parameters!$B$10))) -> 623927.53 | AE4: =IF(OR($B4="",4>Parameters!$B$7),"",IF(4<=0,0,IF(ABS((1+$H4)/(1+Parameters!$B$10)-1)<0.000001,4*$G4/(1+Parameters!$B$10),$G4/(1+Parameters!$B$10)*(1-((1+$H4)/(1+Parameters!$B$10))^4)/(1-(1+$H4)/(1+Parameters!$B$10))))+$F4/(1+Parameters!$B$10)^4+IF(4<=0,0,IF(Parameters!$B$10=0,4*$I4*$J4,$I4*$J4*(1-(1/(1+Parameters!$B$10))^4)/Parameters!$B$10))) -> 792722.54 | AF4: =IF(OR($B4="",5>Parameters!$B$7),"",IF(5<=0,0,IF(ABS((1+$H4)/(1+Parameters!$B$10)-1)<0.000001,5*$G4/(1+Parameters!$B$10),$G4/(1+Parameters!$B$10)*(1-((1+$H4)/(1+Parameters!$B$10))^5)/(1-(1+$H4)/(1+Parameters!$B$10))))+$F4/(1+Parameters!$B$10)^5+IF(5<=0,0,IF(Parameters!$B$10=0,5*$I4*$J4,$I4*$J4*(1-(1/(1+Parameters!$B$10))^5)/Parameters!$B$10))) -> 956777.34 | AG4: =IF(OR($B4="",1>Parameters!$B$7),"",$G4*(1+$H4)^(1-1)) -> 50000 | AH4: =IF(OR($B4="",2>Parameters!$B$7),"",$G4*(1+$H4)^(2-1)) -> 57500 | AI4: =IF(OR($B4="",3>Parameters!$B$7),"",$G4*(1+$H4)^(3-1)) -> 66125 | AJ4: =IF(OR($B4="",4>Parameters!$B$7),"",$G4*(1+$H4)^(4-1)) -> 76043.75 | AK4: =IF(OR($B4="",5>Parameters!$B$7),"",$G4*(1+$H4)^(5-1)) -> 87450.312
A5: PEOPLE-001 | B5: Key person concentration on platform code | C5: People | D5: Two engineers own 60% of platform code, both vest at close | E5: Open | F5: 400000 | G5: 200000 | H5: 0.25 | I5: 0.2 | J5: 2000000 | K5: 120 | M5: =IF($B5="","",$G5+$I5*$J5) -> 600000 | N5: =IF($B5="","",IF(Parameters!$B$7<=0,0,IF(ABS((1+$H5)/(1+Parameters!$B$10)-1)<0.000001,Parameters!$B$7*$G5/(1+Parameters!$B$10),$G5/(1+Parameters!$B$10)*(1-((1+$H5)/(1+Parameters!$B$10))^Parameters!$B$7)/(1-(1+$H5)/(1+Parameters!$B$10))))+IF(Parameters!$B$7<=0,0,IF(Parameters!$B$10=0,Parameters!$B$7*$I5*$J5,$I5*$J5*(1-(1/(1+Parameters!$B$10))^Parameters!$B$7)/Parameters!$B$10))) -> 2864113.5 | O5: =IF(OR($B5="",1>Parameters!$B$7),"",$N5-AB5) -> 1938187.6 | P5: =IF(OR($B5="",2>Parameters!$B$7),"",$N5-AC5) -> 1408352.2 | Q5: =IF(OR($B5="",3>Parameters!$B$7),"",$N5-AD5) -> 868149.37 | R5: =IF(OR($B5="",4>Parameters!$B$7),"",$N5-AE5) -> 310537.35 | S5: =IF(OR($B5="",5>Parameters!$B$7),"",$N5-AF5) -> -272233.28 | T5: =IF($B5="","",IF(MAX($O5:$S5)<0,"Accept",MATCH(MAX($O5:$S5),$O5:$S5,0))) -> 1 | U5: =IF($B5="","",MAX($O5:$S5)) -> 1938187.6 | V5: =IF($B5="","",IF($F5>0,ROUND($O5/$F5,2),IF(N($O5)>0,Lists!$F$2,0))+IF($W5="Yes",Lists!$I$2,0)) -> 4.85 | W5: =IF($B5="","",IF(COUNTIFS($L$2:$L$41,$A5,$E$2:$E$41,"Open",$A$2:$A$41,"<>"&$A5)>0,"Yes","No")) -> No | X5: =IF($B5="","",IF($V5>=Lists!$F$2,"High",IF($V5>=Lists!$F$3,"Medium","Low"))) -> High | Y5: =IF(OR($B5="",$E5<>"Open"),"",IF($L5="",(INDEX(Lists!$G$2:$G$4,MATCH($X5,Lists!$E$2:$E$4,0))*1000000000000-$U5-$H5),IFERROR(MAX((INDEX(Lists!$G$2:$G$4,MATCH($X5,Lists!$E$2:$E$4,0))*1000000000000-$U5-$H5),INDEX($Y$2:$Y$41,MATCH($L5,$A$2:$A$41,0))+1),(INDEX(Lists!$G$2:$G$4,MATCH($X5,Lists!$E$2:$E$4,0))*1000000000000-$U5-$H5)))) -> 9.9999806e+11 | Z5: =IF($Y5="","",RANK($Y5,$Y$2:$Y$41,1)+COUNTIF($Y$2:$Y5,$Y5)-1) -> 3 | AA5: ="" | AB5: =IF(OR($B5="",1>Parameters!$B$7),"",IF(1<=0,0,IF(ABS((1+$H5)/(1+Parameters!$B$10)-1)<0.000001,1*$G5/(1+Parameters!$B$10),$G5/(1+Parameters!$B$10)*(1-((1+$H5)/(1+Parameters!$B$10))^1)/(1-(1+$H5)/(1+Parameters!$B$10))))+$F5/(1+Parameters!$B$10)^1+IF(1<=0,0,IF(Parameters!$B$10=0,1*$I5*$J5,$I5*$J5*(1-(1/(1+Parameters!$B$10))^1)/Parameters!$B$10))) -> 925925.93 | AC5: =IF(OR($B5="",2>Parameters!$B$7),"",IF(2<=0,0,IF(ABS((1+$H5)/(1+Parameters!$B$10)-1)<0.000001,2*$G5/(1+Parameters!$B$10),$G5/(1+Parameters!$B$10)*(1-((1+$H5)/(1+Parameters!$B$10))^2)/(1-(1+$H5)/(1+Parameters!$B$10))))+$F5/(1+Parameters!$B$10)^2+IF(2<=0,0,IF(Parameters!$B$10=0,2*$I5*$J5,$I5*$J5*(1-(1/(1+Parameters!$B$10))^2)/Parameters!$B$10))) -> 1455761.3 | AD5: =IF(OR($B5="",3>Parameters!$B$7),"",IF(3<=0,0,IF(ABS((1+$H5)/(1+Parameters!$B$10)-1)<0.000001,3*$G5/(1+Parameters!$B$10),$G5/(1+Parameters!$B$10)*(1-((1+$H5)/(1+Parameters!$B$10))^3)/(1-(1+$H5)/(1+Parameters!$B$10))))+$F5/(1+Parameters!$B$10)^3+IF(3<=0,0,IF(Parameters!$B$10=0,3*$I5*$J5,$I5*$J5*(1-(1/(1+Parameters!$B$10))^3)/Parameters!$B$10))) -> 1995964.2 | AE5: =IF(OR($B5="",4>Parameters!$B$7),"",IF(4<=0,0,IF(ABS((1+$H5)/(1+Parameters!$B$10)-1)<0.000001,4*$G5/(1+Parameters!$B$10),$G5/(1+Parameters!$B$10)*(1-((1+$H5)/(1+Parameters!$B$10))^4)/(1-(1+$H5)/(1+Parameters!$B$10))))+$F5/(1+Parameters!$B$10)^4+IF(4<=0,0,IF(Parameters!$B$10=0,4*$I5*$J5,$I5*$J5*(1-(1/(1+Parameters!$B$10))^4)/Parameters!$B$10))) -> 2553576.2 | AF5: =IF(OR($B5="",5>Parameters!$B$7),"",IF(5<=0,0,IF(ABS((1+$H5)/(1+Parameters!$B$10)-1)<0.000001,5*$G5/(1+Parameters!$B$10),$G5/(1+Parameters!$B$10)*(1-((1+$H5)/(1+Parameters!$B$10))^5)/(1-(1+$H5)/(1+Parameters!$B$10))))+$F5/(1+Parameters!$B$10)^5+IF(5<=0,0,IF(Parameters!$B$10=0,5*$I5*$J5,$I5*$J5*(1-(1/(1+Parameters!$B$10))^5)/Parameters!$B$10))) -> 3136346.8 | AG5: =IF(OR($B5="",1>Parameters!$B$7),"",$G5*(1+$H5)^(1-1)) -> 200000 | AH5: =IF(OR($B5="",2>Parameters!$B$7),"",$G5*(1+$H5)^(2-1)) -> 250000 | AI5: =IF(OR($B5="",3>Parameters!$B$7),"",$G5*(1+$H5)^(3-1)) -> 312500 | AJ5: =IF(OR($B5="",4>Parameters!$B$7),"",$G5*(1+$H5)^(4-1)) -> 390625 | AK5: =IF(OR($B5="",5>Parameters!$B$7),"",$G5*(1+$H5)^(5-1)) -> 488281.25
A6: OPS-001 | B6: Cloud cost waste - 24/7 dev environments and no RIs | C6: Infrastructure | D6: $4.4M annual waste, easy quick win | E6: Open | F6: 150000 | G6: 4400000 | H6: 0.08 | I6: 0.01 | J6: 100000 | K6: 60 | M6: =IF($B6="","",$G6+$I6*$J6) -> 4401000 | N6: =IF($B6="","",IF(Parameters!$B$7<=0,0,IF(ABS((1+$H6)/(1+Parameters!$B$10)-1)<0.000001,Parameters!$B$7*$G6/(1+Parameters!$B$10),$G6/(1+Parameters!$B$10)*(1-((1+$H6)/(1+Parameters!$B$10))^Parameters!$B$7)/(1-(1+$H6)/(1+Parameters!$B$10))))+IF(Parameters!$B$7<=0,0,IF(Parameters!$B$10=0,Parameters!$B$7*$I6*$J6,$I6*$J6*(1-(1/(1+Parameters!$B$10))^Parameters!$B$7)/Parameters!$B$10))) -> 20374363 | O6: =IF(OR($B6="",1>Parameters!$B$7),"",$N6-AB6) -> 16160474 | P6: =IF(OR($B6="",2>Parameters!$B$7),"",$N6-AC6) -> 12095831 | Q6: =IF(OR($B6="",3>Parameters!$B$7),"",$N6-AD6) -> 8030488.9 | R6: =IF(OR($B6="",4>Parameters!$B$7),"",$N6-AE6) -> 3964500.2 | S6: =IF(OR($B6="",5>Parameters!$B$7),"",$N6-AF6) -> -102087.48 | T6: =IF($B6="","",IF(MAX($O6:$S6)<0,"Accept",MATCH(MAX($O6:$S6),$O6:$S6,0))) -> 1 | U6: =IF($B6="","",MAX($O6:$S6)) -> 16160474 | V6: =IF($B6="","",IF($F6>0,ROUND($O6/$F6,2),IF(N($O6)>0,Lists!$F$2,0))+IF($W6="Yes",Lists!$I$2,0)) -> 107.74 | W6: =IF($B6="","",IF(COUNTIFS($L$2:$L$41,$A6,$E$2:$E$41,"Open",$A$2:$A$41,"<>"&$A6)>0,"Yes","No")) -> No | X6: =IF($B6="","",IF($V6>=Lists!$F$2,"High",IF($V6>=Lists!$F$3,"Medium","Low"))) -> High | Y6: =IF(OR($B6="",$E6<>"Open"),"",IF($L6="",(INDEX(Lists!$G$2:$G$4,MATCH($X6,Lists!$E$2:$E$4,0))*1000000000000-$U6-$H6),IFERROR(MAX((INDEX(Lists!$G$2:$G$4,MATCH($X6,Lists!$E$2:$E$4,0))*1000000000000-$U6-$H6),INDEX($Y$2:$Y$41,MATCH($L6,$A$2:$A$41,0))+1),(INDEX(Lists!$G$2:$G$4,MATCH($X6,Lists!$E$2:$E$4,0))*1000000000000-$U6-$H6)))) -> 9.9998384e+11 | Z6: =IF($Y6="","",RANK($Y6,$Y$2:$Y$41,1)+COUNTIF($Y$2:$Y6,$Y6)-1) -> 1 | AA6: ="" | AB6: =IF(OR($B6="",1>Parameters!$B$7),"",IF(1<=0,0,IF(ABS((1+$H6)/(1+Parameters!$B$10)-1)<0.000001,1*$G6/(1+Parameters!$B$10),$G6/(1+Parameters!$B$10)*(1-((1+$H6)/(1+Parameters!$B$10))^1)/(1-(1+$H6)/(1+Parameters!$B$10))))+$F6/(1+Parameters!$B$10)^1+IF(1<=0,0,IF(Parameters!$B$10=0,1*$I6*$J6,$I6*$J6*(1-(1/(1+Parameters!$B$10))^1)/Parameters!$B$10))) -> 4213888.9 | AC6: =IF(OR($B6="",2>Parameters!$B$7),"",IF(2<=0,0,IF(ABS((1+$H6)/(1+Parameters!$B$10)-1)<0.000001,2*$G6/(1+Parameters!$B$10),$G6/(1+Parameters!$B$10)*(1-((1+$H6)/(1+Parameters!$B$10))^2)/(1-(1+$H6)/(1+Parameters!$B$10))))+$F6/(1+Parameters!$B$10)^2+IF(2<=0,0,IF(Parameters!$B$10=0,2*$I6*$J6,$I6*$J6*(1-(1/(1+Parameters!$B$10))^2)/Parameters!$B$10))) -> 8278532.2 | AD6: =IF(OR($B6="",3>Parameters!$B$7),"",IF(3<=0,0,IF(ABS((1+$H6)/(1+Parameters!$B$10)-1)<0.000001,3*$G6/(1+Parameters!$B$10),$G6/(1+Parameters!$B$10)*(1-((1+$H6)/(1+Parameters!$B$10))^3)/(1-(1+$H6)/(1+Parameters!$B$10))))+$F6/(1+Parameters!$B$10)^3+IF(3<=0,0,IF(Parameters!$B$10=0,3*$I6*$J6,$I6*$J6*(1-(1/(1+Parameters!$B$10))^3)/Parameters!$B$10))) -> 12343874 | AE6: =IF(OR($B6="",4>Parameters!$B$7),"",IF(4<=0,0,IF(ABS((1+$H6)/(1+Parameters!$B$10)-1)<0.000001,4*$G6/(1+Parameters!$B$10),$G6/(1+Parameters!$B$10)*(1-((1+$H6)/(1+Parameters!$B$10))^4)/(1-(1+$H6)/(1+Parameters!$B$10))))+$F6/(1+Parameters!$B$10)^4+IF(4<=0,0,IF(Parameters!$B$10=0,4*$I6*$J6,$I6*$J6*(1-(1/(1+Parameters!$B$10))^4)/Parameters!$B$10))) -> 16409863 | AF6: =IF(OR($B6="",5>Parameters!$B$7),"",IF(5<=0,0,IF(ABS((1+$H6)/(1+Parameters!$B$10)-1)<0.000001,5*$G6/(1+Parameters!$B$10),$G6/(1+Parameters!$B$10)*(1-((1+$H6)/(1+Parameters!$B$10))^5)/(1-(1+$H6)/(1+Parameters!$B$10))))+$F6/(1+Parameters!$B$10)^5+IF(5<=0,0,IF(Parameters!$B$10=0,5*$I6*$J6,$I6*$J6*(1-(1/(1+Parameters!$B$10))^5)/Parameters!$B$10))) -> 20476451 | AG6: =IF(OR($B6="",1>Parameters!$B$7),"",$G6*(1+$H6)^(1-1)) -> 4400000 | AH6: =IF(OR($B6="",2>Parameters!$B$7),"",$G6*(1+$H6)^(2-1)) -> 4752000 | AI6: =IF(OR($B6="",3>Parameters!$B$7),"",$G6*(1+$H6)^(3-1)) -> 5132160 | AJ6: =IF(OR($B6="",4>Parameters!$B$7),"",$G6*(1+$H6)^(4-1)) -> 5542732.8 | AK6: =IF(OR($B6="",5>Parameters!$B$7),"",$G6*(1+$H6)^(5-1)) -> 5986151.4
A7: OPS-002 | B7: DR plan never validated | C7: Infrastructure | D7: 4-hour RTO claimed, never tested, last attempt failed | E7: Open | F7: 200000 | G7: 100000 | H7: 0.1 | I7: 0.05 | J7: 8000000 | K7: 90 | M7: =IF($B7="","",$G7+$I7*$J7) -> 500000 | N7: =IF($B7="","",IF(Parameters!$B$7<=0,0,IF(ABS((1+$H7)/(1+Parameters!$B$10)-1)<0.000001,Parameters!$B$7*$G7/(1+Parameters!$B$10),$G7/(1+Parameters!$B$10)*(1-((1+$H7)/(1+Parameters!$B$10))^Parameters!$B$7)/(1-(1+$H7)/(1+Parameters!$B$10))))+IF(Parameters!$B$7<=0,0,IF(Parameters!$B$10=0,Parameters!$B$7*$I7*$J7,$I7*$J7*(1-(1/(1+Parameters!$B$10))^Parameters!$B$7)/Parameters!$B$10))) -> 2077514.2 | O7: =IF(OR($B7="",1>Parameters!$B$7),"",$N7-AB7) -> 1429366.1 | P7: =IF(OR($B7="",2>Parameters!$B$7),"",$N7-AC7) -> 1005840.7 | Q7: =IF(OR($B7="",3>Parameters!$B$7),"",$N7-AD7) -> 604955.43 | R7: =IF(OR($B7="",4>Parameters!$B$7),"",$N7-AE7) -> 224871.49 | S7: =IF(OR($B7="",5>Parameters!$B$7),"",$N7-AF7) -> -136116.64 | T7: =IF($B7="","",IF(MAX($O7:$S7)<0,"Accept",MATCH(MAX($O7:$S7),$O7:$S7,0))) -> 1 | U7: =IF($B7="","",MAX($O7:$S7)) -> 1429366.1 | V7: =IF($B7="","",IF($F7>0,ROUND($O7/$F7,2),IF(N($O7)>0,Lists!$F$2,0))+IF($W7="Yes",Lists!$I$2,0)) -> 7.15 | W7: =IF($B7="","",IF(COUNTIFS($L$2:$L$41,$A7,$E$2:$E$41,"Open",$A$2:$A$41,"<>"&$A7)>0,"Yes","No")) -> No | X7: =IF($B7="","",IF($V7>=Lists!$F$2,"High",IF($V7>=Lists!$F$3,"Medium","Low"))) -> High | Y7: =IF(OR($B7="",$E7<>"Open"),"",IF($L7="",(INDEX(Lists!$G$2:$G$4,MATCH($X7,Lists!$E$2:$E$4,0))*1000000000000-$U7-$H7),IFERROR(MAX((INDEX(Lists!$G$2:$G$4,MATCH($X7,Lists!$E$2:$E$4,0))*1000000000000-$U7-$H7),INDEX($Y$2:$Y$41,MATCH($L7,$A$2:$A$41,0))+1),(INDEX(Lists!$G$2:$G$4,MATCH($X7,Lists!$E$2:$E$4,0))*1000000000000-$U7-$H7)))) -> 9.9999857e+11 | Z7: =IF($Y7="","",RANK($Y7,$Y$2:$Y$41,1)+COUNTIF($Y$2:$Y7,$Y7)-1) -> 5 | AA7: ="" | AB7: =IF(OR($B7="",1>Parameters!$B$7),"",IF(1<=0,0,IF(ABS((1+$H7)/(1+Parameters!$B$10)-1)<0.000001,1*$G7/(1+Parameters!$B$10),$G7/(1+Parameters!$B$10)*(1-((1+$H7)/(1+Parameters!$B$10))^1)/(1-(1+$H7)/(1+Parameters!$B$10))))+$F7/(1+Parameters!$B$10)^1+IF(1<=0,0,IF(Parameters!$B$10=0,1*$I7*$J7,$I7*$J7*(1-(1/(1+Parameters!$B$10))^1)/Parameters!$B$10))) -> 648148.15 | AC7: =IF(OR($B7="",2>Parameters!$B$7),"",IF(2<=0,0,IF(ABS((1+$H7)/(1+Parameters!$B$10)-1)<0.000001,2*$G7/(1+Parameters!$B$10),$G7/(1+Parameters!$B$10)*(1-((1+$H7)/(1+Parameters!$B$10))^2)/(1-(1+$H7)/(1+Parameters!$B$10))))+$F7/(1+Parameters!$B$10)^2+IF(2<=0,0,IF(Parameters!$B$10=0,2*$I7*$J7,$I7*$J7*(1-(1/(1+Parameters!$B$10))^2)/Parameters!$B$10))) -> 1071673.5 | AD7: =IF(OR($B7="",3>Parameters!$B$7),"",IF(3<=0,0,IF(ABS((1+$H7)/(1+Parameters!$B$10)-1)<0.000001,3*$G7/(1+Parameters!$B$10),$G7/(1+Parameters!$B$10)*(1-((1+$H7)/(1+Parameters!$B$10))^3)/(1-(1+$H7)/(1+Parameters!$B$10))))+$F7/(1+Parameters!$B$10)^3+IF(3<=0,0,IF(Parameters!$B$10=0,3*$I7*$J7,$I7*$J7*(1-(1/(1+Parameters!$B$10))^3)/Parameters!$B$10))) -> 1472558.8 | AE7: =IF(OR($B7="",4>Parameters!$B$7),"",IF(4<=0,0,IF(ABS((1+$H7)/(1+Parameters!$B$10)-1)<0.000001,4*$G7/(1+Parameters!$B$10),$G7/(1+Parameters!$B$10)*(1-((1+$H7)/(1+Parameters!$B$10))^4)/(1-(1+$H7)/(1+Parameters!$B$10))))+$F7/(1+Parameters!$B$10)^4+IF(4<=0,0,IF(Parameters!$B$10=0,4*$I7*$J7,$I7*$J7*(1-(1/(1+Parameters!$B$10))^4)/Parameters!$B$10))) -> 1852642.7 | AF7: =IF(OR($B7="",5>Parameters!$B$7),"",IF(5<=0,0,IF(ABS((1+$H7)/(1+Parameters!$B$10)-1)<0.000001,5*$G7/(1+Parameters!$B$10),$G7/(1+Parameters!$B$10)*(1-((1+$H7)/(1+Parameters!$B$10))^5)/(1-(1+$H7)/(1+Parameters!$B$10))))+$F7/(1+Parameters!$B$10)^5+IF(5<=0,0,IF(Parameters!$B$10=0,5*$I7*$J7,$I7*$J7*(1-(1/(1+Parameters!$B$10))^5)/Parameters!$B$10))) -> 2213630.9 | AG7: =IF(OR($B7="",1>Parameters!$B$7),"",$G7*(1+$H7)^(1-1)) -> 100000 | AH7: =IF(OR($B7="",2>Parameters!$B$7),"",$G7*(1+$H7)^(2-1)) -> 110000 | AI7: =IF(OR($B7="",3>Parameters!$B$7),"",$G7*(1+$H7)^(3-1)) -> 121000 | AJ7: =IF(OR($B7="",4>Parameters!$B$7),"",$G7*(1+$H7)^(4-1)) -> 133100 | AK7: =IF(OR($B7="",5>Parameters!$B$7),"",$G7*(1+$H7)^(5-1)) -> 146410
A8: DATA-001 | B8: Customer churn calculation bug | C8: Data | D8: Understates churn 1.5pp for 18 months, board reporting issue | E8: Open | F8: 75000 | G8: 50000 | H8: 0.05 | I8: 0.02 | J8: 500000 | K8: 30 | M8: =IF($B8="","",$G8+$I8*$J8) -> 60000 | N8: =IF($B8="","",IF(Parameters!$B$7<=0,0,IF(ABS((1+$H8)/(1+Parameters!$B$10)-1)<0.000001,Parameters!$B$7*$G8/(1+Parameters!$B$10),$G8/(1+Parameters!$B$10)*(1-((1+$H8)/(1+Parameters!$B$10))^Parameters!$B$7)/(1-(1+$H8)/(1+Parameters!$B$10))))+IF(Parameters!$B$7<=0,0,IF(Parameters!$B$10=0,Parameters!$B$7*$I8*$J8,$I8*$J8*(1-(1/(1+Parameters!$B$10))^Parameters!$B$7)/Parameters!$B$10))) -> 258900.79 | O8: =IF(OR($B8="",1>Parameters!$B$7),"",$N8-AB8) -> 133900.79 | P8: =IF(OR($B8="",2>Parameters!$B$7),"",$N8-AC8) -> 85461.147 | Q8: =IF(OR($B8="",3>Parameters!$B$7),"",$N8-AD8) -> 38525.816 | R8: =IF(OR($B8="",4>Parameters!$B$7),"",$N8-AE8) -> -6958.7505 | S8: =IF(OR($B8="",5>Parameters!$B$7),"",$N8-AF8) -> -51043.74 | T8: =IF($B8="","",IF(MAX($O8:$S8)<0,"Accept",MATCH(MAX($O8:$S8),$O8:$S8,0))) -> 1 | U8: =IF($B8="","",MAX($O8:$S8)) -> 133900.79 | V8: =IF($B8="","",IF($F8>0,ROUND($O8/$F8,2),IF(N($O8)>0,Lists!$F$2,0))+IF($W8="Yes",Lists!$I$2,0)) -> 1.79 | W8: =IF($B8="","",IF(COUNTIFS($L$2:$L$41,$A8,$E$2:$E$41,"Open",$A$2:$A$41,"<>"&$A8)>0,"Yes","No")) -> No | X8: =IF($B8="","",IF($V8>=Lists!$F$2,"High",IF($V8>=Lists!$F$3,"Medium","Low"))) -> Medium | Y8: =IF(OR($B8="",$E8<>"Open"),"",IF($L8="",(INDEX(Lists!$G$2:$G$4,MATCH($X8,Lists!$E$2:$E$4,0))*1000000000000-$U8-$H8),IFERROR(MAX((INDEX(Lists!$G$2:$G$4,MATCH($X8,Lists!$E$2:$E$4,0))*1000000000000-$U8-$H8),INDEX($Y$2:$Y$41,MATCH($L8,$A$2:$A$41,0))+1),(INDEX(Lists!$G$2:$G$4,MATCH($X8,Lists!$E$2:$E$4,0))*1000000000000-$U8-$H8)))) -> 1.9999999e+12 | Z8: =IF($Y8="","",RANK($Y8,$Y$2:$Y$41,1)+COUNTIF($Y$2:$Y8,$Y8)-1) -> 10 | AA8: ="" | AB8: =IF(OR($B8="",1>Parameters!$B$7),"",IF(1<=0,0,IF(ABS((1+$H8)/(1+Parameters!$B$10)-1)<0.000001,1*$G8/(1+Parameters!$B$10),$G8/(1+Parameters!$B$10)*(1-((1+$H8)/(1+Parameters!$B$10))^1)/(1-(1+$H8)/(1+Parameters!$B$10))))+$F8/(1+Parameters!$B$10)^1+IF(1<=0,0,IF(Parameters!$B$10=0,1*$I8*$J8,$I8*$J8*(1-(1/(1+Parameters!$B$10))^1)/Parameters!$B$10))) -> 125000 | AC8: =IF(OR($B8="",2>Parameters!$B$7),"",IF(2<=0,0,IF(ABS((1+$H8)/(1+Parameters!$B$10)-1)<0.000001,2*$G8/(1+Parameters!$B$10),$G8/(1+Parameters!$B$10)*(1-((1+$H8)/(1+Parameters!$B$10))^2)/(1-(1+$H8)/(1+Parameters!$B$10))))+$F8/(1+Parameters!$B$10)^2+IF(2<=0,0,IF(Parameters!$B$10=0,2*$I8*$J8,$I8*$J8*(1-(1/(1+Parameters!$B$10))^2)/Parameters!$B$10))) -> 173439.64 | AD8: =IF(OR($B8="",3>Parameters!$B$7),"",IF(3<=0,0,IF(ABS((1+$H8)/(1+Parameters!$B$10)-1)<0.000001,3*$G8/(1+Parameters!$B$10),$G8/(1+Parameters!$B$10)*(1-((1+$H8)/(1+Parameters!$B$10))^3)/(1-(1+$H8)/(1+Parameters!$B$10))))+$F8/(1+Parameters!$B$10)^3+IF(3<=0,0,IF(Parameters!$B$10=0,3*$I8*$J8,$I8*$J8*(1-(1/(1+Parameters!$B$10))^3)/Parameters!$B$10))) -> 220374.97 | AE8: =IF(OR($B8="",4>Parameters!$B$7),"",IF(4<=0,0,IF(ABS((1+$H8)/(1+Parameters!$B$10)-1)<0.000001,4*$G8/(1+Parameters!$B$10),$G8/(1+Parameters!$B$10)*(1-((1+$H8)/(1+Parameters!$B$10))^4)/(1-(1+$H8)/(1+Parameters!$B$10))))+$F8/(1+Parameters!$B$10)^4+IF(4<=0,0,IF(Parameters!$B$10=0,4*$I8*$J8,$I8*$J8*(1-(1/(1+Parameters!$B$10))^4)/Parameters!$B$10))) -> 265859.54 | AF8: =IF(OR($B8="",5>Parameters!$B$7),"",IF(5<=0,0,IF(ABS((1+$H8)/(1+Parameters!$B$10)-1)<0.000001,5*$G8/(1+Parameters!$B$10),$G8/(1+Parameters!$B$10)*(1-((1+$H8)/(1+Parameters!$B$10))^5)/(1-(1+$H8)/(1+Parameters!$B$10))))+$F8/(1+Parameters!$B$10)^5+IF(5<=0,0,IF(Parameters!$B$10=0,5*$I8*$J8,$I8*$J8*(1-(1/(1+Parameters!$B$10))^5)/Parameters!$B$10))) -> 309944.53 | AG8: =IF(OR($B8="",1>Parameters!$B$7),"",$G8*(1+$H8)^(1-1)) -> 50000 | AH8: =IF(OR($B8="",2>Parameters!$B$7),"",$G8*(1+$H8)^(2-1)) -> 52500 | AI8: =IF(OR($B8="",3>Parameters!$B$7),"",$G8*(1+$H8)^(3-1)) -> 55125 | AJ8: =IF(OR($B8="",4>Parameters!$B$7),"",$G8*(1+$H8)^(4-1)) -> 57881.25 | AK8: =IF(OR($B8="",5>Parameters!$B$7),"",$G8*(1+$H8)^(5-1)) -> 60775.312
A9: DATA-002 | B9: Three different MAU definitions across teams | C9: Data | D9: 8% variance on quarterly board metrics | E9: Open | F9: 120000 | G9: 80000 | H9: 0.05 | I9: 0.01 | J9: 200000 | K9: 60 | M9: =IF($B9="","",$G9+$I9*$J9) -> 82000 | N9: =IF($B9="","",IF(Parameters!$B$7<=0,0,IF(ABS((1+$H9)/(1+Parameters!$B$10)-1)<0.000001,Parameters!$B$7*$G9/(1+Parameters!$B$10),$G9/(1+Parameters!$B$10)*(1-((1+$H9)/(1+Parameters!$B$10))^Parameters!$B$7)/(1-(1+$H9)/(1+Parameters!$B$10))))+IF(Parameters!$B$7<=0,0,IF(Parameters!$B$10=0,Parameters!$B$7*$I9*$J9,$I9*$J9*(1-(1/(1+Parameters!$B$10))^Parameters!$B$7)/Parameters!$B$10))) -> 358343.32 | O9: =IF(OR($B9="",1>Parameters!$B$7),"",$N9-AB9) -> 171306.29 | P9: =IF(OR($B9="",2>Parameters!$B$7),"",$N9-AC9) -> 105805.6 | Q9: =IF(OR($B9="",3>Parameters!$B$7),"",$N9-AD9) -> 41822.722 | R9: =IF(OR($B9="",4>Parameters!$B$7),"",$N9-AE9) -> -20662.166 | S9: =IF(OR($B9="",5>Parameters!$B$7),"",$N9-AF9) -> -81669.984 | T9: =IF($B9="","",IF(MAX($O9:$S9)<0,"Accept",MATCH(MAX($O9:$S9),$O9:$S9,0))) -> 1 | U9: =IF($B9="","",MAX($O9:$S9)) -> 171306.29 | V9: =IF($B9="","",IF($F9>0,ROUND($O9/$F9,2),IF(N($O9)>0,Lists!$F$2,0))+IF($W9="Yes",Lists!$I$2,0)) -> 1.43 | W9: =IF($B9="","",IF(COUNTIFS($L$2:$L$41,$A9,$E$2:$E$41,"Open",$A$2:$A$41,"<>"&$A9)>0,"Yes","No")) -> No | X9: =IF($B9="","",IF($V9>=Lists!$F$2,"High",IF($V9>=Lists!$F$3,"Medium","Low"))) -> Medium | Y9: =IF(OR($B9="",$E9<>"Open"),"",IF($L9="",(INDEX(Lists!$G$2:$G$4,MATCH($X9,Lists!$E$2:$E$4,0))*1000000000000-$U9-$H9),IFERROR(MAX((INDEX(Lists!$G$2:$G$4,MATCH($X9,Lists!$E$2:$E$4,0))*1000000000000-$U9-$H9),INDEX($Y$2:$Y$41,MATCH($L9,$A$2:$A$41,0))+1),(INDEX(Lists!$G$2:$G$4,MATCH($X9,Lists!$E$2:$E$4,0))*1000000000000-$U9-$H9)))) -> 1.9999998e+12 | Z9: =IF($Y9="","",RANK($Y9,$Y$2:$Y$41,1)+COUNTIF($Y$2:$Y9,$Y9)-1) -> 9 | AA9: ="" | AB9: =IF(OR($B9="",1>Parameters!$B$7),"",IF(1<=0,0,IF(ABS((1+$H9)/(1+Parameters!$B$10)-1)<0.000001,1*$G9/(1+Parameters!$B$10),$G9/(1+Parameters!$B$10)*(1-((1+$H9)/(1+Parameters!$B$10))^1)/(1-(1+$H9)/(1+Parameters!$B$10))))+$F9/(1+Parameters!$B$10)^1+IF(1<=0,0,IF(Parameters!$B$10=0,1*$I9*$J9,$I9*$J9*(1-(1/(1+Parameters!$B$10))^1)/Parameters!$B$10))) -> 187037.04 | AC9: =IF(OR($B9="",2>Parameters!$B$7),"",IF(2<=0,0,IF(ABS((1+$H9)/(1+Parameters!$B$10)-1)<0.000001,2*$G9/(1+Parameters!$B$10),$G9/(1+Parameters!$B$10)*(1-((1+$H9)/(1+Parameters!$B$10))^2)/(1-(1+$H9)/(1+Parameters!$B$10))))+$F9/(1+Parameters!$B$10)^2+IF(2<=0,0,IF(Parameters!$B$10=0,2*$I9*$J9,$I9*$J9*(1-(1/(1+Parameters!$B$10))^2)/Parameters!$B$10))) -> 252537.72 | AD9: =IF(OR($B9="",3>Parameters!$B$7),"",IF(3<=0,0,IF(ABS((1+$H9)/(1+Parameters!$B$10)-1)<0.000001,3*$G9/(1+Parameters!$B$10),$G9/(1+Parameters!$B$10)*(1-((1+$H9)/(1+Parameters!$B$10))^3)/(1-(1+$H9)/(1+Parameters!$B$10))))+$F9/(1+Parameters!$B$10)^3+IF(3<=0,0,IF(Parameters!$B$10=0,3*$I9*$J9,$I9*$J9*(1-(1/(1+Parameters!$B$10))^3)/Parameters!$B$10))) -> 316520.6 | AE9: =IF(OR($B9="",4>Parameters!$B$7),"",IF(4<=0,0,IF(ABS((1+$H9)/(1+Parameters!$B$10)-1)<0.000001,4*$G9/(1+Parameters!$B$10),$G9/(1+Parameters!$B$10)*(1-((1+$H9)/(1+Parameters!$B$10))^4)/(1-(1+$H9)/(1+Parameters!$B$10))))+$F9/(1+Parameters!$B$10)^4+IF(4<=0,0,IF(Parameters!$B$10=0,4*$I9*$J9,$I9*$J9*(1-(1/(1+Parameters!$B$10))^4)/Parameters!$B$10))) -> 379005.49 | AF9: =IF(OR($B9="",5>Parameters!$B$7),"",IF(5<=0,0,IF(ABS((1+$H9)/(1+Parameters!$B$10)-1)<0.000001,5*$G9/(1+Parameters!$B$10),$G9/(1+Parameters!$B$10)*(1-((1+$H9)/(1+Parameters!$B$10))^5)/(1-(1+$H9)/(1+Parameters!$B$10))))+$F9/(1+Parameters!$B$10)^5+IF(5<=0,0,IF(Parameters!$B$10=0,5*$I9*$J9,$I9*$J9*(1-(1/(1+Parameters!$B$10))^5)/Parameters!$B$10))) -> 440013.31 | AG9: =IF(OR($B9="",1>Parameters!$B$7),"",$G9*(1+$H9)^(1-1)) -> 80000 | AH9: =IF(OR($B9="",2>Parameters!$B$7),"",$G9*(1+$H9)^(2-1)) -> 84000 | AI9: =IF(OR($B9="",3>Parameters!$B$7),"",$G9*(1+$H9)^(3-1)) -> 88200 | AJ9: =IF(OR($B9="",4>Parameters!$B$7),"",$G9*(1+$H9)^(4-1)) -> 92610 | AK9: =IF(OR($B9="",5>Parameters!$B$7),"",$G9*(1+$H9)^(5-1)) -> 97240.5
A10: ARCH-002 | B10: PostgreSQL 11 EOL - upgrade required | C10: Infrastructure | D10: EOL since 2023, security and support exposure growing fast | E10: Open | F10: 200000 | G10: 50000 | H10: 0.3 | I10: 0.05 | J10: 1500000 | K10: 90 | M10: =IF($B10="","",$G10+$I10*$J10) -> 125000 | N10: =IF($B10="","",IF(Parameters!$B$7<=0,0,IF(ABS((1+$H10)/(1+Parameters!$B$10)-1)<0.000001,Parameters!$B$7*$G10/(1+Parameters!$B$10),$G10/(1+Parameters!$B$10)*(1-((1+$H10)/(1+Parameters!$B$10))^Parameters!$B$7)/(1-(1+$H10)/(1+Parameters!$B$10))))+IF(Parameters!$B$7<=0,0,IF(Parameters!$B$10=0,Parameters!$B$7*$I10*$J10,$I10*$J10*(1-(1/(1+Parameters!$B$10))^Parameters!$B$7)/Parameters!$B$10))) -> 646489.11 | O10: =IF(OR($B10="",1>Parameters!$B$7),"",$N10-AB10) -> 345563.18 | P10: =IF(OR($B10="",2>Parameters!$B$7),"",$N10-AC10) -> 239253.17 | Q10: =IF(OR($B10="",3>Parameters!$B$7),"",$N10-AD10) -> 125338.24 | R10: =IF(OR($B10="",4>Parameters!$B$7),"",$N10-AE10) -> 1228.4527 | S10: =IF(OR($B10="",5>Parameters!$B$7),"",$N10-AF10) -> -136116.64 | T10: =IF($B10="","",IF(MAX($O10:$S10)<0,"Accept",MATCH(MAX($O10:$S10),$O10:$S10,0))) -> 1 | U10: =IF($B10="","",MAX($O10:$S10)) -> 345563.18 | V10: =IF($B10="","",IF($F10>0,ROUND($O10/$F10,2),IF(N($O10)>0,Lists!$F$2,0))+IF($W10="Yes",Lists!$I$2,0)) -> 1.73 | W10: =IF($B10="","",IF(COUNTIFS($L$2:$L$41,$A10,$E$2:$E$41,"Open",$A$2:$A$41,"<>"&$A10)>0,"Yes","No")) -> No | X10: =IF($B10="","",IF($V10>=Lists!$F$2,"High",IF($V10>=Lists!$F$3,"Medium","Low"))) -> Medium | Y10: =IF(OR($B10="",$E10<>"Open"),"",IF($L10="",(INDEX(Lists!$G$2:$G$4,MATCH($X10,Lists!$E$2:$E$4,0))*1000000000000-$U10-$H10),IFERROR(MAX((INDEX(Lists!$G$2:$G$4,MATCH($X10,Lists!$E$2:$E$4,0))*1000000000000-$U10-$H10),INDEX($Y$2:$Y$41,MATCH($L10,$A$2:$A$41,0))+1),(INDEX(Lists!$G$2:$G$4,MATCH($X10,Lists!$E$2:$E$4,0))*1000000000000-$U10-$H10)))) -> 1.9999997e+12 | Z10: =IF($Y10="","",RANK($Y10,$Y$2:$Y$41,1)+COUNTIF($Y$2:$Y10,$Y10)-1) -> 8 | AA10: ="" | AB10: =IF(OR($B10="",1>Parameters!$B$7),"",IF(1<=0,0,IF(ABS((1+$H10)/(1+Parameters!$B$10)-1)<0.000001,1*$G10/(1+Parameters!$B$10),$G10/(1+Parameters!$B$10)*(1-((1+$H10)/(1+Parameters!$B$10))^1)/(1-(1+$H10)/(1+Parameters!$B$10))))+$F10/(1+Parameters!$B$10)^1+IF(1<=0,0,IF(Parameters!$B$10=0,1*$I10*$J10,$I10*$J10*(1-(1/(1+Parameters!$B$10))^1)/Parameters!$B$10))) -> 300925.93 | AC10: =IF(OR($B10="",2>Parameters!$B$7),"",IF(2<=0,0,IF(ABS((1+$H10)/(1+Parameters!$B$10)-1)<0.000001,2*$G10/(1+Parameters!$B$10),$G10/(1+Parameters!$B$10)*(1-((1+$H10)/(1+Parameters!$B$10))^2)/(1-(1+$H10)/(1+Parameters!$B$10))))+$F10/(1+Parameters!$B$10)^2+IF(2<=0,0,IF(Parameters!$B$10=0,2*$I10*$J10,$I10*$J10*(1-(1/(1+Parameters!$B$10))^2)/Parameters!$B$10))) -> 407235.94 | AD10: =IF(OR($B10="",3>Parameters!$B$7),"",IF(3<=0,0,IF(ABS((1+$H10)/(1+Parameters!$B$10)-1)<0.000001,3*$G10/(1+Parameters!$B$10),$G10/(1+Parameters!$B$10)*(1-((1+$H10)/(1+Parameters!$B$10))^3)/(1-(1+$H10)/(1+Parameters!$B$10))))+$F10/(1+Parameters!$B$10)^3+IF(3<=0,0,IF(Parameters!$B$10=0,3*$I10*$J10,$I10*$J10*(1-(1/(1+Parameters!$B$10))^3)/Parameters!$B$10))) -> 521150.87 | AE10: =IF(OR($B10="",4>Parameters!$B$7),"",IF(4<=0,0,IF(ABS((1+$H10)/(1+Parameters!$B$10)-1)<0.000001,4*$G10/(1+Parameters!$B$10),$G10/(1+Parameters!$B$10)*(1-((1+$H10)/(1+Parameters!$B$10))^4)/(1-(1+$H10)/(1+Parameters!$B$10))))+$F10/(1+Parameters!$B$10)^4+IF(4<=0,0,IF(Parameters!$B$10=0,4*$I10*$J10,$I10*$J10*(1-(1/(1+Parameters!$B$10))^4)/Parameters!$B$10))) -> 645260.66 | AF10: =IF(OR($B10="",5>Parameters!$B$7),"",IF(5<=0,0,IF(ABS((1+$H10)/(1+Parameters!$B$10)-1)<0.000001,5*$G10/(1+Parameters!$B$10),$G10/(1+Parameters!$B$10)*(1-((1+$H10)/(1+Parameters!$B$10))^5)/(1-(1+$H10)/(1+Parameters!$B$10))))+$F10/(1+Parameters!$B$10)^5+IF(5<=0,0,IF(Parameters!$B$10=0,5*$I10*$J10,$I10*$J10*(1-(1/(1+Parameters!$B$10))^5)/Parameters!$B$10))) -> 782605.75 | AG10: =IF(OR($B10="",1>Parameters!$B$7),"",$G10*(1+$H10)^(1-1)) -> 50000 | AH10: =IF(OR($B10="",2>Parameters!$B$7),"",$G10*(1+$H10)^(2-1)) -> 65000 | AI10: =IF(OR($B10="",3>Parameters!$B$7),"",$G10*(1+$H10)^(3-1)) -> 84500 | AJ10: =IF(OR($B10="",4>Parameters!$B$7),"",$G10*(1+$H10)^(4-1)) -> 109850 | AK10: =IF(OR($B10="",5>Parameters!$B$7),"",$G10*(1+$H10)^(5-1)) -> 142805
A11: IP-001 | B11: Missing IP assignments for 12 engineers | C11: Process | D11: Pre-close cleanup required, low effort high reward | E11: Open | F11: 50000 | G11: 25000 | H11: 0.05 | I11: 0.1 | J11: 5000000 | K11: 20 | M11: =IF($B11="","",$G11+$I11*$J11) -> 525000 | N11: =IF($B11="","",IF(Parameters!$B$7<=0,0,IF(ABS((1+$H11)/(1+Parameters!$B$10)-1)<0.000001,Parameters!$B$7*$G11/(1+Parameters!$B$10),$G11/(1+Parameters!$B$10)*(1-((1+$H11)/(1+Parameters!$B$10))^Parameters!$B$7)/(1-(1+$H11)/(1+Parameters!$B$10))))+IF(Parameters!$B$7<=0,0,IF(Parameters!$B$10=0,Parameters!$B$7*$I11*$J11,$I11*$J11*(1-(1/(1+Parameters!$B$10))^Parameters!$B$7)/Parameters!$B$10))) -> 2105841.9 | O11: =IF(OR($B11="",1>Parameters!$B$7),"",$N11-AB11) -> 1573434.5 | P11: =IF(OR($B11="",2>Parameters!$B$7),"",$N11-AC11) -> 1125689.3 | Q11: =IF(OR($B11="",3>Parameters!$B$7),"",$N11-AD11) -> 710068.46 | R11: =IF(OR($B11="",4>Parameters!$B$7),"",$N11-AE11) -> 324221.43 | S11: =IF(OR($B11="",5>Parameters!$B$7),"",$N11-AF11) -> -34029.16 | T11: =IF($B11="","",IF(MAX($O11:$S11)<0,"Accept",MATCH(MAX($O11:$S11),$O11:$S11,0))) -> 1 | U11: =IF($B11="","",MAX($O11:$S11)) -> 1573434.5 | V11: =IF($B11="","",IF($F11>0,ROUND($O11/$F11,2),IF(N($O11)>0,Lists!$F$2,0))+IF($W11="Yes",Lists!$I$2,0)) -> 31.47 | W11: =IF($B11="","",IF(COUNTIFS($L$2:$L$41,$A11,$E$2:$E$41,"Open",$A$2:$A$41,"<>"&$A11)>0,"Yes","No")) -> No | X11: =IF($B11="","",IF($V11>=Lists!$F$2,"High",IF($V11>=Lists!$F$3,"Medium","Low"))) -> High | Y11: =IF(OR($B11="",$E11<>"Open"),"",IF($L11="",(INDEX(Lists!$G$2:$G$4,MATCH($X11,Lists!$E$2:$E$4,0))*1000000000000-$U11-$H11),IFERROR(MAX((INDEX(Lists!$G$2:$G$4,MATCH($X11,Lists!$E$2:$E$4,0))*1000000000000-$U11-$H11),INDEX($Y$2:$Y$41,MATCH($L11,$A$2:$A$41,0))+1),(INDEX(Lists!$G$2:$G$4,MATCH($X11,Lists!$E$2:$E$4,0))*1000000000000-$U11-$H11)))) -> 9.9999843e+11 | Z11: =IF($Y11="","",RANK($Y11,$Y$2:$Y$41,1)+COUNTIF($Y$2:$Y11,$Y11)-1) -> 4 | AA11: ="" | AB11: =IF(OR($B11="",1>Parameters!$B$7),"",IF(1<=0,0,IF(ABS((1+$H11)/(1+Parameters!$B$10)-1)<0.000001,1*$G11/(1+Parameters!$B$10),$G11/(1+Parameters!$B$10)*(1-((1+$H11)/(1+Parameters!$B$10))^1)/(1-(1+$H11)/(1+Parameters!$B$10))))+$F11/(1+Parameters!$B$10)^1+IF(1<=0,0,IF(Parameters!$B$10=0,1*$I11*$J11,$I11*$J11*(1-(1/(1+Parameters!$B$10))^1)/Parameters!$B$10))) -> 532407.41 | AC11: =IF(OR($B11="",2>Parameters!$B$7),"",IF(2<=0,0,IF(ABS((1+$H11)/(1+Parameters!$B$10)-1)<0.000001,2*$G11/(1+Parameters!$B$10),$G11/(1+Parameters!$B$10)*(1-((1+$H11)/(1+Parameters!$B$10))^2)/(1-(1+$H11)/(1+Parameters!$B$10))))+$F11/(1+Parameters!$B$10)^2+IF(2<=0,0,IF(Parameters!$B$10=0,2*$I11*$J11,$I11*$J11*(1-(1/(1+Parameters!$B$10))^2)/Parameters!$B$10))) -> 980152.61 | AD11: =IF(OR($B11="",3>Parameters!$B$7),"",IF(3<=0,0,IF(ABS((1+$H11)/(1+Parameters!$B$10)-1)<0.000001,3*$G11/(1+Parameters!$B$10),$G11/(1+Parameters!$B$10)*(1-((1+$H11)/(1+Parameters!$B$10))^3)/(1-(1+$H11)/(1+Parameters!$B$10))))+$F11/(1+Parameters!$B$10)^3+IF(3<=0,0,IF(Parameters!$B$10=0,3*$I11*$J11,$I11*$J11*(1-(1/(1+Parameters!$B$10))^3)/Parameters!$B$10))) -> 1395773.4 | AE11: =IF(OR($B11="",4>Parameters!$B$7),"",IF(4<=0,0,IF(ABS((1+$H11)/(1+Parameters!$B$10)-1)<0.000001,4*$G11/(1+Parameters!$B$10),$G11/(1+Parameters!$B$10)*(1-((1+$H11)/(1+Parameters!$B$10))^4)/(1-(1+$H11)/(1+Parameters!$B$10))))+$F11/(1+Parameters!$B$10)^4+IF(4<=0,0,IF(Parameters!$B$10=0,4*$I11*$J11,$I11*$J11*(1-(1/(1+Parameters!$B$10))^4)/Parameters!$B$10))) -> 1781620.4 | AF11: =IF(OR($B11="",5>Parameters!$B$7),"",IF(5<=0,0,IF(ABS((1+$H11)/(1+Parameters!$B$10)-1)<0.000001,5*$G11/(1+Parameters!$B$10),$G11/(1+Parameters!$B$10)*(1-((1+$H11)/(1+Parameters!$B$10))^5)/(1-(1+$H11)/(1+Parameters!$B$10))))+$F11/(1+Parameters!$B$10)^5+IF(5<=0,0,IF(Parameters!$B$10=0,5*$I11*$J11,$I11*$J11*(1-(1/(1+Parameters!$B$10))^5)/Parameters!$B$10))) -> 2139871 | AG11: =IF(OR($B11="",1>Parameters!$B$7),"",$G11*(1+$H11)^(1-1)) -> 25000 | AH11: =IF(OR($B11="",2>Parameters!$B$7),"",$G11*(1+$H11)^(2-1)) -> 26250 | AI11: =IF(OR($B11="",3>Parameters!$B$7),"",$G11*(1+$H11)^(3-1)) -> 27562.5 | AJ11: =IF(OR($B11="",4>Parameters!$B$7),"",$G11*(1+$H11)^(4-1)) -> 28940.625 | AK11: =IF(OR($B11="",5>Parameters!$B$7),"",$G11*(1+$H11)^(5-1)) -> 30387.656
A12: ARCH-003 | B12: Code modernization to support multi-tenancy | C12: Code | D12: Application code refactoring blocked until multi-tenancy infra exists | E12: Open | F12: 800000 | G12: 150000 | H12: 0.1 | I12: 0.03 | J12: 1000000 | K12: 240 | L12: ARCH-001 | M12: =IF($B12="","",$G12+$I12*$J12) -> 180000 | N12: =IF($B12="","",IF(Parameters!$B$7<=0,0,IF(ABS((1+$H12)/(1+Parameters!$B$10)-1)<0.000001,Parameters!$B$7*$G12/(1+Parameters!$B$10),$G12/(1+Parameters!$B$10)*(1-((1+$H12)/(1+Parameters!$B$10))^Parameters!$B$7)/(1-(1+$H12)/(1+Parameters!$B$10))))+IF(Parameters!$B$7<=0,0,IF(Parameters!$B$10=0,Parameters!$B$7*$I12*$J12,$I12*$J12*(1-(1/(1+Parameters!$B$10))^Parameters!$B$7)/Parameters!$B$10))) -> 840426.64 | O12: =IF(OR($B12="",1>Parameters!$B$7),"",$N12-AB12) -> -66980.771 | P12: =IF(OR($B12="",2>Parameters!$B$7),"",$N12-AC12) -> -179292.16 | Q12: =IF(OR($B12="",3>Parameters!$B$7),"",$N12-AD12) -> -296382.41 | R12: =IF(OR($B12="",4>Parameters!$B$7),"",$N12-AE12) -> -418140.11 | S12: =IF(OR($B12="",5>Parameters!$B$7),"",$N12-AF12) -> -544466.56 | T12: =IF($B12="","",IF(MAX($O12:$S12)<0,"Accept",MATCH(MAX($O12:$S12),$O12:$S12,0))) -> Accept | U12: =IF($B12="","",MAX($O12:$S12)) -> -66980.771 | V12: =IF($B12="","",IF($F12>0,ROUND($O12/$F12,2),IF(N($O12)>0,Lists!$F$2,0))+IF($W12="Yes",Lists!$I$2,0)) -> -0.08 | W12: =IF($B12="","",IF(COUNTIFS($L$2:$L$41,$A12,$E$2:$E$41,"Open",$A$2:$A$41,"<>"&$A12)>0,"Yes","No")) -> No | X12: =IF($B12="","",IF($V12>=Lists!$F$2,"High",IF($V12>=Lists!$F$3,"Medium","Low"))) -> Low | Y12: =IF(OR($B12="",$E12<>"Open"),"",IF($L12="",(INDEX(Lists!$G$2:$G$4,MATCH($X12,Lists!$E$2:$E$4,0))*1000000000000-$U12-$H12),IFERROR(MAX((INDEX(Lists!$G$2:$G$4,MATCH($X12,Lists!$E$2:$E$4,0))*1000000000000-$U12-$H12),INDEX($Y$2:$Y$41,MATCH($L12,$A$2:$A$41,0))+1),(INDEX(Lists!$G$2:$G$4,MATCH($X12,Lists!$E$2:$E$4,0))*1000000000000-$U12-$H12)))) -> 3.0000001e+12 | Z12: =IF($Y12="","",RANK($Y12,$Y$2:$Y$41,1)+COUNTIF($Y$2:$Y12,$Y12)-1) -> 12 | AA12: ="" | AB12: =IF(OR($B12="",1>Parameters!$B$7),"",IF(1<=0,0,IF(ABS((1+$H12)/(1+Parameters!$B$10)-1)<0.000001,1*$G12/(1+Parameters!$B$10),$G12/(1+Parameters!$B$10)*(1-((1+$H12)/(1+Parameters!$B$10))^1)/(1-(1+$H12)/(1+Parameters!$B$10))))+$F12/(1+Parameters!$B$10)^1+IF(1<=0,0,IF(Parameters!$B$10=0,1*$I12*$J12,$I12*$J12*(1-(1/(1+Parameters!$B$10))^1)/Parameters!$B$10))) -> 907407.41 | AC12: =IF(OR($B12="",2>Parameters!$B$7),"",IF(2<=0,0,IF(ABS((1+$H12)/(1+Parameters!$B$10)-1)<0.000001,2*$G12/(1+Parameters!$B$10),$G12/(1+Parameters!$B$10)*(1-((1+$H12)/(1+Parameters!$B$10))^2)/(1-(1+$H12)/(1+Parameters!$B$10))))+$F12/(1+Parameters!$B$10)^2+IF(2<=0,0,IF(Parameters!$B$10=0,2*$I12*$J12,$I12*$J12*(1-(1/(1+Parameters!$B$10))^2)/Parameters!$B$10))) -> 1019718.8 | AD12: =IF(OR($B12="",3>Parameters!$B$7),"",IF(3<=0,0,IF(ABS((1+$H12)/(1+Parameters!$B$10)-1)<0.000001,3*$G12/(1+Parameters!$B$10),$G12/(1+Parameters!$B$10)*(1-((1+$H12)/(1+Parameters!$B$10))^3)/(1-(1+$H12)/(1+Parameters!$B$10))))+$F12/(1+Parameters!$B$10)^3+IF(3<=0,0,IF(Parameters!$B$10=0,3*$I12*$J12,$I12*$J12*(1-(1/(1+Parameters!$B$10))^3)/Parameters!$B$10))) -> 1136809 | AE12: =IF(OR($B12="",4>Parameters!$B$7),"",IF(4<=0,0,IF(ABS((1+$H12)/(1+Parameters!$B$10)-1)<0.000001,4*$G12/(1+Parameters!$B$10),$G12/(1+Parameters!$B$10)*(1-((1+$H12)/(1+Parameters!$B$10))^4)/(1-(1+$H12)/(1+Parameters!$B$10))))+$F12/(1+Parameters!$B$10)^4+IF(4<=0,0,IF(Parameters!$B$10=0,4*$I12*$J12,$I12*$J12*(1-(1/(1+Parameters!$B$10))^4)/Parameters!$B$10))) -> 1258566.7 | AF12: =IF(OR($B12="",5>Parameters!$B$7),"",IF(5<=0,0,IF(ABS((1+$H12)/(1+Parameters!$B$10)-1)<0.000001,5*$G12/(1+Parameters!$B$10),$G12/(1+Parameters!$B$10)*(1-((1+$H12)/(1+Parameters!$B$10))^5)/(1-(1+$H12)/(1+Parameters!$B$10))))+$F12/(1+Parameters!$B$10)^5+IF(5<=0,0,IF(Parameters!$B$10=0,5*$I12*$J12,$I12*$J12*(1-(1/(1+Parameters!$B$10))^5)/Parameters!$B$10))) -> 1384893.2 | AG12: =IF(OR($B12="",1>Parameters!$B$7),"",$G12*(1+$H12)^(1-1)) -> 150000 | AH12: =IF(OR($B12="",2>Parameters!$B$7),"",$G12*(1+$H12)^(2-1)) -> 165000 | AI12: =IF(OR($B12="",3>Parameters!$B$7),"",$G12*(1+$H12)^(3-1)) -> 181500 | AJ12: =IF(OR($B12="",4>Parameters!$B$7),"",$G12*(1+$H12)^(4-1)) -> 199650 | AK12: =IF(OR($B12="",5>Parameters!$B$7),"",$G12*(1+$H12)^(5-1)) -> 219615
A13: PROCESS-001 | B13: No DORA metrics tracking | C13: Process | D13: No visibility into engineering velocity, blocks capacity planning | E13: Open | F13: 60000 | G13: 30000 | H13: 0.05 | I13: 0.02 | J13: 200000 | K13: 30 | M13: =IF($B13="","",$G13+$I13*$J13) -> 34000 | N13: =IF($B13="","",IF(Parameters!$B$7<=0,0,IF(ABS((1+$H13)/(1+Parameters!$B$10)-1)<0.000001,Parameters!$B$7*$G13/(1+Parameters!$B$10),$G13/(1+Parameters!$B$10)*(1-((1+$H13)/(1+Parameters!$B$10))^Parameters!$B$7)/(1-(1+$H13)/(1+Parameters!$B$10))))+IF(Parameters!$B$7<=0,0,IF(Parameters!$B$10=0,Parameters!$B$7*$I13*$J13,$I13*$J13*(1-(1/(1+Parameters!$B$10))^Parameters!$B$7)/Parameters!$B$10))) -> 147355.05 | O13: =IF(OR($B13="",1>Parameters!$B$7),"",$N13-AB13) -> 60318.017 | P13: =IF(OR($B13="",2>Parameters!$B$7),"",$N13-AC13) -> 33997.715 | Q13: =IF(OR($B13="",3>Parameters!$B$7),"",$N13-AD13) -> 8376.7796 | R13: =IF(OR($B13="",4>Parameters!$B$7),"",$N13-AE13) -> -16561.864 | S13: =IF(OR($B13="",5>Parameters!$B$7),"",$N13-AF13) -> -40834.992 | T13: =IF($B13="","",IF(MAX($O13:$S13)<0,"Accept",MATCH(MAX($O13:$S13),$O13:$S13,0))) -> 1 | U13: =IF($B13="","",MAX($O13:$S13)) -> 60318.017 | V13: =IF($B13="","",IF($F13>0,ROUND($O13/$F13,2),IF(N($O13)>0,Lists!$F$2,0))+IF($W13="Yes",Lists!$I$2,0)) -> 1.01 | W13: =IF($B13="","",IF(COUNTIFS($L$2:$L$41,$A13,$E$2:$E$41,"Open",$A$2:$A$41,"<>"&$A13)>0,"Yes","No")) -> No | X13: =IF($B13="","",IF($V13>=Lists!$F$2,"High",IF($V13>=Lists!$F$3,"Medium","Low"))) -> Medium | Y13: =IF(OR($B13="",$E13<>"Open"),"",IF($L13="",(INDEX(Lists!$G$2:$G$4,MATCH($X13,Lists!$E$2:$E$4,0))*1000000000000-$U13-$H13),IFERROR(MAX((INDEX(Lists!$G$2:$G$4,MATCH($X13,Lists!$E$2:$E$4,0))*1000000000000-$U13-$H13),INDEX($Y$2:$Y$41,MATCH($L13,$A$2:$A$41,0))+1),(INDEX(Lists!$G$2:$G$4,MATCH($X13,Lists!$E$2:$E$4,0))*1000000000000-$U13-$H13)))) -> 1.9999999e+12 | Z13: =IF($Y13="","",RANK($Y13,$Y$2:$Y$41,1)+COUNTIF($Y$2:$Y13,$Y13)-1) -> 11 | AA13: ="" | AB13: =IF(OR($B13="",1>Parameters!$B$7),"",IF(1<=0,0,IF(ABS((1+$H13)/(1+Parameters!$B$10)-1)<0.000001,1*$G13/(1+Parameters!$B$10),$G13/(1+Parameters!$B$10)*(1-((1+$H13)/(1+Parameters!$B$10))^1)/(1-(1+$H13)/(1+Parameters!$B$10))))+$F13/(1+Parameters!$B$10)^1+IF(1<=0,0,IF(Parameters!$B$10=0,1*$I13*$J13,$I13*$J13*(1-(1/(1+Parameters!$B$10))^1)/Parameters!$B$10))) -> 87037.037 | AC13: =IF(OR($B13="",2>Parameters!$B$7),"",IF(2<=0,0,IF(ABS((1+$H13)/(1+Parameters!$B$10)-1)<0.000001,2*$G13/(1+Parameters!$B$10),$G13/(1+Parameters!$B$10)*(1-((1+$H13)/(1+Parameters!$B$10))^2)/(1-(1+$H13)/(1+Parameters!$B$10))))+$F13/(1+Parameters!$B$10)^2+IF(2<=0,0,IF(Parameters!$B$10=0,2*$I13*$J13,$I13*$J13*(1-(1/(1+Parameters!$B$10))^2)/Parameters!$B$10))) -> 113357.34 | AD13: =IF(OR($B13="",3>Parameters!$B$7),"",IF(3<=0,0,IF(ABS((1+$H13)/(1+Parameters!$B$10)-1)<0.000001,3*$G13/(1+Parameters!$B$10),$G13/(1+Parameters!$B$10)*(1-((1+$H13)/(1+Parameters!$B$10))^3)/(1-(1+$H13)/(1+Parameters!$B$10))))+$F13/(1+Parameters!$B$10)^3+IF(3<=0,0,IF(Parameters!$B$10=0,3*$I13*$J13,$I13*$J13*(1-(1/(1+Parameters!$B$10))^3)/Parameters!$B$10))) -> 138978.27 | AE13: =IF(OR($B13="",4>Parameters!$B$7),"",IF(4<=0,0,IF(ABS((1+$H13)/(1+Parameters!$B$10)-1)<0.000001,4*$G13/(1+Parameters!$B$10),$G13/(1+Parameters!$B$10)*(1-((1+$H13)/(1+Parameters!$B$10))^4)/(1-(1+$H13)/(1+Parameters!$B$10))))+$F13/(1+Parameters!$B$10)^4+IF(4<=0,0,IF(Parameters!$B$10=0,4*$I13*$J13,$I13*$J13*(1-(1/(1+Parameters!$B$10))^4)/Parameters!$B$10))) -> 163916.92 | AF13: =IF(OR($B13="",5>Parameters!$B$7),"",IF(5<=0,0,IF(ABS((1+$H13)/(1+Parameters!$B$10)-1)<0.000001,5*$G13/(1+Parameters!$B$10),$G13/(1+Parameters!$B$10)*(1-((1+$H13)/(1+Parameters!$B$10))^5)/(1-(1+$H13)/(1+Parameters!$B$10))))+$F13/(1+Parameters!$B$10)^5+IF(5<=0,0,IF(Parameters!$B$10=0,5*$I13*$J13,$I13*$J13*(1-(1/(1+Parameters!$B$10))^5)/Parameters!$B$10))) -> 188190.05 | AG13: =IF(OR($B13="",1>Parameters!$B$7),"",$G13*(1+$H13)^(1-1)) -> 30000 | AH13: =IF(OR($B13="",2>Parameters!$B$7),"",$G13*(1+$H13)^(2-1)) -> 31500 | AI13: =IF(OR($B13="",3>Parameters!$B$7),"",$G13*(1+$H13)^(3-1)) -> 33075 | AJ13: =IF(OR($B13="",4>Parameters!$B$7),"",$G13*(1+$H13)^(4-1)) -> 34728.75 | AK13: =IF(OR($B13="",5>Parameters!$B$7),"",$G13*(1+$H13)^(5-1)) -> 36465.188
M14: =IF($B14="","",$G14+$I14*$J14) | N14: =IF($B14="","",IF(Parameters!$B$7<=0,0,IF(ABS((1+$H14)/(1+Parameters!$B$10)-1)<0.000001,Parameters!$B$7*$G14/(1+Parameters!$B$10),$G14/(1+Parameters!$B$10)*(1-((1+$H14)/(1+Parameters!$B$10))^Parameters!$B$7)/(1-(1+$H14)/(1+Parameters!$B$10))))+IF(Parameters!$B$7<=0,0,IF(Parameters!$B$10=0,Parameters!$B$7*$I14*$J14,$I14*$J14*(1-(1/(1+Parameters!$B$10))^Parameters!$B$7)/Parameters!$B$10))) | O14: =IF(OR($B14="",1>Parameters!$B$7),"",$N14-AB14) | P14: =IF(OR($B14="",2>Parameters!$B$7),"",$N14-AC14) | Q14: =IF(OR($B14="",3>Parameters!$B$7),"",$N14-AD14) | R14: =IF(OR($B14="",4>Parameters!$B$7),"",$N14-AE14) | S14: =IF(OR($B14="",5>Parameters!$B$7),"",$N14-AF14) | T14: =IF($B14="","",IF(MAX($O14:$S14)<0,"Accept",MATCH(MAX($O14:$S14),$O14:$S14,0))) | U14: =IF($B14="","",MAX($O14:$S14)) | V14: =IF($B14="","",IF($F14>0,ROUND($O14/$F14,2),IF(N($O14)>0,Lists!$F$2,0))+IF($W14="Yes",Lists!$I$2,0)) | W14: =IF($B14="","",IF(COUNTIFS($L$2:$L$41,$A14,$E$2:$E$41,"Open",$A$2:$A$41,"<>"&$A14)>0,"Yes","No")) | X14: =IF($B14="","",IF($V14>=Lists!$F$2,"High",IF($V14>=Lists!$F$3,"Medium","Low"))) | Y14: =IF(OR($B14="",$E14<>"Open"),"",IF($L14="",(INDEX(Lists!$G$2:$G$4,MATCH($X14,Lists!$E$2:$E$4,0))*1000000000000-$U14-$H14),IFERROR(MAX((INDEX(Lists!$G$2:$G$4,MATCH($X14,Lists!$E$2:$E$4,0))*1000000000000-$U14-$H14),INDEX($Y$2:$Y$41,MATCH($L14,$A$2:$A$41,0))+1),(INDEX(Lists!$G$2:$G$4,MATCH($X14,Lists!$E$2:$E$4,0))*1000000000000-$U14-$H14)))) | Z14: =IF($Y14="","",RANK($Y14,$Y$2:$Y$41,1)+COUNTIF($Y$2:$Y14,$Y14)-1) | AA14: ="" | AB14: =IF(OR($B14="",1>Parameters!$B$7),"",IF(1<=0,0,IF(ABS((1+$H14)/(1+Parameters!$B$10)-1)<0.000001,1*$G14/(1+Parameters!$B$10),$G14/(1+Parameters!$B$10)*(1-((1+$H14)/(1+Parameters!$B$10))^1)/(1-(1+$H14)/(1+Parameters!$B$10))))+$F14/(1+Parameters!$B$10)^1+IF(1<=0,0,IF(Parameters!$B$10=0,1*$I14*$J14,$I14*$J14*(1-(1/(1+Parameters!$B$10))^1)/Parameters!$B$10))) | AC14: =IF(OR($B14="",2>Parameters!$B$7),"",IF(2<=0,0,IF(ABS((1+$H14)/(1+Parameters!$B$10)-1)<0.000001,2*$G14/(1+Parameters!$B$10),$G14/(1+Parameters!$B$10)*(1-((1+$H14)/(1+Parameters!$B$10))^2)/(1-(1+$H14)/(1+Parameters!$B$10))))+$F14/(1+Parameters!$B$10)^2+IF(2<=0,0,IF(Parameters!$B$10=0,2*$I14*$J14,$I14*$J14*(1-(1/(1+Parameters!$B$10))^2)/Parameters!$B$10))) | AD14: =IF(OR($B14="",3>Parameters!$B$7),"",IF(3<=0,0,IF(ABS((1+$H14)/(1+Parameters!$B$10)-1)<0.000001,3*$G14/(1+Parameters!$B$10),$G14/(1+Parameters!$B$10)*(1-((1+$H14)/(1+Parameters!$B$10))^3)/(1-(1+$H14)/(1+Parameters!$B$10))))+$F14/(1+Parameters!$B$10)^3+IF(3<=0,0,IF(Parameters!$B$10=0,3*$I14*$J14,$I14*$J14*(1-(1/(1+Parameters!$B$10))^3)/Parameters!$B$10))) | AE14: =IF(OR($B14="",4>Parameters!$B$7),"",IF(4<=0,0,IF(ABS((1+$H14)/(1+Parameters!$B$10)-1)<0.000001,4*$G14/(1+Parameters!$B$10),$G14/(1+Parameters!$B$10)*(1-((1+$H14)/(1+Parameters!$B$10))^4)/(1-(1+$H14)/(1+Parameters!$B$10))))+$F14/(1+Parameters!$B$10)^4+IF(4<=0,0,IF(Parameters!$B$10=0,4*$I14*$J14,$I14*$J14*(1-(1/(1+Parameters!$B$10))^4)/Parameters!$B$10))) | AF14: =IF(OR($B14="",5>Parameters!$B$7),"",IF(5<=0,0,IF(ABS((1+$H14)/(1+Parameters!$B$10)-1)<0.000001,5*$G14/(1+Parameters!$B$10),$G14/(1+Parameters!$B$10)*(1-((1+$H14)/(1+Parameters!$B$10))^5)/(1-(1+$H14)/(1+Parameters!$B$10))))+$F14/(1+Parameters!$B$10)^5+IF(5<=0,0,IF(Parameters!$B$10=0,5*$I14*$J14,$I14*$J14*(1-(1/(1+Parameters!$B$10))^5)/Parameters!$B$10))) | AG14: =IF(OR($B14="",1>Parameters!$B$7),"",$G14*(1+$H14)^(1-1)) | AH14: =IF(OR($B14="",2>Parameters!$B$7),"",$G14*(1+$H14)^(2-1)) | AI14: =IF(OR($B14="",3>Parameters!$B$7),"",$G14*(1+$H14)^(3-1)) | AJ14: =IF(OR($B14="",4>Parameters!$B$7),"",$G14*(1+$H14)^(4-1)) | AK14: =IF(OR($B14="",5>Parameters!$B$7),"",$G14*(1+$H14)^(5-1))
M15: =IF($B15="","",$G15+$I15*$J15) | N15: =IF($B15="","",IF(Parameters!$B$7<=0,0,IF(ABS((1+$H15)/(1+Parameters!$B$10)-1)<0.000001,Parameters!$B$7*$G15/(1+Parameters!$B$10),$G15/(1+Parameters!$B$10)*(1-((1+$H15)/(1+Parameters!$B$10))^Parameters!$B$7)/(1-(1+$H15)/(1+Parameters!$B$10))))+IF(Parameters!$B$7<=0,0,IF(Parameters!$B$10=0,Parameters!$B$7*$I15*$J15,$I15*$J15*(1-(1/(1+Parameters!$B$10))^Parameters!$B$7)/Parameters!$B$10))) | O15: =IF(OR($B15="",1>Parameters!$B$7),"",$N15-AB15) | P15: =IF(OR($B15="",2>Parameters!$B$7),"",$N15-AC15) | Q15: =IF(OR($B15="",3>Parameters!$B$7),"",$N15-AD15) | R15: =IF(OR($B15="",4>Parameters!$B$7),"",$N15-AE15) | S15: =IF(OR($B15="",5>Parameters!$B$7),"",$N15-AF15) | T15: =IF($B15="","",IF(MAX($O15:$S15)<0,"Accept",MATCH(MAX($O15:$S15),$O15:$S15,0))) | U15: =IF($B15="","",MAX($O15:$S15)) | V15: =IF($B15="","",IF($F15>0,ROUND($O15/$F15,2),IF(N($O15)>0,Lists!$F$2,0))+IF($W15="Yes",Lists!$I$2,0)) | W15: =IF($B15="","",IF(COUNTIFS($L$2:$L$41,$A15,$E$2:$E$41,"Open",$A$2:$A$41,"<>"&$A15)>0,"Yes","No")) | X15: =IF($B15="","",IF($V15>=Lists!$F$2,"High",IF($V15>=Lists!$F$3,"Medium","Low"))) | Y15: =IF(OR($B15="",$E15<>"Open"),"",IF($L15="",(INDEX(Lists!$G$2:$G$4,MATCH($X15,Lists!$E$2:$E$4,0))*1000000000000-$U15-$H15),IFERROR(MAX((INDEX(Lists!$G$2:$G$4,MATCH($X15,Lists!$E$2:$E$4,0))*1000000000000-$U15-$H15),INDEX($Y$2:$Y$41,MATCH($L15,$A$2:$A$41,0))+1),(INDEX(Lists!$G$2:$G$4,MATCH($X15,Lists!$E$2:$E$4,0))*1000000000000-$U15-$H15)))) | Z15: =IF($Y15="","",RANK($Y15,$Y$2:$Y$41,1)+COUNTIF($Y$2:$Y15,$Y15)-1) | AA15: ="" | AB15: =IF(OR($B15="",1>Parameters!$B$7),"",IF(1<=0,0,IF(ABS((1+$H15)/(1+Parameters!$B$10)-1)<0.000001,1*$G15/(1+Parameters!$B$10),$G15/(1+Parameters!$B$10)*(1-((1+$H15)/(1+Parameters!$B$10))^1)/(1-(1+$H15)/(1+Parameters!$B$10))))+$F15/(1+Parameters!$B$10)^1+IF(1<=0,0,IF(Parameters!$B$10=0,1*$I15*$J15,$I15*$J15*(1-(1/(1+Parameters!$B$10))^1)/Parameters!$B$10))) | AC15: =IF(OR($B15="",2>Parameters!$B$7),"",IF(2<=0,0,IF(ABS((1+$H15)/(1+Parameters!$B$10)-1)<0.000001,2*$G15/(1+Parameters!$B$10),$G15/(1+Parameters!$B$10)*(1-((1+$H15)/(1+Parameters!$B$10))^2)/(1-(1+$H15)/(1+Parameters!$B$10))))+$F15/(1+Parameters!$B$10)^2+IF(2<=0,0,IF(Parameters!$B$10=0,2*$I15*$J15,$I15*$J15*(1-(1/(1+Parameters!$B$10))^2)/Parameters!$B$10))) | AD15: =IF(OR($B15="",3>Parameters!$B$7),"",IF(3<=0,0,IF(ABS((1+$H15)/(1+Parameters!$B$10)-1)<0.000001,3*$G15/(1+Parameters!$B$10),$G15/(1+Parameters!$B$10)*(1-((1+$H15)/(1+Parameters!$B$10))^3)/(1-(1+$H15)/(1+Parameters!$B$10))))+$F15/(1+Parameters!$B$10)^3+IF(3<=0,0,IF(Parameters!$B$10=0,3*$I15*$J15,$I15*$J15*(1-(1/(1+Parameters!$B$10))^3)/Parameters!$B$10))) | AE15: =IF(OR($B15="",4>Parameters!$B$7),"",IF(4<=0,0,IF(ABS((1+$H15)/(1+Parameters!$B$10)-1)<0.000001,4*$G15/(1+Parameters!$B$10),$G15/(1+Parameters!$B$10)*(1-((1+$H15)/(1+Parameters!$B$10))^4)/(1-(1+$H15)/(1+Parameters!$B$10))))+$F15/(1+Parameters!$B$10)^4+IF(4<=0,0,IF(Parameters!$B$10=0,4*$I15*$J15,$I15*$J15*(1-(1/(1+Parameters!$B$10))^4)/Parameters!$B$10))) | AF15: =IF(OR($B15="",5>Parameters!$B$7),"",IF(5<=0,0,IF(ABS((1+$H15)/(1+Parameters!$B$10)-1)<0.000001,5*$G15/(1+Parameters!$B$10),$G15/(1+Parameters!$B$10)*(1-((1+$H15)/(1+Parameters!$B$10))^5)/(1-(1+$H15)/(1+Parameters!$B$10))))+$F15/(1+Parameters!$B$10)^5+IF(5<=0,0,IF(Parameters!$B$10=0,5*$I15*$J15,$I15*$J15*(1-(1/(1+Parameters!$B$10))^5)/Parameters!$B$10))) | AG15: =IF(OR($B15="",1>Parameters!$B$7),"",$G15*(1+$H15)^(1-1)) | AH15: =IF(OR($B15="",2>Parameters!$B$7),"",$G15*(1+$H15)^(2-1)) | AI15: =IF(OR($B15="",3>Parameters!$B$7),"",$G15*(1+$H15)^(3-1)) | AJ15: =IF(OR($B15="",4>Parameters!$B$7),"",$G15*(1+$H15)^(4-1)) | AK15: =IF(OR($B15="",5>Parameters!$B$7),"",$G15*(1+$H15)^(5-1))
M16: =IF($B16="","",$G16+$I16*$J16) | N16: =IF($B16="","",IF(Parameters!$B$7<=0,0,IF(ABS((1+$H16)/(1+Parameters!$B$10)-1)<0.000001,Parameters!$B$7*$G16/(1+Parameters!$B$10),$G16/(1+Parameters!$B$10)*(1-((1+$H16)/(1+Parameters!$B$10))^Parameters!$B$7)/(1-(1+$H16)/(1+Parameters!$B$10))))+IF(Parameters!$B$7<=0,0,IF(Parameters!$B$10=0,Parameters!$B$7*$I16*$J16,$I16*$J16*(1-(1/(1+Parameters!$B$10))^Parameters!$B$7)/Parameters!$B$10))) | O16: =IF(OR($B16="",1>Parameters!$B$7),"",$N16-AB16) | P16: =IF(OR($B16="",2>Parameters!$B$7),"",$N16-AC16) | Q16: =IF(OR($B16="",3>Parameters!$B$7),"",$N16-AD16) | R16: =IF(OR($B16="",4>Parameters!$B$7),"",$N16-AE16) | S16: =IF(OR($B16="",5>Parameters!$B$7),"",$N16-AF16) | T16: =IF($B16="","",IF(MAX($O16:$S16)<0,"Accept",MATCH(MAX($O16:$S16),$O16:$S16,0))) | U16: =IF($B16="","",MAX($O16:$S16)) | V16: =IF($B16="","",IF($F16>0,ROUND($O16/$F16,2),IF(N($O16)>0,Lists!$F$2,0))+IF($W16="Yes",Lists!$I$2,0)) | W16: =IF($B16="","",IF(COUNTIFS($L$2:$L$41,$A16,$E$2:$E$41,"Open",$A$2:$A$41,"<>"&$A16)>0,"Yes","No")) | X16: =IF($B16="","",IF($V16>=Lists!$F$2,"High",IF($V16>=Lists!$F$3,"Medium","Low"))) | Y16: =IF(OR($B16="",$E16<>"Open"),"",IF($L16="",(INDEX(Lists!$G$2:$G$4,MATCH($X16,Lists!$E$2:$E$4,0))*1000000000000-$U16-$H16),IFERROR(MAX((INDEX(Lists!$G$2:$G$4,MATCH($X16,Lists!$E$2:$E$4,0))*1000000000000-$U16-$H16),INDEX($Y$2:$Y$41,MATCH($L16,$A$2:$A$41,0))+1),(INDEX(Lists!$G$2:$G$4,MATCH($X16,Lists!$E$2:$E$4,0))*1000000000000-$U16-$H16)))) | Z16: =IF($Y16="","",RANK($Y16,$Y$2:$Y$41,1)+COUNTIF($Y$2:$Y16,$Y16)-1) | AA16: ="" | AB16: =IF(OR($B16="",1>Parameters!$B$7),"",IF(1<=0,0,IF(ABS((1+$H16)/(1+Parameters!$B$10)-1)<0.000001,1*$G16/(1+Parameters!$B$10),$G16/(1+Parameters!$B$10)*(1-((1+$H16)/(1+Parameters!$B$10))^1)/(1-(1+$H16)/(1+Parameters!$B$10))))+$F16/(1+Parameters!$B$10)^1+IF(1<=0,0,IF(Parameters!$B$10=0,1*$I16*$J16,$I16*$J16*(1-(1/(1+Parameters!$B$10))^1)/Parameters!$B$10))) | AC16: =IF(OR($B16="",2>Parameters!$B$7),"",IF(2<=0,0,IF(ABS((1+$H16)/(1+Parameters!$B$10)-1)<0.000001,2*$G16/(1+Parameters!$B$10),$G16/(1+Parameters!$B$10)*(1-((1+$H16)/(1+Parameters!$B$10))^2)/(1-(1+$H16)/(1+Parameters!$B$10))))+$F16/(1+Parameters!$B$10)^2+IF(2<=0,0,IF(Parameters!$B$10=0,2*$I16*$J16,$I16*$J16*(1-(1/(1+Parameters!$B$10))^2)/Parameters!$B$10))) | AD16: =IF(OR($B16="",3>Parameters!$B$7),"",IF(3<=0,0,IF(ABS((1+$H16)/(1+Parameters!$B$10)-1)<0.000001,3*$G16/(1+Parameters!$B$10),$G16/(1+Parameters!$B$10)*(1-((1+$H16)/(1+Parameters!$B$10))^3)/(1-(1+$H16)/(1+Parameters!$B$10))))+$F16/(1+Parameters!$B$10)^3+IF(3<=0,0,IF(Parameters!$B$10=0,3*$I16*$J16,$I16*$J16*(1-(1/(1+Parameters!$B$10))^3)/Parameters!$B$10))) | AE16: =IF(OR($B16="",4>Parameters!$B$7),"",IF(4<=0,0,IF(ABS((1+$H16)/(1+Parameters!$B$10)-1)<0.000001,4*$G16/(1+Parameters!$B$10),$G16/(1+Parameters!$B$10)*(1-((1+$H16)/(1+Parameters!$B$10))^4)/(1-(1+$H16)/(1+Parameters!$B$10))))+$F16/(1+Parameters!$B$10)^4+IF(4<=0,0,IF(Parameters!$B$10=0,4*$I16*$J16,$I16*$J16*(1-(1/(1+Parameters!$B$10))^4)/Parameters!$B$10))) | AF16: =IF(OR($B16="",5>Parameters!$B$7),"",IF(5<=0,0,IF(ABS((1+$H16)/(1+Parameters!$B$10)-1)<0.000001,5*$G16/(1+Parameters!$B$10),$G16/(1+Parameters!$B$10)*(1-((1+$H16)/(1+Parameters!$B$10))^5)/(1-(1+$H16)/(1+Parameters!$B$10))))+$F16/(1+Parameters!$B$10)^5+IF(5<=0,0,IF(Parameters!$B$10=0,5*$I16*$J16,$I16*$J16*(1-(1/(1+Parameters!$B$10))^5)/Parameters!$B$10))) | AG16: =IF(OR($B16="",1>Parameters!$B$7),"",$G16*(1+$H16)^(1-1)) | AH16: =IF(OR($B16="",2>Parameters!$B$7),"",$G16*(1+$H16)^(2-1)) | AI16: =IF(OR($B16="",3>Parameters!$B$7),"",$G16*(1+$H16)^(3-1)) | AJ16: =IF(OR($B16="",4>Parameters!$B$7),"",$G16*(1+$H16)^(4-1)) | AK16: =IF(OR($B16="",5>Parameters!$B$7),"",$G16*(1+$H16)^(5-1))
M17: =IF($B17="","",$G17+$I17*$J17) | N17: =IF($B17="","",IF(Parameters!$B$7<=0,0,IF(ABS((1+$H17)/(1+Parameters!$B$10)-1)<0.000001,Parameters!$B$7*$G17/(1+Parameters!$B$10),$G17/(1+Parameters!$B$10)*(1-((1+$H17)/(1+Parameters!$B$10))^Parameters!$B$7)/(1-(1+$H17)/(1+Parameters!$B$10))))+IF(Parameters!$B$7<=0,0,IF(Parameters!$B$10=0,Parameters!$B$7*$I17*$J17,$I17*$J17*(1-(1/(1+Parameters!$B$10))^Parameters!$B$7)/Parameters!$B$10))) | O17: =IF(OR($B17="",1>Parameters!$B$7),"",$N17-AB17) | P17: =IF(OR($B17="",2>Parameters!$B$7),"",$N17-AC17) | Q17: =IF(OR($B17="",3>Parameters!$B$7),"",$N17-AD17) | R17: =IF(OR($B17="",4>Parameters!$B$7),"",$N17-AE17) | S17: =IF(OR($B17="",5>Parameters!$B$7),"",$N17-AF17) | T17: =IF($B17="","",IF(MAX($O17:$S17)<0,"Accept",MATCH(MAX($O17:$S17),$O17:$S17,0))) | U17: =IF($B17="","",MAX($O17:$S17)) | V17: =IF($B17="","",IF($F17>0,ROUND($O17/$F17,2),IF(N($O17)>0,Lists!$F$2,0))+IF($W17="Yes",Lists!$I$2,0)) | W17: =IF($B17="","",IF(COUNTIFS($L$2:$L$41,$A17,$E$2:$E$41,"Open",$A$2:$A$41,"<>"&$A17)>0,"Yes","No")) | X17: =IF($B17="","",IF($V17>=Lists!$F$2,"High",IF($V17>=Lists!$F$3,"Medium","Low"))) | Y17: =IF(OR($B17="",$E17<>"Open"),"",IF($L17="",(INDEX(Lists!$G$2:$G$4,MATCH($X17,Lists!$E$2:$E$4,0))*1000000000000-$U17-$H17),IFERROR(MAX((INDEX(Lists!$G$2:$G$4,MATCH($X17,Lists!$E$2:$E$4,0))*1000000000000-$U17-$H17),INDEX($Y$2:$Y$41,MATCH($L17,$A$2:$A$41,0))+1),(INDEX(Lists!$G$2:$G$4,MATCH($X17,Lists!$E$2:$E$4,0))*1000000000000-$U17-$H17)))) | Z17: =IF($Y17="","",RANK($Y17,$Y$2:$Y$41,1)+COUNTIF($Y$2:$Y17,$Y17)-1) | AA17: ="" | AB17: =IF(OR($B17="",1>Parameters!$B$7),"",IF(1<=0,0,IF(ABS((1+$H17)/(1+Parameters!$B$10)-1)<0.000001,1*$G17/(1+Parameters!$B$10),$G17/(1+Parameters!$B$10)*(1-((1+$H17)/(1+Parameters!$B$10))^1)/(1-(1+$H17)/(1+Parameters!$B$10))))+$F17/(1+Parameters!$B$10)^1+IF(1<=0,0,IF(Parameters!$B$10=0,1*$I17*$J17,$I17*$J17*(1-(1/(1+Parameters!$B$10))^1)/Parameters!$B$10))) | AC17: =IF(OR($B17="",2>Parameters!$B$7),"",IF(2<=0,0,IF(ABS((1+$H17)/(1+Parameters!$B$10)-1)<0.000001,2*$G17/(1+Parameters!$B$10),$G17/(1+Parameters!$B$10)*(1-((1+$H17)/(1+Parameters!$B$10))^2)/(1-(1+$H17)/(1+Parameters!$B$10))))+$F17/(1+Parameters!$B$10)^2+IF(2<=0,0,IF(Parameters!$B$10=0,2*$I17*$J17,$I17*$J17*(1-(1/(1+Parameters!$B$10))^2)/Parameters!$B$10))) | AD17: =IF(OR($B17="",3>Parameters!$B$7),"",IF(3<=0,0,IF(ABS((1+$H17)/(1+Parameters!$B$10)-1)<0.000001,3*$G17/(1+Parameters!$B$10),$G17/(1+Parameters!$B$10)*(1-((1+$H17)/(1+Parameters!$B$10))^3)/(1-(1+$H17)/(1+Parameters!$B$10))))+$F17/(1+Parameters!$B$10)^3+IF(3<=0,0,IF(Parameters!$B$10=0,3*$I17*$J17,$I17*$J17*(1-(1/(1+Parameters!$B$10))^3)/Parameters!$B$10))) | AE17: =IF(OR($B17="",4>Parameters!$B$7),"",IF(4<=0,0,IF(ABS((1+$H17)/(1+Parameters!$B$10)-1)<0.000001,4*$G17/(1+Parameters!$B$10),$G17/(1+Parameters!$B$10)*(1-((1+$H17)/(1+Parameters!$B$10))^4)/(1-(1+$H17)/(1+Parameters!$B$10))))+$F17/(1+Parameters!$B$10)^4+IF(4<=0,0,IF(Parameters!$B$10=0,4*$I17*$J17,$I17*$J17*(1-(1/(1+Parameters!$B$10))^4)/Parameters!$B$10))) | AF17: =IF(OR($B17="",5>Parameters!$B$7),"",IF(5<=0,0,IF(ABS((1+$H17)/(1+Parameters!$B$10)-1)<0.000001,5*$G17/(1+Parameters!$B$10),$G17/(1+Parameters!$B$10)*(1-((1+$H17)/(1+Parameters!$B$10))^5)/(1-(1+$H17)/(1+Parameters!$B$10))))+$F17/(1+Parameters!$B$10)^5+IF(5<=0,0,IF(Parameters!$B$10=0,5*$I17*$J17,$I17*$J17*(1-(1/(1+Parameters!$B$10))^5)/Parameters!$B$10))) | AG17: =IF(OR($B17="",1>Parameters!$B$7),"",$G17*(1+$H17)^(1-1)) | AH17: =IF(OR($B17="",2>Parameters!$B$7),"",$G17*(1+$H17)^(2-1)) | AI17: =IF(OR($B17="",3>Parameters!$B$7),"",$G17*(1+$H17)^(3-1)) | AJ17: =IF(OR($B17="",4>Parameters!$B$7),"",$G17*(1+$H17)^(4-1)) | AK17: =IF(OR($B17="",5>Parameters!$B$7),"",$G17*(1+$H17)^(5-1))
M18: =IF($B18="","",$G18+$I18*$J18) | N18: =IF($B18="","",IF(Parameters!$B$7<=0,0,IF(ABS((1+$H18)/(1+Parameters!$B$10)-1)<0.000001,Parameters!$B$7*$G18/(1+Parameters!$B$10),$G18/(1+Parameters!$B$10)*(1-((1+$H18)/(1+Parameters!$B$10))^Parameters!$B$7)/(1-(1+$H18)/(1+Parameters!$B$10))))+IF(Parameters!$B$7<=0,0,IF(Parameters!$B$10=0,Parameters!$B$7*$I18*$J18,$I18*$J18*(1-(1/(1+Parameters!$B$10))^Parameters!$B$7)/Parameters!$B$10))) | O18: =IF(OR($B18="",1>Parameters!$B$7),"",$N18-AB18) | P18: =IF(OR($B18="",2>Parameters!$B$7),"",$N18-AC18) | Q18: =IF(OR($B18="",3>Parameters!$B$7),"",$N18-AD18) | R18: =IF(OR($B18="",4>Parameters!$B$7),"",$N18-AE18) | S18: =IF(OR($B18="",5>Parameters!$B$7),"",$N18-AF18) | T18: =IF($B18="","",IF(MAX($O18:$S18)<0,"Accept",MATCH(MAX($O18:$S18),$O18:$S18,0))) | U18: =IF($B18="","",MAX($O18:$S18)) | V18: =IF($B18="","",IF($F18>0,ROUND($O18/$F18,2),IF(N($O18)>0,Lists!$F$2,0))+IF($W18="Yes",Lists!$I$2,0)) | W18: =IF($B18="","",IF(COUNTIFS($L$2:$L$41,$A18,$E$2:$E$41,"Open",$A$2:$A$41,"<>"&$A18)>0,"Yes","No")) | X18: =IF($B18="","",IF($V18>=Lists!$F$2,"High",IF($V18>=Lists!$F$3,"Medium","Low"))) | Y18: =IF(OR($B18="",$E18<>"Open"),"",IF($L18="",(INDEX(Lists!$G$2:$G$4,MATCH($X18,Lists!$E$2:$E$4,0))*1000000000000-$U18-$H18),IFERROR(MAX((INDEX(Lists!$G$2:$G$4,MATCH($X18,Lists!$E$2:$E$4,0))*1000000000000-$U18-$H18),INDEX($Y$2:$Y$41,MATCH($L18,$A$2:$A$41,0))+1),(INDEX(Lists!$G$2:$G$4,MATCH($X18,Lists!$E$2:$E$4,0))*1000000000000-$U18-$H18)))) | Z18: =IF($Y18="","",RANK($Y18,$Y$2:$Y$41,1)+COUNTIF($Y$2:$Y18,$Y18)-1) | AA18: ="" | AB18: =IF(OR($B18="",1>Parameters!$B$7),"",IF(1<=0,0,IF(ABS((1+$H18)/(1+Parameters!$B$10)-1)<0.000001,1*$G18/(1+Parameters!$B$10),$G18/(1+Parameters!$B$10)*(1-((1+$H18)/(1+Parameters!$B$10))^1)/(1-(1+$H18)/(1+Parameters!$B$10))))+$F18/(1+Parameters!$B$10)^1+IF(1<=0,0,IF(Parameters!$B$10=0,1*$I18*$J18,$I18*$J18*(1-(1/(1+Parameters!$B$10))^1)/Parameters!$B$10))) | AC18: =IF(OR($B18="",2>Parameters!$B$7),"",IF(2<=0,0,IF(ABS((1+$H18)/(1+Parameters!$B$10)-1)<0.000001,2*$G18/(1+Parameters!$B$10),$G18/(1+Parameters!$B$10)*(1-((1+$H18)/(1+Parameters!$B$10))^2)/(1-(1+$H18)/(1+Parameters!$B$10))))+$F18/(1+Parameters!$B$10)^2+IF(2<=0,0,IF(Parameters!$B$10=0,2*$I18*$J18,$I18*$J18*(1-(1/(1+Parameters!$B$10))^2)/Parameters!$B$10))) | AD18: =IF(OR($B18="",3>Parameters!$B$7),"",IF(3<=0,0,IF(ABS((1+$H18)/(1+Parameters!$B$10)-1)<0.000001,3*$G18/(1+Parameters!$B$10),$G18/(1+Parameters!$B$10)*(1-((1+$H18)/(1+Parameters!$B$10))^3)/(1-(1+$H18)/(1+Parameters!$B$10))))+$F18/(1+Parameters!$B$10)^3+IF(3<=0,0,IF(Parameters!$B$10=0,3*$I18*$J18,$I18*$J18*(1-(1/(1+Parameters!$B$10))^3)/Parameters!$B$10))) | AE18: =IF(OR($B18="",4>Parameters!$B$7),"",IF(4<=0,0,IF(ABS((1+$H18)/(1+Parameters!$B$10)-1)<0.000001,4*$G18/(1+Parameters!$B$10),$G18/(1+Parameters!$B$10)*(1-((1+$H18)/(1+Parameters!$B$10))^4)/(1-(1+$H18)/(1+Parameters!$B$10))))+$F18/(1+Parameters!$B$10)^4+IF(4<=0,0,IF(Parameters!$B$10=0,4*$I18*$J18,$I18*$J18*(1-(1/(1+Parameters!$B$10))^4)/Parameters!$B$10))) | AF18: =IF(OR($B18="",5>Parameters!$B$7),"",IF(5<=0,0,IF(ABS((1+$H18)/(1+Parameters!$B$10)-1)<0.000001,5*$G18/(1+Parameters!$B$10),$G18/(1+Parameters!$B$10)*(1-((1+$H18)/(1+Parameters!$B$10))^5)/(1-(1+$H18)/(1+Parameters!$B$10))))+$F18/(1+Parameters!$B$10)^5+IF(5<=0,0,IF(Parameters!$B$10=0,5*$I18*$J18,$I18*$J18*(1-(1/(1+Parameters!$B$10))^5)/Parameters!$B$10))) | AG18: =IF(OR($B18="",1>Parameters!$B$7),"",$G18*(1+$H18)^(1-1)) | AH18: =IF(OR($B18="",2>Parameters!$B$7),"",$G18*(1+$H18)^(2-1)) | AI18: =IF(OR($B18="",3>Parameters!$B$7),"",$G18*(1+$H18)^(3-1)) | AJ18: =IF(OR($B18="",4>Parameters!$B$7),"",$G18*(1+$H18)^(4-1)) | AK18: =IF(OR($B18="",5>Parameters!$B$7),"",$G18*(1+$H18)^(5-1))
M19: =IF($B19="","",$G19+$I19*$J19) | N19: =IF($B19="","",IF(Parameters!$B$7<=0,0,IF(ABS((1+$H19)/(1+Parameters!$B$10)-1)<0.000001,Parameters!$B$7*$G19/(1+Parameters!$B$10),$G19/(1+Parameters!$B$10)*(1-((1+$H19)/(1+Parameters!$B$10))^Parameters!$B$7)/(1-(1+$H19)/(1+Parameters!$B$10))))+IF(Parameters!$B$7<=0,0,IF(Parameters!$B$10=0,Parameters!$B$7*$I19*$J19,$I19*$J19*(1-(1/(1+Parameters!$B$10))^Parameters!$B$7)/Parameters!$B$10))) | O19: =IF(OR($B19="",1>Parameters!$B$7),"",$N19-AB19) | P19: =IF(OR($B19="",2>Parameters!$B$7),"",$N19-AC19) | Q19: =IF(OR($B19="",3>Parameters!$B$7),"",$N19-AD19) | R19: =IF(OR($B19="",4>Parameters!$B$7),"",$N19-AE19) | S19: =IF(OR($B19="",5>Parameters!$B$7),"",$N19-AF19) | T19: =IF($B19="","",IF(MAX($O19:$S19)<0,"Accept",MATCH(MAX($O19:$S19),$O19:$S19,0))) | U19: =IF($B19="","",MAX($O19:$S19)) | V19: =IF($B19="","",IF($F19>0,ROUND($O19/$F19,2),IF(N($O19)>0,Lists!$F$2,0))+IF($W19="Yes",Lists!$I$2,0)) | W19: =IF($B19="","",IF(COUNTIFS($L$2:$L$41,$A19,$E$2:$E$41,"Open",$A$2:$A$41,"<>"&$A19)>0,"Yes","No")) | X19: =IF($B19="","",IF($V19>=Lists!$F$2,"High",IF($V19>=Lists!$F$3,"Medium","Low"))) | Y19: =IF(OR($B19="",$E19<>"Open"),"",IF($L19="",(INDEX(Lists!$G$2:$G$4,MATCH($X19,Lists!$E$2:$E$4,0))*1000000000000-$U19-$H19),IFERROR(MAX((INDEX(Lists!$G$2:$G$4,MATCH($X19,Lists!$E$2:$E$4,0))*1000000000000-$U19-$H19),INDEX($Y$2:$Y$41,MATCH($L19,$A$2:$A$41,0))+1),(INDEX(Lists!$G$2:$G$4,MATCH($X19,Lists!$E$2:$E$4,0))*1000000000000-$U19-$H19)))) | Z19: =IF($Y19="","",RANK($Y19,$Y$2:$Y$41,1)+COUNTIF($Y$2:$Y19,$Y19)-1) | AA19: ="" | AB19: =IF(OR($B19="",1>Parameters!$B$7),"",IF(1<=0,0,IF(ABS((1+$H19)/(1+Parameters!$B$10)-1)<0.000001,1*$G19/(1+Parameters!$B$10),$G19/(1+Parameters!$B$10)*(1-((1+$H19)/(1+Parameters!$B$10))^1)/(1-(1+$H19)/(1+Parameters!$B$10))))+$F19/(1+Parameters!$B$10)^1+IF(1<=0,0,IF(Parameters!$B$10=0,1*$I19*$J19,$I19*$J19*(1-(1/(1+Parameters!$B$10))^1)/Parameters!$B$10))) | AC19: =IF(OR($B19="",2>Parameters!$B$7),"",IF(2<=0,0,IF(ABS((1+$H19)/(1+Parameters!$B$10)-1)<0.000001,2*$G19/(1+Parameters!$B$10),$G19/(1+Parameters!$B$10)*(1-((1+$H19)/(1+Parameters!$B$10))^2)/(1-(1+$H19)/(1+Parameters!$B$10))))+$F19/(1+Parameters!$B$10)^2+IF(2<=0,0,IF(Parameters!$B$10=0,2*$I19*$J19,$I19*$J19*(1-(1/(1+Parameters!$B$10))^2)/Parameters!$B$10))) | AD19: =IF(OR($B19="",3>Parameters!$B$7),"",IF(3<=0,0,IF(ABS((1+$H19)/(1+Parameters!$B$10)-1)<0.000001,3*$G19/(1+Parameters!$B$10),$G19/(1+Parameters!$B$10)*(1-((1+$H19)/(1+Parameters!$B$10))^3)/(1-(1+$H19)/(1+Parameters!$B$10))))+$F19/(1+Parameters!$B$10)^3+IF(3<=0,0,IF(Parameters!$B$10=0,3*$I19*$J19,$I19*$J19*(1-(1/(1+Parameters!$B$10))^3)/Parameters!$B$10))) | AE19: =IF(OR($B19="",4>Parameters!$B$7),"",IF(4<=0,0,IF(ABS((1+$H19)/(1+Parameters!$B$10)-1)<0.000001,4*$G19/(1+Parameters!$B$10),$G19/(1+Parameters!$B$10)*(1-((1+$H19)/(1+Parameters!$B$10))^4)/(1-(1+$H19)/(1+Parameters!$B$10))))+$F19/(1+Parameters!$B$10)^4+IF(4<=0,0,IF(Parameters!$B$10=0,4*$I19*$J19,$I19*$J19*(1-(1/(1+Parameters!$B$10))^4)/Parameters!$B$10))) | AF19: =IF(OR($B19="",5>Parameters!$B$7),"",IF(5<=0,0,IF(ABS((1+$H19)/(1+Parameters!$B$10)-1)<0.000001,5*$G19/(1+Parameters!$B$10),$G19/(1+Parameters!$B$10)*(1-((1+$H19)/(1+Parameters!$B$10))^5)/(1-(1+$H19)/(1+Parameters!$B$10))))+$F19/(1+Parameters!$B$10)^5+IF(5<=0,0,IF(Parameters!$B$10=0,5*$I19*$J19,$I19*$J19*(1-(1/(1+Parameters!$B$10))^5)/Parameters!$B$10))) | AG19: =IF(OR($B19="",1>Parameters!$B$7),"",$G19*(1+$H19)^(1-1)) | AH19: =IF(OR($B19="",2>Parameters!$B$7),"",$G19*(1+$H19)^(2-1)) | AI19: =IF(OR($B19="",3>Parameters!$B$7),"",$G19*(1+$H19)^(3-1)) | AJ19: =IF(OR($B19="",4>Parameters!$B$7),"",$G19*(1+$H19)^(4-1)) | AK19: =IF(OR($B19="",5>Parameters!$B$7),"",$G19*(1+$H19)^(5-1))
M20: =IF($B20="","",$G20+$I20*$J20) | N20: =IF($B20="","",IF(Parameters!$B$7<=0,0,IF(ABS((1+$H20)/(1+Parameters!$B$10)-1)<0.000001,Parameters!$B$7*$G20/(1+Parameters!$B$10),$G20/(1+Parameters!$B$10)*(1-((1+$H20)/(1+Parameters!$B$10))^Parameters!$B$7)/(1-(1+$H20)/(1+Parameters!$B$10))))+IF(Parameters!$B$7<=0,0,IF(Parameters!$B$10=0,Parameters!$B$7*$I20*$J20,$I20*$J20*(1-(1/(1+Parameters!$B$10))^Parameters!$B$7)/Parameters!$B$10))) | O20: =IF(OR($B20="",1>Parameters!$B$7),"",$N20-AB20) | P20: =IF(OR($B20="",2>Parameters!$B$7),"",$N20-AC20) | Q20: =IF(OR($B20="",3>Parameters!$B$7),"",$N20-AD20) | R20: =IF(OR($B20="",4>Parameters!$B$7),"",$N20-AE20) | S20: =IF(OR($B20="",5>Parameters!$B$7),"",$N20-AF20) | T20: =IF($B20="","",IF(MAX($O20:$S20)<0,"Accept",MATCH(MAX($O20:$S20),$O20:$S20,0))) | U20: =IF($B20="","",MAX($O20:$S20)) | V20: =IF($B20="","",IF($F20>0,ROUND($O20/$F20,2),IF(N($O20)>0,Lists!$F$2,0))+IF($W20="Yes",Lists!$I$2,0)) | W20: =IF($B20="","",IF(COUNTIFS($L$2:$L$41,$A20,$E$2:$E$41,"Open",$A$2:$A$41,"<>"&$A20)>0,"Yes","No")) | X20: =IF($B20="","",IF($V20>=Lists!$F$2,"High",IF($V20>=Lists!$F$3,"Medium","Low"))) | Y20: =IF(OR($B20="",$E20<>"Open"),"",IF($L20="",(INDEX(Lists!$G$2:$G$4,MATCH($X20,Lists!$E$2:$E$4,0))*1000000000000-$U20-$H20),IFERROR(MAX((INDEX(Lists!$G$2:$G$4,MATCH($X20,Lists!$E$2:$E$4,0))*1000000000000-$U20-$H20),INDEX($Y$2:$Y$41,MATCH($L20,$A$2:$A$41,0))+1),(INDEX(Lists!$G$2:$G$4,MATCH($X20,Lists!$E$2:$E$4,0))*1000000000000-$U20-$H20)))) | Z20: =IF($Y20="","",RANK($Y20,$Y$2:$Y$41,1)+COUNTIF($Y$2:$Y20,$Y20)-1) | AA20: ="" | AB20: =IF(OR($B20="",1>Parameters!$B$7),"",IF(1<=0,0,IF(ABS((1+$H20)/(1+Parameters!$B$10)-1)<0.000001,1*$G20/(1+Parameters!$B$10),$G20/(1+Parameters!$B$10)*(1-((1+$H20)/(1+Parameters!$B$10))^1)/(1-(1+$H20)/(1+Parameters!$B$10))))+$F20/(1+Parameters!$B$10)^1+IF(1<=0,0,IF(Parameters!$B$10=0,1*$I20*$J20,$I20*$J20*(1-(1/(1+Parameters!$B$10))^1)/Parameters!$B$10))) | AC20: =IF(OR($B20="",2>Parameters!$B$7),"",IF(2<=0,0,IF(ABS((1+$H20)/(1+Parameters!$B$10)-1)<0.000001,2*$G20/(1+Parameters!$B$10),$G20/(1+Parameters!$B$10)*(1-((1+$H20)/(1+Parameters!$B$10))^2)/(1-(1+$H20)/(1+Parameters!$B$10))))+$F20/(1+Parameters!$B$10)^2+IF(2<=0,0,IF(Parameters!$B$10=0,2*$I20*$J20,$I20*$J20*(1-(1/(1+Parameters!$B$10))^2)/Parameters!$B$10))) | AD20: =IF(OR($B20="",3>Parameters!$B$7),"",IF(3<=0,0,IF(ABS((1+$H20)/(1+Parameters!$B$10)-1)<0.000001,3*$G20/(1+Parameters!$B$10),$G20/(1+Parameters!$B$10)*(1-((1+$H20)/(1+Parameters!$B$10))^3)/(1-(1+$H20)/(1+Parameters!$B$10))))+$F20/(1+Parameters!$B$10)^3+IF(3<=0,0,IF(Parameters!$B$10=0,3*$I20*$J20,$I20*$J20*(1-(1/(1+Parameters!$B$10))^3)/Parameters!$B$10))) | AE20: =IF(OR($B20="",4>Parameters!$B$7),"",IF(4<=0,0,IF(ABS((1+$H20)/(1+Parameters!$B$10)-1)<0.000001,4*$G20/(1+Parameters!$B$10),$G20/(1+Parameters!$B$10)*(1-((1+$H20)/(1+Parameters!$B$10))^4)/(1-(1+$H20)/(1+Parameters!$B$10))))+$F20/(1+Parameters!$B$10)^4+IF(4<=0,0,IF(Parameters!$B$10=0,4*$I20*$J20,$I20*$J20*(1-(1/(1+Parameters!$B$10))^4)/Parameters!$B$10))) | AF20: =IF(OR($B20="",5>Parameters!$B$7),"",IF(5<=0,0,IF(ABS((1+$H20)/(1+Parameters!$B$10)-1)<0.000001,5*$G20/(1+Parameters!$B$10),$G20/(1+Parameters!$B$10)*(1-((1+$H20)/(1+Parameters!$B$10))^5)/(1-(1+$H20)/(1+Parameters!$B$10))))+$F20/(1+Parameters!$B$10)^5+IF(5<=0,0,IF(Parameters!$B$10=0,5*$I20*$J20,$I20*$J20*(1-(1/(1+Parameters!$B$10))^5)/Parameters!$B$10))) | AG20: =IF(OR($B20="",1>Parameters!$B$7),"",$G20*(1+$H20)^(1-1)) | AH20: =IF(OR($B20="",2>Parameters!$B$7),"",$G20*(1+$H20)^(2-1)) | AI20: =IF(OR($B20="",3>Parameters!$B$7),"",$G20*(1+$H20)^(3-1)) | AJ20: =IF(OR($B20="",4>Parameters!$B$7),"",$G20*(1+$H20)^(4-1)) | AK20: =IF(OR($B20="",5>Parameters!$B$7),"",$G20*(1+$H20)^(5-1))
M21: =IF($B21="","",$G21+$I21*$J21) | N21: =IF($B21="","",IF(Parameters!$B$7<=0,0,IF(ABS((1+$H21)/(1+Parameters!$B$10)-1)<0.000001,Parameters!$B$7*$G21/(1+Parameters!$B$10),$G21/(1+Parameters!$B$10)*(1-((1+$H21)/(1+Parameters!$B$10))^Parameters!$B$7)/(1-(1+$H21)/(1+Parameters!$B$10))))+IF(Parameters!$B$7<=0,0,IF(Parameters!$B$10=0,Parameters!$B$7*$I21*$J21,$I21*$J21*(1-(1/(1+Parameters!$B$10))^Parameters!$B$7)/Parameters!$B$10))) | O21: =IF(OR($B21="",1>Parameters!$B$7),"",$N21-AB21) | P21: =IF(OR($B21="",2>Parameters!$B$7),"",$N21-AC21) | Q21: =IF(OR($B21="",3>Parameters!$B$7),"",$N21-AD21) | R21: =IF(OR($B21="",4>Parameters!$B$7),"",$N21-AE21) | S21: =IF(OR($B21="",5>Parameters!$B$7),"",$N21-AF21) | T21: =IF($B21="","",IF(MAX($O21:$S21)<0,"Accept",MATCH(MAX($O21:$S21),$O21:$S21,0))) | U21: =IF($B21="","",MAX($O21:$S21)) | V21: =IF($B21="","",IF($F21>0,ROUND($O21/$F21,2),IF(N($O21)>0,Lists!$F$2,0))+IF($W21="Yes",Lists!$I$2,0)) | W21: =IF($B21="","",IF(COUNTIFS($L$2:$L$41,$A21,$E$2:$E$41,"Open",$A$2:$A$41,"<>"&$A21)>0,"Yes","No")) | X21: =IF($B21="","",IF($V21>=Lists!$F$2,"High",IF($V21>=Lists!$F$3,"Medium","Low"))) | Y21: =IF(OR($B21="",$E21<>"Open"),"",IF($L21="",(INDEX(Lists!$G$2:$G$4,MATCH($X21,Lists!$E$2:$E$4,0))*1000000000000-$U21-$H21),IFERROR(MAX((INDEX(Lists!$G$2:$G$4,MATCH($X21,Lists!$E$2:$E$4,0))*1000000000000-$U21-$H21),INDEX($Y$2:$Y$41,MATCH($L21,$A$2:$A$41,0))+1),(INDEX(Lists!$G$2:$G$4,MATCH($X21,Lists!$E$2:$E$4,0))*1000000000000-$U21-$H21)))) | Z21: =IF($Y21="","",RANK($Y21,$Y$2:$Y$41,1)+COUNTIF($Y$2:$Y21,$Y21)-1) | AA21: ="" | AB21: =IF(OR($B21="",1>Parameters!$B$7),"",IF(1<=0,0,IF(ABS((1+$H21)/(1+Parameters!$B$10)-1)<0.000001,1*$G21/(1+Parameters!$B$10),$G21/(1+Parameters!$B$10)*(1-((1+$H21)/(1+Parameters!$B$10))^1)/(1-(1+$H21)/(1+Parameters!$B$10))))+$F21/(1+Parameters!$B$10)^1+IF(1<=0,0,IF(Parameters!$B$10=0,1*$I21*$J21,$I21*$J21*(1-(1/(1+Parameters!$B$10))^1)/Parameters!$B$10))) | AC21: =IF(OR($B21="",2>Parameters!$B$7),"",IF(2<=0,0,IF(ABS((1+$H21)/(1+Parameters!$B$10)-1)<0.000001,2*$G21/(1+Parameters!$B$10),$G21/(1+Parameters!$B$10)*(1-((1+$H21)/(1+Parameters!$B$10))^2)/(1-(1+$H21)/(1+Parameters!$B$10))))+$F21/(1+Parameters!$B$10)^2+IF(2<=0,0,IF(Parameters!$B$10=0,2*$I21*$J21,$I21*$J21*(1-(1/(1+Parameters!$B$10))^2)/Parameters!$B$10))) | AD21: =IF(OR($B21="",3>Parameters!$B$7),"",IF(3<=0,0,IF(ABS((1+$H21)/(1+Parameters!$B$10)-1)<0.000001,3*$G21/(1+Parameters!$B$10),$G21/(1+Parameters!$B$10)*(1-((1+$H21)/(1+Parameters!$B$10))^3)/(1-(1+$H21)/(1+Parameters!$B$10))))+$F21/(1+Parameters!$B$10)^3+IF(3<=0,0,IF(Parameters!$B$10=0,3*$I21*$J21,$I21*$J21*(1-(1/(1+Parameters!$B$10))^3)/Parameters!$B$10))) | AE21: =IF(OR($B21="",4>Parameters!$B$7),"",IF(4<=0,0,IF(ABS((1+$H21)/(1+Parameters!$B$10)-1)<0.000001,4*$G21/(1+Parameters!$B$10),$G21/(1+Parameters!$B$10)*(1-((1+$H21)/(1+Parameters!$B$10))^4)/(1-(1+$H21)/(1+Parameters!$B$10))))+$F21/(1+Parameters!$B$10)^4+IF(4<=0,0,IF(Parameters!$B$10=0,4*$I21*$J21,$I21*$J21*(1-(1/(1+Parameters!$B$10))^4)/Parameters!$B$10))) | AF21: =IF(OR($B21="",5>Parameters!$B$7),"",IF(5<=0,0,IF(ABS((1+$H21)/(1+Parameters!$B$10)-1)<0.000001,5*$G21/(1+Parameters!$B$10),$G21/(1+Parameters!$B$10)*(1-((1+$H21)/(1+Parameters!$B$10))^5)/(1-(1+$H21)/(1+Parameters!$B$10))))+$F21/(1+Parameters!$B$10)^5+IF(5<=0,0,IF(Parameters!$B$10=0,5*$I21*$J21,$I21*$J21*(1-(1/(1+Parameters!$B$10))^5)/Parameters!$B$10))) | AG21: =IF(OR($B21="",1>Parameters!$B$7),"",$G21*(1+$H21)^(1-1)) | AH21: =IF(OR($B21="",2>Parameters!$B$7),"",$G21*(1+$H21)^(2-1)) | AI21: =IF(OR($B21="",3>Parameters!$B$7),"",$G21*(1+$H21)^(3-1)) | AJ21: =IF(OR($B21="",4>Parameters!$B$7),"",$G21*(1+$H21)^(4-1)) | AK21: =IF(OR($B21="",5>Parameters!$B$7),"",$G21*(1+$H21)^(5-1))
M22: =IF($B22="","",$G22+$I22*$J22) | N22: =IF($B22="","",IF(Parameters!$B$7<=0,0,IF(ABS((1+$H22)/(1+Parameters!$B$10)-1)<0.000001,Parameters!$B$7*$G22/(1+Parameters!$B$10),$G22/(1+Parameters!$B$10)*(1-((1+$H22)/(1+Parameters!$B$10))^Parameters!$B$7)/(1-(1+$H22)/(1+Parameters!$B$10))))+IF(Parameters!$B$7<=0,0,IF(Parameters!$B$10=0,Parameters!$B$7*$I22*$J22,$I22*$J22*(1-(1/(1+Parameters!$B$10))^Parameters!$B$7)/Parameters!$B$10))) | O22: =IF(OR($B22="",1>Parameters!$B$7),"",$N22-AB22) | P22: =IF(OR($B22="",2>Parameters!$B$7),"",$N22-AC22) | Q22: =IF(OR($B22="",3>Parameters!$B$7),"",$N22-AD22) | R22: =IF(OR($B22="",4>Parameters!$B$7),"",$N22-AE22) | S22: =IF(OR($B22="",5>Parameters!$B$7),"",$N22-AF22) | T22: =IF($B22="","",IF(MAX($O22:$S22)<0,"Accept",MATCH(MAX($O22:$S22),$O22:$S22,0))) | U22: =IF($B22="","",MAX($O22:$S22)) | V22: =IF($B22="","",IF($F22>0,ROUND($O22/$F22,2),IF(N($O22)>0,Lists!$F$2,0))+IF($W22="Yes",Lists!$I$2,0)) | W22: =IF($B22="","",IF(COUNTIFS($L$2:$L$41,$A22,$E$2:$E$41,"Open",$A$2:$A$41,"<>"&$A22)>0,"Yes","No")) | X22: =IF($B22="","",IF($V22>=Lists!$F$2,"High",IF($V22>=Lists!$F$3,"Medium","Low"))) | Y22: =IF(OR($B22="",$E22<>"Open"),"",IF($L22="",(INDEX(Lists!$G$2:$G$4,MATCH($X22,Lists!$E$2:$E$4,0))*1000000000000-$U22-$H22),IFERROR(MAX((INDEX(Lists!$G$2:$G$4,MATCH($X22,Lists!$E$2:$E$4,0))*1000000000000-$U22-$H22),INDEX($Y$2:$Y$41,MATCH($L22,$A$2:$A$41,0))+1),(INDEX(Lists!$G$2:$G$4,MATCH($X22,Lists!$E$2:$E$4,0))*1000000000000-$U22-$H22)))) | Z22: =IF($Y22="","",RANK($Y22,$Y$2:$Y$41,1)+COUNTIF($Y$2:$Y22,$Y22)-1) | AA22: ="" | AB22: =IF(OR($B22="",1>Parameters!$B$7),"",IF(1<=0,0,IF(ABS((1+$H22)/(1+Parameters!$B$10)-1)<0.000001,1*$G22/(1+Parameters!$B$10),$G22/(1+Parameters!$B$10)*(1-((1+$H22)/(1+Parameters!$B$10))^1)/(1-(1+$H22)/(1+Parameters!$B$10))))+$F22/(1+Parameters!$B$10)^1+IF(1<=0,0,IF(Parameters!$B$10=0,1*$I22*$J22,$I22*$J22*(1-(1/(1+Parameters!$B$10))^1)/Parameters!$B$10))) | AC22: =IF(OR($B22="",2>Parameters!$B$7),"",IF(2<=0,0,IF(ABS((1+$H22)/(1+Parameters!$B$10)-1)<0.000001,2*$G22/(1+Parameters!$B$10),$G22/(1+Parameters!$B$10)*(1-((1+$H22)/(1+Parameters!$B$10))^2)/(1-(1+$H22)/(1+Parameters!$B$10))))+$F22/(1+Parameters!$B$10)^2+IF(2<=0,0,IF(Parameters!$B$10=0,2*$I22*$J22,$I22*$J22*(1-(1/(1+Parameters!$B$10))^2)/Parameters!$B$10))) | AD22: =IF(OR($B22="",3>Parameters!$B$7),"",IF(3<=0,0,IF(ABS((1+$H22)/(1+Parameters!$B$10)-1)<0.000001,3*$G22/(1+Parameters!$B$10),$G22/(1+Parameters!$B$10)*(1-((1+$H22)/(1+Parameters!$B$10))^3)/(1-(1+$H22)/(1+Parameters!$B$10))))+$F22/(1+Parameters!$B$10)^3+IF(3<=0,0,IF(Parameters!$B$10=0,3*$I22*$J22,$I22*$J22*(1-(1/(1+Parameters!$B$10))^3)/Parameters!$B$10))) | AE22: =IF(OR($B22="",4>Parameters!$B$7),"",IF(4<=0,0,IF(ABS((1+$H22)/(1+Parameters!$B$10)-1)<0.000001,4*$G22/(1+Parameters!$B$10),$G22/(1+Parameters!$B$10)*(1-((1+$H22)/(1+Parameters!$B$10))^4)/(1-(1+$H22)/(1+Parameters!$B$10))))+$F22/(1+Parameters!$B$10)^4+IF(4<=0,0,IF(Parameters!$B$10=0,4*$I22*$J22,$I22*$J22*(1-(1/(1+Parameters!$B$10))^4)/Parameters!$B$10))) | AF22: =IF(OR($B22="",5>Parameters!$B$7),"",IF(5<=0,0,IF(ABS((1+$H22)/(1+Parameters!$B$10)-1)<0.000001,5*$G22/(1+Parameters!$B$10),$G22/(1+Parameters!$B$10)*(1-((1+$H22)/(1+Parameters!$B$10))^5)/(1-(1+$H22)/(1+Parameters!$B$10))))+$F22/(1+Parameters!$B$10)^5+IF(5<=0,0,IF(Parameters!$B$10=0,5*$I22*$J22,$I22*$J22*(1-(1/(1+Parameters!$B$10))^5)/Parameters!$B$10))) | AG22: =IF(OR($B22="",1>Parameters!$B$7),"",$G22*(1+$H22)^(1-1)) | AH22: =IF(OR($B22="",2>Parameters!$B$7),"",$G22*(1+$H22)^(2-1)) | AI22: =IF(OR($B22="",3>Parameters!$B$7),"",$G22*(1+$H22)^(3-1)) | AJ22: =IF(OR($B22="",4>Parameters!$B$7),"",$G22*(1+$H22)^(4-1)) | AK22: =IF(OR($B22="",5>Parameters!$B$7),"",$G22*(1+$H22)^(5-1))
M23: =IF($B23="","",$G23+$I23*$J23) | N23: =IF($B23="","",IF(Parameters!$B$7<=0,0,IF(ABS((1+$H23)/(1+Parameters!$B$10)-1)<0.000001,Parameters!$B$7*$G23/(1+Parameters!$B$10),$G23/(1+Parameters!$B$10)*(1-((1+$H23)/(1+Parameters!$B$10))^Parameters!$B$7)/(1-(1+$H23)/(1+Parameters!$B$10))))+IF(Parameters!$B$7<=0,0,IF(Parameters!$B$10=0,Parameters!$B$7*$I23*$J23,$I23*$J23*(1-(1/(1+Parameters!$B$10))^Parameters!$B$7)/Parameters!$B$10))) | O23: =IF(OR($B23="",1>Parameters!$B$7),"",$N23-AB23) | P23: =IF(OR($B23="",2>Parameters!$B$7),"",$N23-AC23) | Q23: =IF(OR($B23="",3>Parameters!$B$7),"",$N23-AD23) | R23: =IF(OR($B23="",4>Parameters!$B$7),"",$N23-AE23) | S23: =IF(OR($B23="",5>Parameters!$B$7),"",$N23-AF23) | T23: =IF($B23="","",IF(MAX($O23:$S23)<0,"Accept",MATCH(MAX($O23:$S23),$O23:$S23,0))) | U23: =IF($B23="","",MAX($O23:$S23)) | V23: =IF($B23="","",IF($F23>0,ROUND($O23/$F23,2),IF(N($O23)>0,Lists!$F$2,0))+IF($W23="Yes",Lists!$I$2,0)) | W23: =IF($B23="","",IF(COUNTIFS($L$2:$L$41,$A23,$E$2:$E$41,"Open",$A$2:$A$41,"<>"&$A23)>0,"Yes","No")) | X23: =IF($B23="","",IF($V23>=Lists!$F$2,"High",IF($V23>=Lists!$F$3,"Medium","Low"))) | Y23: =IF(OR($B23="",$E23<>"Open"),"",IF($L23="",(INDEX(Lists!$G$2:$G$4,MATCH($X23,Lists!$E$2:$E$4,0))*1000000000000-$U23-$H23),IFERROR(MAX((INDEX(Lists!$G$2:$G$4,MATCH($X23,Lists!$E$2:$E$4,0))*1000000000000-$U23-$H23),INDEX($Y$2:$Y$41,MATCH($L23,$A$2:$A$41,0))+1),(INDEX(Lists!$G$2:$G$4,MATCH($X23,Lists!$E$2:$E$4,0))*1000000000000-$U23-$H23)))) | Z23: =IF($Y23="","",RANK($Y23,$Y$2:$Y$41,1)+COUNTIF($Y$2:$Y23,$Y23)-1) | AA23: ="" | AB23: =IF(OR($B23="",1>Parameters!$B$7),"",IF(1<=0,0,IF(ABS((1+$H23)/(1+Parameters!$B$10)-1)<0.000001,1*$G23/(1+Parameters!$B$10),$G23/(1+Parameters!$B$10)*(1-((1+$H23)/(1+Parameters!$B$10))^1)/(1-(1+$H23)/(1+Parameters!$B$10))))+$F23/(1+Parameters!$B$10)^1+IF(1<=0,0,IF(Parameters!$B$10=0,1*$I23*$J23,$I23*$J23*(1-(1/(1+Parameters!$B$10))^1)/Parameters!$B$10))) | AC23: =IF(OR($B23="",2>Parameters!$B$7),"",IF(2<=0,0,IF(ABS((1+$H23)/(1+Parameters!$B$10)-1)<0.000001,2*$G23/(1+Parameters!$B$10),$G23/(1+Parameters!$B$10)*(1-((1+$H23)/(1+Parameters!$B$10))^2)/(1-(1+$H23)/(1+Parameters!$B$10))))+$F23/(1+Parameters!$B$10)^2+IF(2<=0,0,IF(Parameters!$B$10=0,2*$I23*$J23,$I23*$J23*(1-(1/(1+Parameters!$B$10))^2)/Parameters!$B$10))) | AD23: =IF(OR($B23="",3>Parameters!$B$7),"",IF(3<=0,0,IF(ABS((1+$H23)/(1+Parameters!$B$10)-1)<0.000001,3*$G23/(1+Parameters!$B$10),$G23/(1+Parameters!$B$10)*(1-((1+$H23)/(1+Parameters!$B$10))^3)/(1-(1+$H23)/(1+Parameters!$B$10))))+$F23/(1+Parameters!$B$10)^3+IF(3<=0,0,IF(Parameters!$B$10=0,3*$I23*$J23,$I23*$J23*(1-(1/(1+Parameters!$B$10))^3)/Parameters!$B$10))) | AE23: =IF(OR($B23="",4>Parameters!$B$7),"",IF(4<=0,0,IF(ABS((1+$H23)/(1+Parameters!$B$10)-1)<0.000001,4*$G23/(1+Parameters!$B$10),$G23/(1+Parameters!$B$10)*(1-((1+$H23)/(1+Parameters!$B$10))^4)/(1-(1+$H23)/(1+Parameters!$B$10))))+$F23/(1+Parameters!$B$10)^4+IF(4<=0,0,IF(Parameters!$B$10=0,4*$I23*$J23,$I23*$J23*(1-(1/(1+Parameters!$B$10))^4)/Parameters!$B$10))) | AF23: =IF(OR($B23="",5>Parameters!$B$7),"",IF(5<=0,0,IF(ABS((1+$H23)/(1+Parameters!$B$10)-1)<0.000001,5*$G23/(1+Parameters!$B$10),$G23/(1+Parameters!$B$10)*(1-((1+$H23)/(1+Parameters!$B$10))^5)/(1-(1+$H23)/(1+Parameters!$B$10))))+$F23/(1+Parameters!$B$10)^5+IF(5<=0,0,IF(Parameters!$B$10=0,5*$I23*$J23,$I23*$J23*(1-(1/(1+Parameters!$B$10))^5)/Parameters!$B$10))) | AG23: =IF(OR($B23="",1>Parameters!$B$7),"",$G23*(1+$H23)^(1-1)) | AH23: =IF(OR($B23="",2>Parameters!$B$7),"",$G23*(1+$H23)^(2-1)) | AI23: =IF(OR($B23="",3>Parameters!$B$7),"",$G23*(1+$H23)^(3-1)) | AJ23: =IF(OR($B23="",4>Parameters!$B$7),"",$G23*(1+$H23)^(4-1)) | AK23: =IF(OR($B23="",5>Parameters!$B$7),"",$G23*(1+$H23)^(5-1))
M24: =IF($B24="","",$G24+$I24*$J24) | N24: =IF($B24="","",IF(Parameters!$B$7<=0,0,IF(ABS((1+$H24)/(1+Parameters!$B$10)-1)<0.000001,Parameters!$B$7*$G24/(1+Parameters!$B$10),$G24/(1+Parameters!$B$10)*(1-((1+$H24)/(1+Parameters!$B$10))^Parameters!$B$7)/(1-(1+$H24)/(1+Parameters!$B$10))))+IF(Parameters!$B$7<=0,0,IF(Parameters!$B$10=0,Parameters!$B$7*$I24*$J24,$I24*$J24*(1-(1/(1+Parameters!$B$10))^Parameters!$B$7)/Parameters!$B$10))) | O24: =IF(OR($B24="",1>Parameters!$B$7),"",$N24-AB24) | P24: =IF(OR($B24="",2>Parameters!$B$7),"",$N24-AC24) | Q24: =IF(OR($B24="",3>Parameters!$B$7),"",$N24-AD24) | R24: =IF(OR($B24="",4>Parameters!$B$7),"",$N24-AE24) | S24: =IF(OR($B24="",5>Parameters!$B$7),"",$N24-AF24) | T24: =IF($B24="","",IF(MAX($O24:$S24)<0,"Accept",MATCH(MAX($O24:$S24),$O24:$S24,0))) | U24: =IF($B24="","",MAX($O24:$S24)) | V24: =IF($B24="","",IF($F24>0,ROUND($O24/$F24,2),IF(N($O24)>0,Lists!$F$2,0))+IF($W24="Yes",Lists!$I$2,0)) | W24: =IF($B24="","",IF(COUNTIFS($L$2:$L$41,$A24,$E$2:$E$41,"Open",$A$2:$A$41,"<>"&$A24)>0,"Yes","No")) | X24: =IF($B24="","",IF($V24>=Lists!$F$2,"High",IF($V24>=Lists!$F$3,"Medium","Low"))) | Y24: =IF(OR($B24="",$E24<>"Open"),"",IF($L24="",(INDEX(Lists!$G$2:$G$4,MATCH($X24,Lists!$E$2:$E$4,0))*1000000000000-$U24-$H24),IFERROR(MAX((INDEX(Lists!$G$2:$G$4,MATCH($X24,Lists!$E$2:$E$4,0))*1000000000000-$U24-$H24),INDEX($Y$2:$Y$41,MATCH($L24,$A$2:$A$41,0))+1),(INDEX(Lists!$G$2:$G$4,MATCH($X24,Lists!$E$2:$E$4,0))*1000000000000-$U24-$H24)))) | Z24: =IF($Y24="","",RANK($Y24,$Y$2:$Y$41,1)+COUNTIF($Y$2:$Y24,$Y24)-1) | AA24: ="" | AB24: =IF(OR($B24="",1>Parameters!$B$7),"",IF(1<=0,0,IF(ABS((1+$H24)/(1+Parameters!$B$10)-1)<0.000001,1*$G24/(1+Parameters!$B$10),$G24/(1+Parameters!$B$10)*(1-((1+$H24)/(1+Parameters!$B$10))^1)/(1-(1+$H24)/(1+Parameters!$B$10))))+$F24/(1+Parameters!$B$10)^1+IF(1<=0,0,IF(Parameters!$B$10=0,1*$I24*$J24,$I24*$J24*(1-(1/(1+Parameters!$B$10))^1)/Parameters!$B$10))) | AC24: =IF(OR($B24="",2>Parameters!$B$7),"",IF(2<=0,0,IF(ABS((1+$H24)/(1+Parameters!$B$10)-1)<0.000001,2*$G24/(1+Parameters!$B$10),$G24/(1+Parameters!$B$10)*(1-((1+$H24)/(1+Parameters!$B$10))^2)/(1-(1+$H24)/(1+Parameters!$B$10))))+$F24/(1+Parameters!$B$10)^2+IF(2<=0,0,IF(Parameters!$B$10=0,2*$I24*$J24,$I24*$J24*(1-(1/(1+Parameters!$B$10))^2)/Parameters!$B$10))) | AD24: =IF(OR($B24="",3>Parameters!$B$7),"",IF(3<=0,0,IF(ABS((1+$H24)/(1+Parameters!$B$10)-1)<0.000001,3*$G24/(1+Parameters!$B$10),$G24/(1+Parameters!$B$10)*(1-((1+$H24)/(1+Parameters!$B$10))^3)/(1-(1+$H24)/(1+Parameters!$B$10))))+$F24/(1+Parameters!$B$10)^3+IF(3<=0,0,IF(Parameters!$B$10=0,3*$I24*$J24,$I24*$J24*(1-(1/(1+Parameters!$B$10))^3)/Parameters!$B$10))) | AE24: =IF(OR($B24="",4>Parameters!$B$7),"",IF(4<=0,0,IF(ABS((1+$H24)/(1+Parameters!$B$10)-1)<0.000001,4*$G24/(1+Parameters!$B$10),$G24/(1+Parameters!$B$10)*(1-((1+$H24)/(1+Parameters!$B$10))^4)/(1-(1+$H24)/(1+Parameters!$B$10))))+$F24/(1+Parameters!$B$10)^4+IF(4<=0,0,IF(Parameters!$B$10=0,4*$I24*$J24,$I24*$J24*(1-(1/(1+Parameters!$B$10))^4)/Parameters!$B$10))) | AF24: =IF(OR($B24="",5>Parameters!$B$7),"",IF(5<=0,0,IF(ABS((1+$H24)/(1+Parameters!$B$10)-1)<0.000001,5*$G24/(1+Parameters!$B$10),$G24/(1+Parameters!$B$10)*(1-((1+$H24)/(1+Parameters!$B$10))^5)/(1-(1+$H24)/(1+Parameters!$B$10))))+$F24/(1+Parameters!$B$10)^5+IF(5<=0,0,IF(Parameters!$B$10=0,5*$I24*$J24,$I24*$J24*(1-(1/(1+Parameters!$B$10))^5)/Parameters!$B$10))) | AG24: =IF(OR($B24="",1>Parameters!$B$7),"",$G24*(1+$H24)^(1-1)) | AH24: =IF(OR($B24="",2>Parameters!$B$7),"",$G24*(1+$H24)^(2-1)) | AI24: =IF(OR($B24="",3>Parameters!$B$7),"",$G24*(1+$H24)^(3-1)) | AJ24: =IF(OR($B24="",4>Parameters!$B$7),"",$G24*(1+$H24)^(4-1)) | AK24: =IF(OR($B24="",5>Parameters!$B$7),"",$G24*(1+$H24)^(5-1))
M25: =IF($B25="","",$G25+$I25*$J25) | N25: =IF($B25="","",IF(Parameters!$B$7<=0,0,IF(ABS((1+$H25)/(1+Parameters!$B$10)-1)<0.000001,Parameters!$B$7*$G25/(1+Parameters!$B$10),$G25/(1+Parameters!$B$10)*(1-((1+$H25)/(1+Parameters!$B$10))^Parameters!$B$7)/(1-(1+$H25)/(1+Parameters!$B$10))))+IF(Parameters!$B$7<=0,0,IF(Parameters!$B$10=0,Parameters!$B$7*$I25*$J25,$I25*$J25*(1-(1/(1+Parameters!$B$10))^Parameters!$B$7)/Parameters!$B$10))) | O25: =IF(OR($B25="",1>Parameters!$B$7),"",$N25-AB25) | P25: =IF(OR($B25="",2>Parameters!$B$7),"",$N25-AC25) | Q25: =IF(OR($B25="",3>Parameters!$B$7),"",$N25-AD25) | R25: =IF(OR($B25="",4>Parameters!$B$7),"",$N25-AE25) | S25: =IF(OR($B25="",5>Parameters!$B$7),"",$N25-AF25) | T25: =IF($B25="","",IF(MAX($O25:$S25)<0,"Accept",MATCH(MAX($O25:$S25),$O25:$S25,0))) | U25: =IF($B25="","",MAX($O25:$S25)) | V25: =IF($B25="","",IF($F25>0,ROUND($O25/$F25,2),IF(N($O25)>0,Lists!$F$2,0))+IF($W25="Yes",Lists!$I$2,0)) | W25: =IF($B25="","",IF(COUNTIFS($L$2:$L$41,$A25,$E$2:$E$41,"Open",$A$2:$A$41,"<>"&$A25)>0,"Yes","No")) | X25: =IF($B25="","",IF($V25>=Lists!$F$2,"High",IF($V25>=Lists!$F$3,"Medium","Low"))) | Y25: =IF(OR($B25="",$E25<>"Open"),"",IF($L25="",(INDEX(Lists!$G$2:$G$4,MATCH($X25,Lists!$E$2:$E$4,0))*1000000000000-$U25-$H25),IFERROR(MAX((INDEX(Lists!$G$2:$G$4,MATCH($X25,Lists!$E$2:$E$4,0))*1000000000000-$U25-$H25),INDEX($Y$2:$Y$41,MATCH($L25,$A$2:$A$41,0))+1),(INDEX(Lists!$G$2:$G$4,MATCH($X25,Lists!$E$2:$E$4,0))*1000000000000-$U25-$H25)))) | Z25: =IF($Y25="","",RANK($Y25,$Y$2:$Y$41,1)+COUNTIF($Y$2:$Y25,$Y25)-1) | AA25: ="" | AB25: =IF(OR($B25="",1>Parameters!$B$7),"",IF(1<=0,0,IF(ABS((1+$H25)/(1+Parameters!$B$10)-1)<0.000001,1*$G25/(1+Parameters!$B$10),$G25/(1+Parameters!$B$10)*(1-((1+$H25)/(1+Parameters!$B$10))^1)/(1-(1+$H25)/(1+Parameters!$B$10))))+$F25/(1+Parameters!$B$10)^1+IF(1<=0,0,IF(Parameters!$B$10=0,1*$I25*$J25,$I25*$J25*(1-(1/(1+Parameters!$B$10))^1)/Parameters!$B$10))) | AC25: =IF(OR($B25="",2>Parameters!$B$7),"",IF(2<=0,0,IF(ABS((1+$H25)/(1+Parameters!$B$10)-1)<0.000001,2*$G25/(1+Parameters!$B$10),$G25/(1+Parameters!$B$10)*(1-((1+$H25)/(1+Parameters!$B$10))^2)/(1-(1+$H25)/(1+Parameters!$B$10))))+$F25/(1+Parameters!$B$10)^2+IF(2<=0,0,IF(Parameters!$B$10=0,2*$I25*$J25,$I25*$J25*(1-(1/(1+Parameters!$B$10))^2)/Parameters!$B$10))) | AD25: =IF(OR($B25="",3>Parameters!$B$7),"",IF(3<=0,0,IF(ABS((1+$H25)/(1+Parameters!$B$10)-1)<0.000001,3*$G25/(1+Parameters!$B$10),$G25/(1+Parameters!$B$10)*(1-((1+$H25)/(1+Parameters!$B$10))^3)/(1-(1+$H25)/(1+Parameters!$B$10))))+$F25/(1+Parameters!$B$10)^3+IF(3<=0,0,IF(Parameters!$B$10=0,3*$I25*$J25,$I25*$J25*(1-(1/(1+Parameters!$B$10))^3)/Parameters!$B$10))) | AE25: =IF(OR($B25="",4>Parameters!$B$7),"",IF(4<=0,0,IF(ABS((1+$H25)/(1+Parameters!$B$10)-1)<0.000001,4*$G25/(1+Parameters!$B$10),$G25/(1+Parameters!$B$10)*(1-((1+$H25)/(1+Parameters!$B$10))^4)/(1-(1+$H25)/(1+Parameters!$B$10))))+$F25/(1+Parameters!$B$10)^4+IF(4<=0,0,IF(Parameters!$B$10=0,4*$I25*$J25,$I25*$J25*(1-(1/(1+Parameters!$B$10))^4)/Parameters!$B$10))) | AF25: =IF(OR($B25="",5>Parameters!$B$7),"",IF(5<=0,0,IF(ABS((1+$H25)/(1+Parameters!$B$10)-1)<0.000001,5*$G25/(1+Parameters!$B$10),$G25/(1+Parameters!$B$10)*(1-((1+$H25)/(1+Parameters!$B$10))^5)/(1-(1+$H25)/(1+Parameters!$B$10))))+$F25/(1+Parameters!$B$10)^5+IF(5<=0,0,IF(Parameters!$B$10=0,5*$I25*$J25,$I25*$J25*(1-(1/(1+Parameters!$B$10))^5)/Parameters!$B$10))) | AG25: =IF(OR($B25="",1>Parameters!$B$7),"",$G25*(1+$H25)^(1-1)) | AH25: =IF(OR($B25="",2>Parameters!$B$7),"",$G25*(1+$H25)^(2-1)) | AI25: =IF(OR($B25="",3>Parameters!$B$7),"",$G25*(1+$H25)^(3-1)) | AJ25: =IF(OR($B25="",4>Parameters!$B$7),"",$G25*(1+$H25)^(4-1)) | AK25: =IF(OR($B25="",5>Parameters!$B$7),"",$G25*(1+$H25)^(5-1))
... M41: =IF($B41="","",$G41+$I41*$J41) | N41: =IF($B41="","",IF(Parameters!$B$7<=0,0,IF(ABS((1+$H41)/(1+Parameters!$B$10)-1)<0.000001,Parameters!$B$7*$G41/(1+Parameters!$B$10),$G41/(1+Parameters!$B$10)*(1-((1+$H41)/(1+Parameters!$B$10))^Parameters!$B$7)/(1-(1+$H41)/(1+Parameters!$B$10))))+IF(Parameters!$B$7<=0,0,IF(Parameters!$B$10=0,Parameters!$B$7*$I41*$J41,$I41*$J41*(1-(1/(1+Parameters!$B$10))^Parameters!$B$7)/Parameters!$B$10))) | O41: =IF(OR($B41="",1>Parameters!$B$7),"",$N41-AB41) | P41: =IF(OR($B41="",2>Parameters!$B$7),"",$N41-AC41) | Q41: =IF(OR($B41="",3>Parameters!$B$7),"",$N41-AD41) | R41: =IF(OR($B41="",4>Parameters!$B$7),"",$N41-AE41) | S41: =IF(OR($B41="",5>Parameters!$B$7),"",$N41-AF41) | T41: =IF($B41="","",IF(MAX($O41:$S41)<0,"Accept",MATCH(MAX($O41:$S41),$O41:$S41,0))) | U41: =IF($B41="","",MAX($O41:$S41)) | V41: =IF($B41="","",IF($F41>0,ROUND($O41/$F41,2),IF(N($O41)>0,Lists!$F$2,0))+IF($W41="Yes",Lists!$I$2,0)) | W41: =IF($B41="","",IF(COUNTIFS($L$2:$L$41,$A41,$E$2:$E$41,"Open",$A$2:$A$41,"<>"&$A41)>0,"Yes","No")) | X41: =IF($B41="","",IF($V41>=Lists!$F$2,"High",IF($V41>=Lists!$F$3,"Medium","Low"))) | Y41: =IF(OR($B41="",$E41<>"Open"),"",IF($L41="",(INDEX(Lists!$G$2:$G$4,MATCH($X41,Lists!$E$2:$E$4,0))*1000000000000-$U41-$H41),IFERROR(MAX((INDEX(Lists!$G$2:$G$4,MATCH($X41,Lists!$E$2:$E$4,0))*1000000000000-$U41-$H41),INDEX($Y$2:$Y$41,MATCH($L41,$A$2:$A$41,0))+1),(INDEX(Lists!$G$2:$G$4,MATCH($X41,Lists!$E$2:$E$4,0))*1000000000000-$U41-$H41)))) | Z41: =IF($Y41="","",RANK($Y41,$Y$2:$Y$41,1)+COUNTIF($Y$2:$Y41,$Y41)-1) | AA41: ="" | AB41: =IF(OR($B41="",1>Parameters!$B$7),"",IF(1<=0,0,IF(ABS((1+$H41)/(1+Parameters!$B$10)-1)<0.000001,1*$G41/(1+Parameters!$B$10),$G41/(1+Parameters!$B$10)*(1-((1+$H41)/(1+Parameters!$B$10))^1)/(1-(1+$H41)/(1+Parameters!$B$10))))+$F41/(1+Parameters!$B$10)^1+IF(1<=0,0,IF(Parameters!$B$10=0,1*$I41*$J41,$I41*$J41*(1-(1/(1+Parameters!$B$10))^1)/Parameters!$B$10))) | AC41: =IF(OR($B41="",2>Parameters!$B$7),"",IF(2<=0,0,IF(ABS((1+$H41)/(1+Parameters!$B$10)-1)<0.000001,2*$G41/(1+Parameters!$B$10),$G41/(1+Parameters!$B$10)*(1-((1+$H41)/(1+Parameters!$B$10))^2)/(1-(1+$H41)/(1+Parameters!$B$10))))+$F41/(1+Parameters!$B$10)^2+IF(2<=0,0,IF(Parameters!$B$10=0,2*$I41*$J41,$I41*$J41*(1-(1/(1+Parameters!$B$10))^2)/Parameters!$B$10))) | AD41: =IF(OR($B41="",3>Parameters!$B$7),"",IF(3<=0,0,IF(ABS((1+$H41)/(1+Parameters!$B$10)-1)<0.000001,3*$G41/(1+Parameters!$B$10),$G41/(1+Parameters!$B$10)*(1-((1+$H41)/(1+Parameters!$B$10))^3)/(1-(1+$H41)/(1+Parameters!$B$10))))+$F41/(1+Parameters!$B$10)^3+IF(3<=0,0,IF(Parameters!$B$10=0,3*$I41*$J41,$I41*$J41*(1-(1/(1+Parameters!$B$10))^3)/Parameters!$B$10))) | AE41: =IF(OR($B41="",4>Parameters!$B$7),"",IF(4<=0,0,IF(ABS((1+$H41)/(1+Parameters!$B$10)-1)<0.000001,4*$G41/(1+Parameters!$B$10),$G41/(1+Parameters!$B$10)*(1-((1+$H41)/(1+Parameters!$B$10))^4)/(1-(1+$H41)/(1+Parameters!$B$10))))+$F41/(1+Parameters!$B$10)^4+IF(4<=0,0,IF(Parameters!$B$10=0,4*$I41*$J41,$I41*$J41*(1-(1/(1+Parameters!$B$10))^4)/Parameters!$B$10))) | AF41: =IF(OR($B41="",5>Parameters!$B$7),"",IF(5<=0,0,IF(ABS((1+$H41)/(1+Parameters!$B$10)-1)<0.000001,5*$G41/(1+Parameters!$B$10),$G41/(1+Parameters!$B$10)*(1-((1+$H41)/(1+Parameters!$B$10))^5)/(1-(1+$H41)/(1+Parameters!$B$10))))+$F41/(1+Parameters!$B$10)^5+IF(5<=0,0,IF(Parameters!$B$10=0,5*$I41*$J41,$I41*$J41*(1-(1/(1+Parameters!$B$10))^5)/Parameters!$B$10))) | AG41: =IF(OR($B41="",1>Parameters!$B$7),"",$G41*(1+$H41)^(1-1)) | AH41: =IF(OR($B41="",2>Parameters!$B$7),"",$G41*(1+$H41)^(2-1)) | AI41: =IF(OR($B41="",3>Parameters!$B$7),"",$G41*(1+$H41)^(3-1)) | AJ41: =IF(OR($B41="",4>Parameters!$B$7),"",$G41*(1+$H41)^(4-1)) | AK41: =IF(OR($B41="",5>Parameters!$B$7),"",$G41*(1+$H41)^(5-1))
